Workbook

Sheet LMStudio
A1: tablescraper-selected-row href | B1: text-lg | D1: text-muted-foreground | E1: font-medium | F1: font-medium 2 | G1: font-medium 3 | H1: opacity-70 | I1: shadow-sm | J1: shadow-sm 3 | K1: shadow-sm 5 | L1: shadow-sm 6
A2: URL | B2: Model | D2: Description | E2: Number of Downloads | F2: Stars | G2: Box | H2: Updates
A3: https://lmstudio.ai/models/nemotron-3-omni | B3: Nemotron 3 Omni | C3: =VLOOKUP(B3,'Unique LMStudio'!A$4:G1001,4,false) | D3: NVIDIA Nemotron 3 Nano Omni is an open multimodal model with highest efficiency that powers sub-agents to complete tasks faster across vision, audio, and language | E3: 32.9K | F3: 7 | H3: Updated 2 days ago | I3: 30B
A4: https://lmstudio.ai/models/qwen3.6 | B4: Qwen3.6 | C4: =VLOOKUP(B4,'Unique LMStudio'!A$4:G1001,4,false) -> https://llm-stats.com/models/qwen3.6-plus | D4: Qwen3.6 prioritizes stability and real-world utility, offering developers a more intuitive, responsive, and genuinely productive coding experience. | E4: 763.3K | F4: 45 | G4: 2 | H4: Updated 2 days ago | I4: 27B | J4: 35B
A5: https://lmstudio.ai/models/gemma-4 | B5: Gemma 4 | C5: =VLOOKUP(B5,'Unique LMStudio'!A$4:G1001,4,false) -> https://llm-stats.com/models/gemma-4-e4b-it | D5: Gemma 4 is Google's most capable family of open models, built from Gemini 3 research. Supports vision input and available in multiple sizes for on-device deployment. | E5: 3.2M | F5: 571 | G5: 4 | H5: Updated 24 days ago | I5: 5.1B | J5: 7.9B | K5: 26B | L5: 31B
A6: https://lmstudio.ai/models/nemotron-3-super | B6: Nemotron 3 Super | C6: =VLOOKUP(B6,'Unique LMStudio'!A$4:G1001,4,false) -> https://llm-stats.com/models/nemotron-3-super-120b-a12b | D6: NVIDIA Nemotron 3 Super, a 120B open hybrid MoE model (12B active), supporting up to 1M tokens context window | E6: 149.3K | F6: 41 | H6: Updated 1 month ago | I6: 120B
A7: https://lmstudio.ai/models/qwen3.5 | B7: Qwen3.5 | C7: =VLOOKUP(B7,'Unique LMStudio'!A$4:G1001,4,false) -> https://llm-stats.com/models/qwen3.5-2b | D7: Qwen3.5 represents a significant leap forward, integrating breakthroughs in multimodal learning, architectural efficiency, reinforcement learning scale, and global accessibility to empower developers and enterprises with unprecedented capability and efficiency | E7: 2.7M | F7: 265 | G7: 5 | H7: Updated 1 month ago | I7: 2B | J7: 4B | K7: 9B | L7: 27B
A8: https://lmstudio.ai/models/lfm2-24b-a2b | B8: LFM2-24B-A2B | C8: =VLOOKUP(B8,'Unique LMStudio'!A$4:G1001,4,false) | D8: LFM2 is a family of hybrid models designed for on-device deployment. LFM2-24B-A2B is the largest model in the family, scaling the architecture to 24 billion parameters while keeping inference efficient. | E8: 76.2K | F8: 15 | H8: Updated 2 months ago | I8: 24B
A9: https://lmstudio.ai/models/qwen3-coder-next | B9: Qwen3-Coder-Next | C9: =VLOOKUP(B9,'Unique LMStudio'!A$4:G1001,4,false) -> https://llm-stats.com/models/qwen3-coder-480b-a35b-instruct | D9: Qwen3 Coder Next is an 80B MoE with 3B active parameters designed for coding agents and local development. Excels at long-horizon reasoning, complex tool usage, and recovery from execution failures. | E9: 272.6K | F9: 77 | H9: Updated 2 months ago | I9: 80B
A10: https://lmstudio.ai/models/glm-4.7 | B10: GLM-4.7 | C10: =VLOOKUP(B10,'Unique LMStudio'!A$4:G1001,4,false) -> https://llm-stats.com/models/glm-4.7 | D10: Open source coding models by Z.ai, based on a new base model and specializing in coding and tool calling. | E10: 307.3K | F10: 105 | H10: Updated 3 months ago | I10: 30B
A11: https://lmstudio.ai/models/functiongemma | B11: FunctionGemma | C11: =VLOOKUP(B11,'Unique LMStudio'!A$4:G1001,4,false) -> https://huggingface.co/google/functiongemma-270m-it | D11: FunctionGemma is a lightweight, open model from Google, built as a foundation for creating your own specialized function calling models. | E11: 2.8K | F11: 44 | H11: Updated 4 months ago | I11: 270M
A12: https://lmstudio.ai/models/nemotron-3 | B12: Nemotron 3 | C12: =VLOOKUP(B12,'Unique LMStudio'!A$4:G1001,4,false) -> https://llm-stats.com/models/nemotron-3-nano-30b-a3b | D12: General purpose reasoning and chat model trained from scratch by NVIDIA. Contains 30B total parameters with only 3.5B active at a time for low-latency MoE inference | E12: 153.3K | F12: 58 | H12: Updated 4 months ago | I12: 30B
A13: https://lmstudio.ai/models/glm-4.6v-flash | B13: GLM-4.6V-Flash | C13: =VLOOKUP(B13,'Unique LMStudio'!A$4:G1001,4,false) -> https://llm-stats.com/models/glm-4.6 | D13: GLM 4.6V Flash is a 9B vision-language model optimized for local deployment and low-latency applications. | E13: 286.4K | F13: 59 | H13: Updated 4 months ago | I13: 9B
A14: https://lmstudio.ai/models/devstral-2 | B14: Devstral 2 | C14: =VLOOKUP(B14,'Unique LMStudio'!A$4:G1001,4,false) -> https://llm-stats.com/models/devstral-small-2507 | D14: Second-generation Devstral for agentic coding. Built for tool use to explore codebases, edit multiple files, and power software engineering agents with newly added vision support. | E14: 183.6K | F14: 60 | G14: 2 | H14: Updated 4 months ago | I14: 24B | J14: 123B
A15: https://lmstudio.ai/models/rnj-1 | B15: Rnj-1 | C15: =VLOOKUP(B15,'Unique LMStudio'!A$4:G1001,4,false) | D15: Rnj-1 is a family of 8B parameter open-weight, dense models trained from scratch by Essential AI. | E15: 63.3K | F15: 19 | H15: Updated 4 months ago | I15: 8B
A16: https://lmstudio.ai/models/ministral | B16: Ministral 3 | C16: =VLOOKUP(B16,'Unique LMStudio'!A$4:G1001,4,false) -> https://llm-stats.com/models/ministral-3-8b-base-2512 | D16: Ministral 3 series, available in three model sizes: 3B, 8B, and 14B parameters. Provides best of class cost-to-performance ratio. | E16: 544.1K | F16: 112 | G16: 6 | H16: Updated 4 months ago | I16: 3B | J16: 3B | K16: 8B | L16: 8B
A17: https://lmstudio.ai/models/qwen3-next | B17: Qwen3 Next | C17: =VLOOKUP(B17,'Unique LMStudio'!A$4:G1001,4,false) -> https://llm-stats.com/models/qwen3-next-80b-a3b-base | D17: Hybrid attention architecture, high-sparsity Mixture-of-Experts 80B model (active 3B). | E17: 57K | F17: 29 | H17: Updated 5 months ago | I17: 80B
A18: https://lmstudio.ai/models/olmo3 | B18: Olmo 3 | C18: =VLOOKUP(B18,'Unique LMStudio'!A$4:G1001,4,false) | D18: Olmo 3 is a family of Open language models designed to enable the science of language models. | E18: 37.8K | F18: 29 | G18: 3 | H18: Updated 5 months ago | I18: 7B | J18: 7B | K18: 32B
A19: https://lmstudio.ai/models/olmocr2 | B19: olmOCR 2 | C19: =VLOOKUP(B19,'Unique LMStudio'!A$4:G1001,4,false) | D19: The olmOCR 2 model is a Vision Language Model (VLM) from Allen AI. | E19: 70.5K | F19: 19 | H19: Updated 5 months ago | I19: 7B
A20: https://lmstudio.ai/models/minimax-m2 | B20: minimax-m2 | C20: =VLOOKUP(B20,'Unique LMStudio'!A$4:G1001,4,false) | D20: MiniMax M2 is a 230B MoE (10B active) model built for coding and agentic workflows | E20: 17.4K | F20: 37 | H20: Updated 5 months ago | I20: 230B
A21: https://lmstudio.ai/models/gpt-oss-safeguard | B21: gpt-oss-safeguard | C21: =VLOOKUP(B21,'Unique LMStudio'!A$4:G1001,4,false) -> https://llm-stats.com/models/gpt-oss-20b | D21: gpt-oss-safeguard-20b and gpt-oss-safeguard-120b are open safety models from OpenAI, building on gpt-oss. Trained to help classify text content based on customizable policies. | E21: 8K | F21: 36 | G21: 2 | H21: Updated 6 months ago | I21: 20B | J21: 120B
A22: https://lmstudio.ai/models/qwen3-vl | B22: Qwen3-VL | C22: =VLOOKUP(B22,'Unique LMStudio'!A$4:G1001,4,false) -> https://llm-stats.com/models/qwen3-vl-4b-instruct | D22: Qwen's latest vision-language model. Includes comprehensive upgrades to visual perception, spatial reasoning, and image understanding. | E22: 763.5K | F22: 128 | G22: 5 | H22: Updated 6 months ago | I22: 2B | J22: 4B | K22: 8B | L22: 30B
A23: https://lmstudio.ai/models/granite-4 | B23: Granite 4.0 | C23: =VLOOKUP(B23,'Unique LMStudio'!A$4:G1001,4,false) | D23: Granite 4.0 language models are lightweight, state-of-the-art open models that natively support multilingual capabilities, coding tasks, RAG, tool use, and JSON output. | E23: 72.4K | F23: 51 | G23: 4 | H23: Updated 6 months ago | I23: 3B | J23: 3B | K23: 7B | L23: 32B
A24: https://lmstudio.ai/models/seed-oss | B24: seed-oss | C24: =VLOOKUP(B24,'Unique LMStudio'!A$4:G1001,4,false) | D24: Advanced reasoning model from ByteDance with flexible "thinking budget" control and ability to reflect on the length of its own reasoning | E24: 54.1K | F24: 23 | H24: Updated 6 months ago | I24: 36B
A25: https://lmstudio.ai/models/qwen3 | B25: Qwen3 | C25: =VLOOKUP(B25,'Unique LMStudio'!A$4:G1001,4,false) -> https://llm-stats.com/models/qwen3-32b | D25: The latest version of the Qwen3 model family, featuring 4B, 30B, and 235B dense and MoE models, both thinking and non-thinking variants. | E25: 480.1K | F25: 178 | G25: 6 | H25: Updated 6 months ago | I25: 4B | J25: 4B | K25: 30B | L25: 30B
A26: https://lmstudio.ai/models/gpt-oss | B26: gpt-oss | C26: =VLOOKUP(B26,'Unique LMStudio'!A$4:G1001,4,false) -> https://llm-stats.com/models/gpt-oss-20b | D26: OpenAI's first open source LLM. Comes in 2 sizes: 20B and 120B. Supports configurable reasoning effort (low, medium, high). Trained for tool use. Apache 2.0 licensed. | E26: 1.7M | F26: 348 | G26: 2 | H26: Updated 6 months ago | I26: 20B | J26: 120B
A27: https://lmstudio.ai/models/qwen3-coder | B27: Qwen3-Coder | C27: =VLOOKUP(B27,'Unique LMStudio'!A$4:G1001,4,false) -> https://llm-stats.com/models/qwen3-coder | D27: State-of-the-art, Mixture-of-Experts local coding model with native support for 256K context length. Available in 30B (3B active) and 480B (35B active) sizes. | E27: 395.3K | F27: 146 | G27: 2 | H27: Updated 6 months ago | I27: 30B | J27: 480B
A28: https://lmstudio.ai/models/ernie-4.5 | B28: Ernie-4.5 | C28: =VLOOKUP(B28,'Unique LMStudio'!A$4:G1001,4,false) | D28: Medium-size Mixture-of-Experts model from Baidu's new Ernie 4.5 line of foundation models. | E28: 21.4K | F28: 12 | H28: Updated 6 months ago | I28: 21B
A29: https://lmstudio.ai/models/lfm2 | B29: LFM2 | C29: =VLOOKUP(B29,'Unique LMStudio'!A$4:G1001,4,false) | D29: LFM2 is a new generation of hybrid models developed by Liquid AI, specifically designed for edge AI and on-device deployment. It sets a new standard in terms of quality, speed, and memory efficiency. | E29: 67.5K | F29: 49 | G29: 3 | H29: Updated 6 months ago | I29: 350M | J29: 700M | K29: 1.2B
A30: https://lmstudio.ai/models/devstral | B30: Devstral | C30: =VLOOKUP(B30,'Unique LMStudio'!A$4:G1001,4,false) -> https://llm-stats.com/models/devstral-small-2507 | D30: Devstral is a coding model from Mistral AI. It excels at using tools to explore codebases, editing multiple files and power software engineering agents. | E30: 78.3K | F30: 40 | G30: 2 | H30: Updated 4 months ago | I30: 23.6B | J30: 24B
A31: https://lmstudio.ai/models/gemma-3n | B31: gemma-3n | C31: =VLOOKUP(B31,'Unique LMStudio'!A$4:G1001,4,false) -> https://llm-stats.com/models/gemma-3n-e2b | D31: Gemma 3n is a generative AI model optimized for use in everyday devices, such as phones, laptops, and tablets. | E31: 250.2K | F31: 95 | G31: 2 | H31: Updated 6 months ago | I31: 4.5B | J31: 6.9B
A32: https://lmstudio.ai/models/mistral-small | B32: Mistral Small | C32: =VLOOKUP(B32,'Unique LMStudio'!A$4:G1001,4,false) -> https://llm-stats.com/models/mistral-small-latest | D32: Mistrall Small is a 'knowledge-dense' 24B multi-modal (image input) local model that supports up to 128 token context length. | E32: 79.6K | F32: 20 | H32: Updated 6 months ago | I32: 24B
A33: https://lmstudio.ai/models/magistral | B33: Magistral | C33: =VLOOKUP(B33,'Unique LMStudio'!A$4:G1001,4,false) -> https://llm-stats.com/models/magistral-small-2506 | D33: MistralAI's open-weight reasoning model. 24B dense transformer model supporting up to 128K token context window. The model is capable of long chains of reasoning traces before providing answers. | E33: 129.9K | F33: 50 | G33: 2 | H33: Updated 6 months ago | I33: 23.6B | J33: 24B
A34: https://lmstudio.ai/models/mistral-nemo | B34: mistral-nemo | C34: =VLOOKUP(B34,'Unique LMStudio'!A$4:G1001,4,false) -> https://llm-stats.com/models/mistral-nemo-instruct-2407 | D34: General purpose dense transformer designed for multilingual use cases. Built in collaboration between MistralAI and NVIDIA. | E34: 46.9K | F34: 9 | H34: Updated 6 months ago | I34: 12B
A35: https://lmstudio.ai/models/qwen2.5-vl | B35: qwen2.5-vl | C35: =VLOOKUP(B35,'Unique LMStudio'!A$4:G1001,4,false) -> https://llm-stats.com/models/qwen2.5-vl-7b | D35: Qwen2.5-VL is a performant vision-language model, capable of recognizing common objects and text. Supports context length of 128k tokens in a variety of human languages. | E35: 195.7K | F35: 30 | G35: 4 | H35: Updated 6 months ago | I35: 3B | J35: 7B | K35: 32B | L35: 72B
A36: https://lmstudio.ai/models/gemma-3 | B36: gemma-3 | C36: =VLOOKUP(B36,'Unique LMStudio'!A$4:G1001,4,false) -> https://llm-stats.com/models/gemma-3-1b-it | D36: State-of-the-art image + text input models from Google, built from the same research and tech used to create the Gemini models | E36: 2.1M | F36: 213 | G36: 5 | H36: Updated 6 months ago | I36: 270M | J36: 1B | K36: 4B | L36: 12B
A37: https://lmstudio.ai/models/phi-4-reasoning | B37: phi-4-reasoning | C37: =VLOOKUP(B37,'Unique LMStudio'!A$4:G1001,4,false) -> https://llm-stats.com/models/phi-4-reasoning | D37: Phi-4-mini-reasoning is a lightweight open model built upon synthetic data with a focus on high-quality, reasoning dense data. | E37: 174.7K | F37: 52 | G37: 3 | H37: Updated 6 months ago | I37: 3.8B | J37: 14.7B | K37: 14.7B
A38: https://lmstudio.ai/models/phi-4 | B38: phi-4 | C38: =VLOOKUP(B38,'Unique LMStudio'!A$4:G1001,4,false) -> https://llm-stats.com/models/phi-4 | D38: phi-4 is a state-of-the-art open model built upon a blend of synthetic datasets, data from filtered public domain websites, and acquired academic books and Q&A datasets. | E38: 36.6K | F38: 18 | G38: 2 | H38: Updated 6 months ago | I38: 3B | J38: 14B
A39: https://lmstudio.ai/models/codestral | B39: Codestral | C39: =VLOOKUP(B39,'Unique LMStudio'!A$4:G1001,4,false) -> https://llm-stats.com/models/codestral-22b | D39: Mistral AI's latest coding model, Codestral can handle both instructions and code completions with ease in over 80 programming languages. | E39: 55.8K | F39: 31 | H39: Updated 6 months ago | I39: 22B
A40: https://lmstudio.ai/models/mistral | B40: Mistral | C40: =VLOOKUP(B40,'Unique LMStudio'!A$4:G1001,4,false) -> https://llm-stats.com/models/mistral-small-latest | D40: One of the most popular open-source LLMs, Mistral's 7B Instruct model's balance of speed, size, and performance makes it a great general-purpose daily driver. | E40: 136.4K | F40: 46 | H40: Updated 6 months ago | I40: 7B
A41: https://lmstudio.ai/models/qwen3-2504 | B41: Qwen3 (1st Generation) | C41: =VLOOKUP(B41,'Unique LMStudio'!A$4:G1001,4,false) -> https://llm-stats.com/models/qwen3-32b | D41: The first batch of Qwen3 models (Qwen3-2504), a collection of dense and MoE models ranging from 4B to 235B. These are general purpose models that score highly on benchmarks. | E41: 524.5K | F41: 51 | G41: 6 | H41: Updated 6 months ago | I41: 4B | J41: 8B | K41: 14B | L41: 30B
A42: https://lmstudio.ai/models/deepseek-r1 | B42: deepseek-r1 | C42: =VLOOKUP(B42,'Unique LMStudio'!A$4:G1001,4,false) -> https://llm-stats.com/models/deepseek-r1 | D42: Distilled version of the DeepSeek-R1-0528 model, created by continuing the post-training process on the Qwen3 8B Base model using Chain-of-Thought (CoT) from DeepSeek-R1-0528. | E42: 824.9K | F42: 231 | G42: 6 | H42: Updated 6 months ago | I42: 7B | J42: 8B | K42: 8B | L42: 14B

Sheet Source Data
A1: https://lmstudio.ai/models
A2: https://openrouter.ai/models?order=latency-low-to-high
A3: https://llm-stats.com/organizations/openai
A4: https://llm-stats.com/organizations
A5: https://magazine.sebastianraschka.com/notes
A6: https://sebastianraschka.com/llm-architecture-gallery/
A7: https://sebastianraschka.com/llm-architecture-gallery/aa-intelligence-index/
A8: https://artificialanalysis.ai/
A10: https://localai.io/getting-started/models/index.html
A11: https://localai.io/gallery.html

Sheet Unique LMStudio
V1: https://docs.z.ai/guides/llm/glm-4.5
S2: https://llm-stats.com/organizations/nvidia | T2: https://llm-stats.com/organizations/qwen | U2: https://llm-stats.com/organizations/google | V2: https://llm-stats.com/organizations/zai-org | W2: https://llm-stats.com/organizations/microsoft | X2: https://llm-stats.com/organizations/mistral | Y2: https://llm-stats.com/organizations/mistral | Z2: https://llm-stats.com/organizations/mistral | AA2: https://llm-stats.com/organizations/deepseek | AB2: https://llm-stats.com/organizations/mistral | AC2: https://llm-stats.com/organizations/mistral | AD2: https://llm-stats.com/organizations/openai | AE2: https://www.together.ai/models/lfm2-24b-a2b | AF2: https://huggingface.co/EssentialAI/rnj-1 | AG2: https://allenai.org/blog/olmo3 | AH2: https://olmocr.allenai.org/ | AI2: https://huggingface.co/MiniMaxAI/MiniMax-M2 | AJ2: https://ernie.baidu.com/ | AK2: https://github.com/ByteDance-Seed/seed-oss | AL2: https://www.ibm.com/granite/docs/models/granite
B3: Reason | C3: Use | I3: http://127.0.0.1:1234/v1/models | Q3: Model | R3: Model | S3: Nemotron | T3: Qwen | U3: Gemma | V3: GLM | W3: Phi | X3: Mistral | Y3: Codestral | Z3: Magistral | AA3: Deepseek | AB3: Devstral | AC3: Ministral | AD3: GPT
A4: =O4 -> Nemotron 3 Omni | E4: GB Size in LMStudio | F4: =VLOOKUP($D4,'LLM Stats list of Model'!$B$2:$N1003,4,false) -> #N/A | G4: =VLOOKUP($D4,'LLM Stats list of Model'!$B$2:$N1003,6,false) -> #N/A | H4: =R4 -> Nemotron | L4: =IFERROR(__xludf.DUMMYFUNCTION("QUERY( ARRAYFORMULA(REGEXEXTRACT(LMStudio!B3:B1003, ""^[^ ]+"")), ""select Col1, count(Col1) where Col1 is not null group by Col1 label count(Col1) ''"" )"),"#N/A") -> #N/A | M4: =IFERROR(__xludf.DUMMYFUNCTION("""COMPUTED_VALUE"""),959.0) -> 959 | O4: {=UNIQUE(LMStudio!B3:B1003)} -> Nemotron 3 Omni | P4: =IFERROR(__xludf.DUMMYFUNCTION("ARRAYFORMULA( IF(O4:O1003="""","""", IF(REGEXMATCH(O4:O1003,""(?i)gemma""),""Gemma"", IF(REGEXMATCH(O4:O1003,""(?i)qwen""),""Qwen"", IF(REGEXMATCH(O4:O1003,""(?i)nemotron""),""Nemotron"", ""Other"")))) )"),"Nemotron") -> Nemotron | Q4: {=IF(S4:S1003="","", IF(S4:S1003<>"Other", S4:S1003, IF(T4:T1003<>"Other", T4:T1003, "Other") ) )} -> Nemotron | R4: =IFERROR(__xludf.DUMMYFUNCTION("ARRAYFORMULA( IF(S4:S1003="""","""", IFERROR( BYROW(S4:AAL1003, LAMBDA(r, INDEX(FILTER(r, r<>""Other""), 1)) ), ""Other"" ) ) )"),"Nemotron") -> Nemotron | S4: =IFERROR(__xludf.DUMMYFUNCTION("ARRAYFORMULA( IF($O4:$O1003="""","""", IF(REGEXMATCH($O4:$O1003,""(?i)""&S$3), S$3, ""Other"") ) )"),"Nemotron") -> Nemotron | T4: =IFERROR(__xludf.DUMMYFUNCTION("ARRAYFORMULA( IF($O4:$O1003="""","""", IF(REGEXMATCH($O4:$O1003,""(?i)""&T$3), T$3, ""Other"") ) )"),"Other") -> Other | U4: =IFERROR(__xludf.DUMMYFUNCTION("ARRAYFORMULA( IF($O4:$O1003="""","""", IF(REGEXMATCH($O4:$O1003,""(?i)""&U$3), U$3, ""Other"") ) )"),"Other") -> Other | V4: =IFERROR(__xludf.DUMMYFUNCTION("ARRAYFORMULA( IF($O4:$O1003="""","""", IF(REGEXMATCH($O4:$O1003,""(?i)""&V$3), V$3, ""Other"") ) )"),"Other") -> Other | W4: =IFERROR(__xludf.DUMMYFUNCTION("ARRAYFORMULA( IF($O4:$O1003="""","""", IF(REGEXMATCH($O4:$O1003,""(?i)""&W$3), W$3, ""Other"") ) )"),"Other") -> Other | X4: =IFERROR(__xludf.DUMMYFUNCTION("ARRAYFORMULA( IF($O4:$O1003="""","""", IF(REGEXMATCH($O4:$O1003,""(?i)""&X$3), X$3, ""Other"") ) )"),"Other") -> Other | Y4: =IFERROR(__xludf.DUMMYFUNCTION("ARRAYFORMULA( IF($O4:$O1003="""","""", IF(REGEXMATCH($O4:$O1003,""(?i)""&Y$3), Y$3, ""Other"") ) )"),"Other") -> Other | Z4: =IFERROR(__xludf.DUMMYFUNCTION("ARRAYFORMULA( IF($O4:$O1003="""","""", IF(REGEXMATCH($O4:$O1003,""(?i)""&Z$3), Z$3, ""Other"") ) )"),"Other") -> Other | AA4: =IFERROR(__xludf.DUMMYFUNCTION("ARRAYFORMULA( IF($O4:$O1003="""","""", IF(REGEXMATCH($O4:$O1003,""(?i)""&AA$3), AA$3, ""Other"") ) )"),"Other") -> Other | AB4: =IFERROR(__xludf.DUMMYFUNCTION("ARRAYFORMULA( IF($O4:$O1003="""","""", IF(REGEXMATCH($O4:$O1003,""(?i)""&AB$3), AB$3, ""Other"") ) )"),"Other") -> Other | AC4: =IFERROR(__xludf.DUMMYFUNCTION("ARRAYFORMULA( IF($O4:$O1003="""","""", IF(REGEXMATCH($O4:$O1003,""(?i)""&AC$3), AC$3, ""Other"") ) )"),"Other") -> Other | AD4: =IFERROR(__xludf.DUMMYFUNCTION("ARRAYFORMULA( IF($O4:$O1003="""","""", IF(REGEXMATCH($O4:$O1003,""(?i)""&AD$3), AD$3, ""Other"") ) )"),"Other") -> Other
A5: =O5 -> Qwen3.6 | D5: https://llm-stats.com/models/qwen3.6-plus | F5: =VLOOKUP($D5,'LLM Stats list of Model'!$B$2:$N1003,4,false) -> 2 | G5: =VLOOKUP($D5,'LLM Stats list of Model'!$B$2:$N1003,6,false) -> Qwen3.6 Plus | H5: =R5 -> Qwen | I5: =VLOOKUP(H5,'Unique Organization'!C$2:D$13,2,FALSE) -> qwen | L5: =IFERROR(__xludf.DUMMYFUNCTION("""COMPUTED_VALUE"""),"Codestral") -> Codestral | M5: =IFERROR(__xludf.DUMMYFUNCTION("""COMPUTED_VALUE"""),1.0) -> 1 | O5: Qwen3.6 | P5: =IFERROR(__xludf.DUMMYFUNCTION("""COMPUTED_VALUE"""),"Qwen") -> Qwen | Q5: Qwen | R5: =IFERROR(__xludf.DUMMYFUNCTION("""COMPUTED_VALUE"""),"Qwen") -> Qwen | S5: =IFERROR(__xludf.DUMMYFUNCTION("""COMPUTED_VALUE"""),"Other") -> Other | T5: =IFERROR(__xludf.DUMMYFUNCTION("""COMPUTED_VALUE"""),"Qwen") -> Qwen | U5: =IFERROR(__xludf.DUMMYFUNCTION("""COMPUTED_VALUE"""),"Other") -> Other | V5: =IFERROR(__xludf.DUMMYFUNCTION("""COMPUTED_VALUE"""),"Other") -> Other | W5: =IFERROR(__xludf.DUMMYFUNCTION("""COMPUTED_VALUE"""),"Other") -> Other | X5: =IFERROR(__xludf.DUMMYFUNCTION("""COMPUTED_VALUE"""),"Other") -> Other | Y5: =IFERROR(__xludf.DUMMYFUNCTION("""COMPUTED_VALUE"""),"Other") -> Other | Z5: =IFERROR(__xludf.DUMMYFUNCTION("""COMPUTED_VALUE"""),"Other") -> Other | AA5: =IFERROR(__xludf.DUMMYFUNCTION("""COMPUTED_VALUE"""),"Other") -> Other | AB5: =IFERROR(__xludf.DUMMYFUNCTION("""COMPUTED_VALUE"""),"Other") -> Other | ... AD5: =IFERROR(__xludf.DUMMYFUNCTION("""COMPUTED_VALUE"""),"Other") -> Other
A6: =O6 -> Gemma 4 | D6: https://llm-stats.com/models/gemma-4-e4b-it | F6: =VLOOKUP($D6,'LLM Stats list of Model'!$B$2:$N1003,4,false) | G6: =VLOOKUP($D6,'LLM Stats list of Model'!$B$2:$N1003,6,false) -> Gemma 4 E4B | H6: =R6 -> Gemma | I6: =VLOOKUP(H6,'Unique Organization'!C$2:D$13,2,FALSE) -> google | L6: =IFERROR(__xludf.DUMMYFUNCTION("""COMPUTED_VALUE"""),"Devstral") -> Devstral | M6: =IFERROR(__xludf.DUMMYFUNCTION("""COMPUTED_VALUE"""),2.0) -> 2 | O6: Gemma 4 | P6: =IFERROR(__xludf.DUMMYFUNCTION("""COMPUTED_VALUE"""),"Gemma") -> Gemma | Q6: Other | R6: =IFERROR(__xludf.DUMMYFUNCTION("""COMPUTED_VALUE"""),"Gemma") -> Gemma | S6: =IFERROR(__xludf.DUMMYFUNCTION("""COMPUTED_VALUE"""),"Other") -> Other | T6: =IFERROR(__xludf.DUMMYFUNCTION("""COMPUTED_VALUE"""),"Other") -> Other | U6: =IFERROR(__xludf.DUMMYFUNCTION("""COMPUTED_VALUE"""),"Gemma") -> Gemma | V6: =IFERROR(__xludf.DUMMYFUNCTION("""COMPUTED_VALUE"""),"Other") -> Other | W6: =IFERROR(__xludf.DUMMYFUNCTION("""COMPUTED_VALUE"""),"Other") -> Other | X6: =IFERROR(__xludf.DUMMYFUNCTION("""COMPUTED_VALUE"""),"Other") -> Other | Y6: =IFERROR(__xludf.DUMMYFUNCTION("""COMPUTED_VALUE"""),"Other") -> Other | Z6: =IFERROR(__xludf.DUMMYFUNCTION("""COMPUTED_VALUE"""),"Other") -> Other | AA6: =IFERROR(__xludf.DUMMYFUNCTION("""COMPUTED_VALUE"""),"Other") -> Other | AB6: =IFERROR(__xludf.DUMMYFUNCTION("""COMPUTED_VALUE"""),"Other") -> Other | AC6: =IFERROR(__xludf.DUMMYFUNCTION("""COMPUTED_VALUE"""),"Other") -> Other | AD6: =IFERROR(__xludf.DUMMYFUNCTION("""COMPUTED_VALUE"""),"Other") -> Other
A7: =O7 -> Nemotron 3 Super | D7: https://llm-stats.com/models/nemotron-3-super-120b-a12b | F7: =VLOOKUP($D7,'LLM Stats list of Model'!$B$2:$N1003,4,false) | G7: =VLOOKUP($D7,'LLM Stats list of Model'!$B$2:$N1003,6,false) -> Nemotron 3 Super (120B A12B) | H7: =R7 -> Nemotron | I7: =VLOOKUP(H7,'Unique Organization'!C$2:D$13,2,FALSE) -> nvidia | L7: =IFERROR(__xludf.DUMMYFUNCTION("""COMPUTED_VALUE"""),"Ernie-4.5") -> Ernie-4.5 | M7: =IFERROR(__xludf.DUMMYFUNCTION("""COMPUTED_VALUE"""),1.0) -> 1 | O7: Nemotron 3 Super | P7: =IFERROR(__xludf.DUMMYFUNCTION("""COMPUTED_VALUE"""),"Nemotron") -> Nemotron | Q7: Nemotron | R7: =IFERROR(__xludf.DUMMYFUNCTION("""COMPUTED_VALUE"""),"Nemotron") -> Nemotron | S7: =IFERROR(__xludf.DUMMYFUNCTION("""COMPUTED_VALUE"""),"Nemotron") -> Nemotron | T7: =IFERROR(__xludf.DUMMYFUNCTION("""COMPUTED_VALUE"""),"Other") -> Other | U7: =IFERROR(__xludf.DUMMYFUNCTION("""COMPUTED_VALUE"""),"Other") -> Other | V7: =IFERROR(__xludf.DUMMYFUNCTION("""COMPUTED_VALUE"""),"Other") -> Other | W7: =IFERROR(__xludf.DUMMYFUNCTION("""COMPUTED_VALUE"""),"Other") -> Other | X7: =IFERROR(__xludf.DUMMYFUNCTION("""COMPUTED_VALUE"""),"Other") -> Other | Y7: =IFERROR(__xludf.DUMMYFUNCTION("""COMPUTED_VALUE"""),"Other") -> Other | Z7: =IFERROR(__xludf.DUMMYFUNCTION("""COMPUTED_VALUE"""),"Other") -> Other | AA7: =IFERROR(__xludf.DUMMYFUNCTION("""COMPUTED_VALUE"""),"Other") -> Other | ... AD7: =IFERROR(__xludf.DUMMYFUNCTION("""COMPUTED_VALUE"""),"Other") -> Other
A8: =O8 -> Qwen3.5 | D8: https://llm-stats.com/models/qwen3.5-2b | F8: =VLOOKUP($D8,'LLM Stats list of Model'!$B$2:$N1003,4,false) -> 2 | G8: =VLOOKUP($D8,'LLM Stats list of Model'!$B$2:$N1003,6,false) -> Qwen3.5-2B | H8: =R8 -> Qwen | I8: =VLOOKUP(H8,'Unique Organization'!C$2:D$13,2,FALSE) -> qwen | L8: =IFERROR(__xludf.DUMMYFUNCTION("""COMPUTED_VALUE"""),"FunctionGemma") -> FunctionGemma | M8: =IFERROR(__xludf.DUMMYFUNCTION("""COMPUTED_VALUE"""),1.0) -> 1 | O8: Qwen3.5 | P8: =IFERROR(__xludf.DUMMYFUNCTION("""COMPUTED_VALUE"""),"Qwen") -> Qwen | Q8: Qwen | R8: =IFERROR(__xludf.DUMMYFUNCTION("""COMPUTED_VALUE"""),"Qwen") -> Qwen | S8: =IFERROR(__xludf.DUMMYFUNCTION("""COMPUTED_VALUE"""),"Other") -> Other | T8: =IFERROR(__xludf.DUMMYFUNCTION("""COMPUTED_VALUE"""),"Qwen") -> Qwen | U8: =IFERROR(__xludf.DUMMYFUNCTION("""COMPUTED_VALUE"""),"Other") -> Other | V8: =IFERROR(__xludf.DUMMYFUNCTION("""COMPUTED_VALUE"""),"Other") -> Other | W8: =IFERROR(__xludf.DUMMYFUNCTION("""COMPUTED_VALUE"""),"Other") -> Other | X8: =IFERROR(__xludf.DUMMYFUNCTION("""COMPUTED_VALUE"""),"Other") -> Other | Y8: =IFERROR(__xludf.DUMMYFUNCTION("""COMPUTED_VALUE"""),"Other") -> Other | Z8: =IFERROR(__xludf.DUMMYFUNCTION("""COMPUTED_VALUE"""),"Other") -> Other | AA8: =IFERROR(__xludf.DUMMYFUNCTION("""COMPUTED_VALUE"""),"Other") -> Other | AB8: =IFERROR(__xludf.DUMMYFUNCTION("""COMPUTED_VALUE"""),"Other") -> Other | ... AD8: =IFERROR(__xludf.DUMMYFUNCTION("""COMPUTED_VALUE"""),"Other") -> Other
A9: =O9 -> LFM2-24B-A2B | L9: =IFERROR(__xludf.DUMMYFUNCTION("""COMPUTED_VALUE"""),"GLM-4.6V-Flash") -> GLM-4.6V-Flash | M9: =IFERROR(__xludf.DUMMYFUNCTION("""COMPUTED_VALUE"""),1.0) -> 1 | O9: LFM2-24B-A2B | P9: =IFERROR(__xludf.DUMMYFUNCTION("""COMPUTED_VALUE"""),"Other") -> Other | Q9: Other | S9: =IFERROR(__xludf.DUMMYFUNCTION("""COMPUTED_VALUE"""),"Other") -> Other | T9: =IFERROR(__xludf.DUMMYFUNCTION("""COMPUTED_VALUE"""),"Other") -> Other | U9: =IFERROR(__xludf.DUMMYFUNCTION("""COMPUTED_VALUE"""),"Other") -> Other | V9: =IFERROR(__xludf.DUMMYFUNCTION("""COMPUTED_VALUE"""),"Other") -> Other | W9: =IFERROR(__xludf.DUMMYFUNCTION("""COMPUTED_VALUE"""),"Other") -> Other | X9: =IFERROR(__xludf.DUMMYFUNCTION("""COMPUTED_VALUE"""),"Other") -> Other | Y9: =IFERROR(__xludf.DUMMYFUNCTION("""COMPUTED_VALUE"""),"Other") -> Other | Z9: =IFERROR(__xludf.DUMMYFUNCTION("""COMPUTED_VALUE"""),"Other") -> Other | ... AD9: =IFERROR(__xludf.DUMMYFUNCTION("""COMPUTED_VALUE"""),"Other") -> Other
A10: =O10 -> Qwen3-Coder-Next | D10: https://llm-stats.com/models/qwen3-coder-480b-a35b-instruct | F10: =VLOOKUP($D10,'LLM Stats list of Model'!$B$2:$N1003,4,false) -> 2 | G10: =VLOOKUP($D10,'LLM Stats list of Model'!$B$2:$N1003,6,false) -> Qwen3-Coder 480B A35B Instruct | H10: =R10 -> Qwen | I10: =VLOOKUP(H10,'Unique Organization'!C$2:D$13,2,FALSE) -> qwen | L10: =IFERROR(__xludf.DUMMYFUNCTION("""COMPUTED_VALUE"""),"GLM-4.7") -> GLM-4.7 | M10: =IFERROR(__xludf.DUMMYFUNCTION("""COMPUTED_VALUE"""),1.0) -> 1 | O10: Qwen3-Coder-Next | P10: =IFERROR(__xludf.DUMMYFUNCTION("""COMPUTED_VALUE"""),"Qwen") -> Qwen | Q10: Qwen | R10: =IFERROR(__xludf.DUMMYFUNCTION("""COMPUTED_VALUE"""),"Qwen") -> Qwen | S10: =IFERROR(__xludf.DUMMYFUNCTION("""COMPUTED_VALUE"""),"Other") -> Other | T10: =IFERROR(__xludf.DUMMYFUNCTION("""COMPUTED_VALUE"""),"Qwen") -> Qwen | U10: =IFERROR(__xludf.DUMMYFUNCTION("""COMPUTED_VALUE"""),"Other") -> Other | V10: =IFERROR(__xludf.DUMMYFUNCTION("""COMPUTED_VALUE"""),"Other") -> Other | W10: =IFERROR(__xludf.DUMMYFUNCTION("""COMPUTED_VALUE"""),"Other") -> Other | X10: =IFERROR(__xludf.DUMMYFUNCTION("""COMPUTED_VALUE"""),"Other") -> Other | Y10: =IFERROR(__xludf.DUMMYFUNCTION("""COMPUTED_VALUE"""),"Other") -> Other | Z10: =IFERROR(__xludf.DUMMYFUNCTION("""COMPUTED_VALUE"""),"Other") -> Other | AA10: =IFERROR(__xludf.DUMMYFUNCTION("""COMPUTED_VALUE"""),"Other") -> Other | AB10: =IFERROR(__xludf.DUMMYFUNCTION("""COMPUTED_VALUE"""),"Other") -> Other | ... AD10: =IFERROR(__xludf.DUMMYFUNCTION("""COMPUTED_VALUE"""),"Other") -> Other
A11: =O11 -> GLM-4.7 | D11: https://llm-stats.com/models/glm-4.7 | F11: =VLOOKUP($D11,'LLM Stats list of Model'!$B$2:$N1003,4,false) | G11: =VLOOKUP($D11,'LLM Stats list of Model'!$B$2:$N1003,6,false) -> GLM-4.7 | H11: =R11 -> GLM | I11: =VLOOKUP(H11,'Unique Organization'!C$2:D$13,2,FALSE) -> zai-org | L11: =IFERROR(__xludf.DUMMYFUNCTION("""COMPUTED_VALUE"""),"Gemma") -> Gemma | M11: =IFERROR(__xludf.DUMMYFUNCTION("""COMPUTED_VALUE"""),1.0) -> 1 | O11: GLM-4.7 | P11: =IFERROR(__xludf.DUMMYFUNCTION("""COMPUTED_VALUE"""),"Other") -> Other | Q11: Other | R11: =IFERROR(__xludf.DUMMYFUNCTION("""COMPUTED_VALUE"""),"GLM") -> GLM | S11: =IFERROR(__xludf.DUMMYFUNCTION("""COMPUTED_VALUE"""),"Other") -> Other | T11: =IFERROR(__xludf.DUMMYFUNCTION("""COMPUTED_VALUE"""),"Other") -> Other | U11: =IFERROR(__xludf.DUMMYFUNCTION("""COMPUTED_VALUE"""),"Other") -> Other | V11: =IFERROR(__xludf.DUMMYFUNCTION("""COMPUTED_VALUE"""),"GLM") -> GLM | W11: =IFERROR(__xludf.DUMMYFUNCTION("""COMPUTED_VALUE"""),"Other") -> Other | X11: =IFERROR(__xludf.DUMMYFUNCTION("""COMPUTED_VALUE"""),"Other") -> Other | Y11: =IFERROR(__xludf.DUMMYFUNCTION("""COMPUTED_VALUE"""),"Other") -> Other | Z11: =IFERROR(__xludf.DUMMYFUNCTION("""COMPUTED_VALUE"""),"Other") -> Other | AA11: =IFERROR(__xludf.DUMMYFUNCTION("""COMPUTED_VALUE"""),"Other") -> Other | AB11: =IFERROR(__xludf.DUMMYFUNCTION("""COMPUTED_VALUE"""),"Other") -> Other | AC11: =IFERROR(__xludf.DUMMYFUNCTION("""COMPUTED_VALUE"""),"Other") -> Other | AD11: =IFERROR(__xludf.DUMMYFUNCTION("""COMPUTED_VALUE"""),"Other") -> Other
A12: =O12 -> FunctionGemma | D12: https://huggingface.co/google/functiongemma-270m-it | H12: =R12 -> Gemma | I12: =VLOOKUP(H12,'Unique Organization'!C$2:D$13,2,FALSE) -> google | L12: =IFERROR(__xludf.DUMMYFUNCTION("""COMPUTED_VALUE"""),"Granite") -> Granite | M12: =IFERROR(__xludf.DUMMYFUNCTION("""COMPUTED_VALUE"""),1.0) -> 1 | O12: FunctionGemma | P12: =IFERROR(__xludf.DUMMYFUNCTION("""COMPUTED_VALUE"""),"Gemma") -> Gemma | Q12: Other | R12: =IFERROR(__xludf.DUMMYFUNCTION("""COMPUTED_VALUE"""),"Gemma") -> Gemma | S12: =IFERROR(__xludf.DUMMYFUNCTION("""COMPUTED_VALUE"""),"Other") -> Other | T12: =IFERROR(__xludf.DUMMYFUNCTION("""COMPUTED_VALUE"""),"Other") -> Other | U12: =IFERROR(__xludf.DUMMYFUNCTION("""COMPUTED_VALUE"""),"Gemma") -> Gemma | V12: =IFERROR(__xludf.DUMMYFUNCTION("""COMPUTED_VALUE"""),"Other") -> Other | W12: =IFERROR(__xludf.DUMMYFUNCTION("""COMPUTED_VALUE"""),"Other") -> Other | X12: =IFERROR(__xludf.DUMMYFUNCTION("""COMPUTED_VALUE"""),"Other") -> Other | Y12: =IFERROR(__xludf.DUMMYFUNCTION("""COMPUTED_VALUE"""),"Other") -> Other | Z12: =IFERROR(__xludf.DUMMYFUNCTION("""COMPUTED_VALUE"""),"Other") -> Other | AA12: =IFERROR(__xludf.DUMMYFUNCTION("""COMPUTED_VALUE"""),"Other") -> Other | AB12: =IFERROR(__xludf.DUMMYFUNCTION("""COMPUTED_VALUE"""),"Other") -> Other | AC12: =IFERROR(__xludf.DUMMYFUNCTION("""COMPUTED_VALUE"""),"Other") -> Other | AD12: =IFERROR(__xludf.DUMMYFUNCTION("""COMPUTED_VALUE"""),"Other") -> Other
A13: =O13 -> Nemotron 3 | D13: https://llm-stats.com/models/nemotron-3-nano-30b-a3b | F13: =VLOOKUP($D13,'LLM Stats list of Model'!$B$2:$N1003,4,false) | G13: =VLOOKUP($D13,'LLM Stats list of Model'!$B$2:$N1003,6,false) -> Nemotron 3 Nano (30B A3B) | H13: =R13 -> Nemotron | I13: =VLOOKUP(H13,'Unique Organization'!C$2:D$13,2,FALSE) -> nvidia | L13: =IFERROR(__xludf.DUMMYFUNCTION("""COMPUTED_VALUE"""),"LFM2") -> LFM2 | M13: =IFERROR(__xludf.DUMMYFUNCTION("""COMPUTED_VALUE"""),1.0) -> 1 | O13: Nemotron 3 | P13: =IFERROR(__xludf.DUMMYFUNCTION("""COMPUTED_VALUE"""),"Nemotron") -> Nemotron | Q13: Nemotron | R13: =IFERROR(__xludf.DUMMYFUNCTION("""COMPUTED_VALUE"""),"Nemotron") -> Nemotron | S13: =IFERROR(__xludf.DUMMYFUNCTION("""COMPUTED_VALUE"""),"Nemotron") -> Nemotron | T13: =IFERROR(__xludf.DUMMYFUNCTION("""COMPUTED_VALUE"""),"Other") -> Other | U13: =IFERROR(__xludf.DUMMYFUNCTION("""COMPUTED_VALUE"""),"Other") -> Other | V13: =IFERROR(__xludf.DUMMYFUNCTION("""COMPUTED_VALUE"""),"Other") -> Other | W13: =IFERROR(__xludf.DUMMYFUNCTION("""COMPUTED_VALUE"""),"Other") -> Other | X13: =IFERROR(__xludf.DUMMYFUNCTION("""COMPUTED_VALUE"""),"Other") -> Other | Y13: =IFERROR(__xludf.DUMMYFUNCTION("""COMPUTED_VALUE"""),"Other") -> Other | Z13: =IFERROR(__xludf.DUMMYFUNCTION("""COMPUTED_VALUE"""),"Other") -> Other | AA13: =IFERROR(__xludf.DUMMYFUNCTION("""COMPUTED_VALUE"""),"Other") -> Other | ... AD13: =IFERROR(__xludf.DUMMYFUNCTION("""COMPUTED_VALUE"""),"Other") -> Other
A14: =O14 -> GLM-4.6V-Flash | D14: https://llm-stats.com/models/glm-4.6 | F14: =VLOOKUP($D14,'LLM Stats list of Model'!$B$2:$N1003,4,false) | G14: =VLOOKUP($D14,'LLM Stats list of Model'!$B$2:$N1003,6,false) -> GLM-4.6 | H14: =R14 -> GLM | I14: =VLOOKUP(H14,'Unique Organization'!C$2:D$13,2,FALSE) -> zai-org | L14: =IFERROR(__xludf.DUMMYFUNCTION("""COMPUTED_VALUE"""),"LFM2-24B-A2B") -> LFM2-24B-A2B | M14: =IFERROR(__xludf.DUMMYFUNCTION("""COMPUTED_VALUE"""),1.0) -> 1 | O14: GLM-4.6V-Flash | P14: =IFERROR(__xludf.DUMMYFUNCTION("""COMPUTED_VALUE"""),"Other") -> Other | Q14: Other | R14: =IFERROR(__xludf.DUMMYFUNCTION("""COMPUTED_VALUE"""),"GLM") -> GLM | S14: =IFERROR(__xludf.DUMMYFUNCTION("""COMPUTED_VALUE"""),"Other") -> Other | T14: =IFERROR(__xludf.DUMMYFUNCTION("""COMPUTED_VALUE"""),"Other") -> Other | U14: =IFERROR(__xludf.DUMMYFUNCTION("""COMPUTED_VALUE"""),"Other") -> Other | V14: =IFERROR(__xludf.DUMMYFUNCTION("""COMPUTED_VALUE"""),"GLM") -> GLM | W14: =IFERROR(__xludf.DUMMYFUNCTION("""COMPUTED_VALUE"""),"Other") -> Other | X14: =IFERROR(__xludf.DUMMYFUNCTION("""COMPUTED_VALUE"""),"Other") -> Other | Y14: =IFERROR(__xludf.DUMMYFUNCTION("""COMPUTED_VALUE"""),"Other") -> Other | Z14: =IFERROR(__xludf.DUMMYFUNCTION("""COMPUTED_VALUE"""),"Other") -> Other | AA14: =IFERROR(__xludf.DUMMYFUNCTION("""COMPUTED_VALUE"""),"Other") -> Other | AB14: =IFERROR(__xludf.DUMMYFUNCTION("""COMPUTED_VALUE"""),"Other") -> Other | AC14: =IFERROR(__xludf.DUMMYFUNCTION("""COMPUTED_VALUE"""),"Other") -> Other | AD14: =IFERROR(__xludf.DUMMYFUNCTION("""COMPUTED_VALUE"""),"Other") -> Other
A15: =O15 -> Devstral 2 | D15: https://llm-stats.com/models/devstral-small-2507 | F15: =VLOOKUP($D15,'LLM Stats list of Model'!$B$2:$N1003,4,false) | G15: =VLOOKUP($D15,'LLM Stats list of Model'!$B$2:$N1003,6,false) -> Devstral Small 1.1 | H15: =R15 -> Devstral | I15: =VLOOKUP(H15,'Unique Organization'!C$2:D$13,2,FALSE) -> mistral | L15: =IFERROR(__xludf.DUMMYFUNCTION("""COMPUTED_VALUE"""),"Magistral") -> Magistral | M15: =IFERROR(__xludf.DUMMYFUNCTION("""COMPUTED_VALUE"""),1.0) -> 1 | O15: Devstral 2 | P15: =IFERROR(__xludf.DUMMYFUNCTION("""COMPUTED_VALUE"""),"Other") -> Other | Q15: Other | R15: =IFERROR(__xludf.DUMMYFUNCTION("""COMPUTED_VALUE"""),"Devstral") -> Devstral | S15: =IFERROR(__xludf.DUMMYFUNCTION("""COMPUTED_VALUE"""),"Other") -> Other | T15: =IFERROR(__xludf.DUMMYFUNCTION("""COMPUTED_VALUE"""),"Other") -> Other | U15: =IFERROR(__xludf.DUMMYFUNCTION("""COMPUTED_VALUE"""),"Other") -> Other | V15: =IFERROR(__xludf.DUMMYFUNCTION("""COMPUTED_VALUE"""),"Other") -> Other | W15: =IFERROR(__xludf.DUMMYFUNCTION("""COMPUTED_VALUE"""),"Other") -> Other | X15: =IFERROR(__xludf.DUMMYFUNCTION("""COMPUTED_VALUE"""),"Other") -> Other | Y15: =IFERROR(__xludf.DUMMYFUNCTION("""COMPUTED_VALUE"""),"Other") -> Other | Z15: =IFERROR(__xludf.DUMMYFUNCTION("""COMPUTED_VALUE"""),"Other") -> Other | AA15: =IFERROR(__xludf.DUMMYFUNCTION("""COMPUTED_VALUE"""),"Other") -> Other | AB15: =IFERROR(__xludf.DUMMYFUNCTION("""COMPUTED_VALUE"""),"Devstral") -> Devstral | AC15: =IFERROR(__xludf.DUMMYFUNCTION("""COMPUTED_VALUE"""),"Other") -> Other | AD15: =IFERROR(__xludf.DUMMYFUNCTION("""COMPUTED_VALUE"""),"Other") -> Other
A16: =O16 -> Rnj-1 | L16: =IFERROR(__xludf.DUMMYFUNCTION("""COMPUTED_VALUE"""),"Ministral") -> Ministral | M16: =IFERROR(__xludf.DUMMYFUNCTION("""COMPUTED_VALUE"""),1.0) -> 1 | O16: Rnj-1 | P16: =IFERROR(__xludf.DUMMYFUNCTION("""COMPUTED_VALUE"""),"Other") -> Other | Q16: Other | S16: =IFERROR(__xludf.DUMMYFUNCTION("""COMPUTED_VALUE"""),"Other") -> Other | T16: =IFERROR(__xludf.DUMMYFUNCTION("""COMPUTED_VALUE"""),"Other") -> Other | U16: =IFERROR(__xludf.DUMMYFUNCTION("""COMPUTED_VALUE"""),"Other") -> Other | V16: =IFERROR(__xludf.DUMMYFUNCTION("""COMPUTED_VALUE"""),"Other") -> Other | W16: =IFERROR(__xludf.DUMMYFUNCTION("""COMPUTED_VALUE"""),"Other") -> Other | X16: =IFERROR(__xludf.DUMMYFUNCTION("""COMPUTED_VALUE"""),"Other") -> Other | Y16: =IFERROR(__xludf.DUMMYFUNCTION("""COMPUTED_VALUE"""),"Other") -> Other | Z16: =IFERROR(__xludf.DUMMYFUNCTION("""COMPUTED_VALUE"""),"Other") -> Other | ... AD16: =IFERROR(__xludf.DUMMYFUNCTION("""COMPUTED_VALUE"""),"Other") -> Other
A17: =O17 -> Ministral 3 | D17: https://llm-stats.com/models/ministral-3-8b-base-2512 | F17: =VLOOKUP($D17,'LLM Stats list of Model'!$B$2:$N1003,4,false) | G17: =VLOOKUP($D17,'LLM Stats list of Model'!$B$2:$N1003,6,false) -> Ministral 3 (8B Base 2512) | H17: =R17 -> Ministral | I17: =VLOOKUP(H17,'Unique Organization'!C$2:D$13,2,FALSE) -> mistral | L17: =IFERROR(__xludf.DUMMYFUNCTION("""COMPUTED_VALUE"""),"Mistral") -> Mistral | M17: =IFERROR(__xludf.DUMMYFUNCTION("""COMPUTED_VALUE"""),2.0) -> 2 | O17: Ministral 3 | P17: =IFERROR(__xludf.DUMMYFUNCTION("""COMPUTED_VALUE"""),"Other") -> Other | Q17: Other | R17: =IFERROR(__xludf.DUMMYFUNCTION("""COMPUTED_VALUE"""),"Ministral") -> Ministral | S17: =IFERROR(__xludf.DUMMYFUNCTION("""COMPUTED_VALUE"""),"Other") -> Other | T17: =IFERROR(__xludf.DUMMYFUNCTION("""COMPUTED_VALUE"""),"Other") -> Other | U17: =IFERROR(__xludf.DUMMYFUNCTION("""COMPUTED_VALUE"""),"Other") -> Other | V17: =IFERROR(__xludf.DUMMYFUNCTION("""COMPUTED_VALUE"""),"Other") -> Other | W17: =IFERROR(__xludf.DUMMYFUNCTION("""COMPUTED_VALUE"""),"Other") -> Other | X17: =IFERROR(__xludf.DUMMYFUNCTION("""COMPUTED_VALUE"""),"Other") -> Other | Y17: =IFERROR(__xludf.DUMMYFUNCTION("""COMPUTED_VALUE"""),"Other") -> Other | Z17: =IFERROR(__xludf.DUMMYFUNCTION("""COMPUTED_VALUE"""),"Other") -> Other | ... AB17: =IFERROR(__xludf.DUMMYFUNCTION("""COMPUTED_VALUE"""),"Other") -> Other | AC17: =IFERROR(__xludf.DUMMYFUNCTION("""COMPUTED_VALUE"""),"Ministral") -> Ministral | AD17: =IFERROR(__xludf.DUMMYFUNCTION("""COMPUTED_VALUE"""),"Other") -> Other
A18: =O18 -> Qwen3 Next | D18: https://llm-stats.com/models/qwen3-next-80b-a3b-base | F18: =VLOOKUP($D18,'LLM Stats list of Model'!$B$2:$N1003,4,false) -> 2 | G18: =VLOOKUP($D18,'LLM Stats list of Model'!$B$2:$N1003,6,false) -> Qwen3-Next-80B-A3B-Base | H18: =R18 -> Qwen | I18: =VLOOKUP(H18,'Unique Organization'!C$2:D$13,2,FALSE) -> qwen | L18: =IFERROR(__xludf.DUMMYFUNCTION("""COMPUTED_VALUE"""),"Nemotron") -> Nemotron | M18: =IFERROR(__xludf.DUMMYFUNCTION("""COMPUTED_VALUE"""),3.0) -> 3 | O18: Qwen3 Next | P18: =IFERROR(__xludf.DUMMYFUNCTION("""COMPUTED_VALUE"""),"Qwen") -> Qwen | Q18: Qwen | R18: =IFERROR(__xludf.DUMMYFUNCTION("""COMPUTED_VALUE"""),"Qwen") -> Qwen | S18: =IFERROR(__xludf.DUMMYFUNCTION("""COMPUTED_VALUE"""),"Other") -> Other | T18: =IFERROR(__xludf.DUMMYFUNCTION("""COMPUTED_VALUE"""),"Qwen") -> Qwen | U18: =IFERROR(__xludf.DUMMYFUNCTION("""COMPUTED_VALUE"""),"Other") -> Other | V18: =IFERROR(__xludf.DUMMYFUNCTION("""COMPUTED_VALUE"""),"Other") -> Other | W18: =IFERROR(__xludf.DUMMYFUNCTION("""COMPUTED_VALUE"""),"Other") -> Other | X18: =IFERROR(__xludf.DUMMYFUNCTION("""COMPUTED_VALUE"""),"Other") -> Other | Y18: =IFERROR(__xludf.DUMMYFUNCTION("""COMPUTED_VALUE"""),"Other") -> Other | Z18: =IFERROR(__xludf.DUMMYFUNCTION("""COMPUTED_VALUE"""),"Other") -> Other | AA18: =IFERROR(__xludf.DUMMYFUNCTION("""COMPUTED_VALUE"""),"Other") -> Other | AB18: =IFERROR(__xludf.DUMMYFUNCTION("""COMPUTED_VALUE"""),"Other") -> Other | ... AD18: =IFERROR(__xludf.DUMMYFUNCTION("""COMPUTED_VALUE"""),"Other") -> Other
A19: =O19 -> Olmo 3 | H19: =R19 | L19: =IFERROR(__xludf.DUMMYFUNCTION("""COMPUTED_VALUE"""),"Olmo") -> Olmo | M19: =IFERROR(__xludf.DUMMYFUNCTION("""COMPUTED_VALUE"""),1.0) -> 1 | O19: Olmo 3 | P19: =IFERROR(__xludf.DUMMYFUNCTION("""COMPUTED_VALUE"""),"Other") -> Other | Q19: Other | S19: =IFERROR(__xludf.DUMMYFUNCTION("""COMPUTED_VALUE"""),"Other") -> Other | T19: =IFERROR(__xludf.DUMMYFUNCTION("""COMPUTED_VALUE"""),"Other") -> Other | U19: =IFERROR(__xludf.DUMMYFUNCTION("""COMPUTED_VALUE"""),"Other") -> Other | V19: =IFERROR(__xludf.DUMMYFUNCTION("""COMPUTED_VALUE"""),"Other") -> Other | W19: =IFERROR(__xludf.DUMMYFUNCTION("""COMPUTED_VALUE"""),"Other") -> Other | X19: =IFERROR(__xludf.DUMMYFUNCTION("""COMPUTED_VALUE"""),"Other") -> Other | Y19: =IFERROR(__xludf.DUMMYFUNCTION("""COMPUTED_VALUE"""),"Other") -> Other | Z19: =IFERROR(__xludf.DUMMYFUNCTION("""COMPUTED_VALUE"""),"Other") -> Other | ... AD19: =IFERROR(__xludf.DUMMYFUNCTION("""COMPUTED_VALUE"""),"Other") -> Other
A20: =O20 -> olmOCR 2 | H20: =R20 | L20: =IFERROR(__xludf.DUMMYFUNCTION("""COMPUTED_VALUE"""),"Qwen3") -> Qwen3 | M20: =IFERROR(__xludf.DUMMYFUNCTION("""COMPUTED_VALUE"""),3.0) -> 3 | O20: olmOCR 2 | P20: =IFERROR(__xludf.DUMMYFUNCTION("""COMPUTED_VALUE"""),"Other") -> Other | Q20: Other | S20: =IFERROR(__xludf.DUMMYFUNCTION("""COMPUTED_VALUE"""),"Other") -> Other | T20: =IFERROR(__xludf.DUMMYFUNCTION("""COMPUTED_VALUE"""),"Other") -> Other | U20: =IFERROR(__xludf.DUMMYFUNCTION("""COMPUTED_VALUE"""),"Other") -> Other | V20: =IFERROR(__xludf.DUMMYFUNCTION("""COMPUTED_VALUE"""),"Other") -> Other | W20: =IFERROR(__xludf.DUMMYFUNCTION("""COMPUTED_VALUE"""),"Other") -> Other | X20: =IFERROR(__xludf.DUMMYFUNCTION("""COMPUTED_VALUE"""),"Other") -> Other | Y20: =IFERROR(__xludf.DUMMYFUNCTION("""COMPUTED_VALUE"""),"Other") -> Other | Z20: =IFERROR(__xludf.DUMMYFUNCTION("""COMPUTED_VALUE"""),"Other") -> Other | ... AD20: =IFERROR(__xludf.DUMMYFUNCTION("""COMPUTED_VALUE"""),"Other") -> Other
A21: =O21 -> minimax-m2 | H21: =R21 | L21: =IFERROR(__xludf.DUMMYFUNCTION("""COMPUTED_VALUE"""),"Qwen3-Coder") -> Qwen3-Coder | M21: =IFERROR(__xludf.DUMMYFUNCTION("""COMPUTED_VALUE"""),1.0) -> 1 | O21: minimax-m2 | P21: =IFERROR(__xludf.DUMMYFUNCTION("""COMPUTED_VALUE"""),"Other") -> Other | Q21: Other | S21: =IFERROR(__xludf.DUMMYFUNCTION("""COMPUTED_VALUE"""),"Other") -> Other | T21: =IFERROR(__xludf.DUMMYFUNCTION("""COMPUTED_VALUE"""),"Other") -> Other | U21: =IFERROR(__xludf.DUMMYFUNCTION("""COMPUTED_VALUE"""),"Other") -> Other | V21: =IFERROR(__xludf.DUMMYFUNCTION("""COMPUTED_VALUE"""),"Other") -> Other | W21: =IFERROR(__xludf.DUMMYFUNCTION("""COMPUTED_VALUE"""),"Other") -> Other | X21: =IFERROR(__xludf.DUMMYFUNCTION("""COMPUTED_VALUE"""),"Other") -> Other | Y21: =IFERROR(__xludf.DUMMYFUNCTION("""COMPUTED_VALUE"""),"Other") -> Other | Z21: =IFERROR(__xludf.DUMMYFUNCTION("""COMPUTED_VALUE"""),"Other") -> Other | ... AD21: =IFERROR(__xludf.DUMMYFUNCTION("""COMPUTED_VALUE"""),"Other") -> Other
A22: =O22 -> gpt-oss-safeguard | D22: https://llm-stats.com/models/gpt-oss-20b | F22: =VLOOKUP($D22,'LLM Stats list of Model'!$B$2:$N1003,4,false) | G22: =VLOOKUP($D22,'LLM Stats list of Model'!$B$2:$N1003,6,false) -> GPT OSS 20B | H22: =R22 -> GPT | I22: =VLOOKUP(H22,'Unique Organization'!C$2:D$13,2,FALSE) -> openai | L22: =IFERROR(__xludf.DUMMYFUNCTION("""COMPUTED_VALUE"""),"Qwen3-Coder-Next") -> Qwen3-Coder-Next | M22: =IFERROR(__xludf.DUMMYFUNCTION("""COMPUTED_VALUE"""),1.0) -> 1 | O22: gpt-oss-safeguard | P22: =IFERROR(__xludf.DUMMYFUNCTION("""COMPUTED_VALUE"""),"Other") -> Other | Q22: Other | R22: =IFERROR(__xludf.DUMMYFUNCTION("""COMPUTED_VALUE"""),"GPT") -> GPT | S22: =IFERROR(__xludf.DUMMYFUNCTION("""COMPUTED_VALUE"""),"Other") -> Other | T22: =IFERROR(__xludf.DUMMYFUNCTION("""COMPUTED_VALUE"""),"Other") -> Other | U22: =IFERROR(__xludf.DUMMYFUNCTION("""COMPUTED_VALUE"""),"Other") -> Other | V22: =IFERROR(__xludf.DUMMYFUNCTION("""COMPUTED_VALUE"""),"Other") -> Other | W22: =IFERROR(__xludf.DUMMYFUNCTION("""COMPUTED_VALUE"""),"Other") -> Other | X22: =IFERROR(__xludf.DUMMYFUNCTION("""COMPUTED_VALUE"""),"Other") -> Other | Y22: =IFERROR(__xludf.DUMMYFUNCTION("""COMPUTED_VALUE"""),"Other") -> Other | Z22: =IFERROR(__xludf.DUMMYFUNCTION("""COMPUTED_VALUE"""),"Other") -> Other | ... AC22: =IFERROR(__xludf.DUMMYFUNCTION("""COMPUTED_VALUE"""),"Other") -> Other | AD22: =IFERROR(__xludf.DUMMYFUNCTION("""COMPUTED_VALUE"""),"GPT") -> GPT
A23: =O23 -> Qwen3-VL | D23: https://llm-stats.com/models/qwen3-vl-4b-instruct | F23: =VLOOKUP($D23,'LLM Stats list of Model'!$B$2:$N1003,4,false) -> 2 | G23: =VLOOKUP($D23,'LLM Stats list of Model'!$B$2:$N1003,6,false) -> Qwen3 VL 4B Instruct | H23: =R23 -> Qwen | I23: =VLOOKUP(H23,'Unique Organization'!C$2:D$13,2,FALSE) -> qwen | L23: =IFERROR(__xludf.DUMMYFUNCTION("""COMPUTED_VALUE"""),"Qwen3-VL") -> Qwen3-VL | M23: =IFERROR(__xludf.DUMMYFUNCTION("""COMPUTED_VALUE"""),1.0) -> 1 | O23: Qwen3-VL | P23: =IFERROR(__xludf.DUMMYFUNCTION("""COMPUTED_VALUE"""),"Qwen") -> Qwen | Q23: Qwen | R23: =IFERROR(__xludf.DUMMYFUNCTION("""COMPUTED_VALUE"""),"Qwen") -> Qwen | S23: =IFERROR(__xludf.DUMMYFUNCTION("""COMPUTED_VALUE"""),"Other") -> Other | T23: =IFERROR(__xludf.DUMMYFUNCTION("""COMPUTED_VALUE"""),"Qwen") -> Qwen | U23: =IFERROR(__xludf.DUMMYFUNCTION("""COMPUTED_VALUE"""),"Other") -> Other | V23: =IFERROR(__xludf.DUMMYFUNCTION("""COMPUTED_VALUE"""),"Other") -> Other | W23: =IFERROR(__xludf.DUMMYFUNCTION("""COMPUTED_VALUE"""),"Other") -> Other | X23: =IFERROR(__xludf.DUMMYFUNCTION("""COMPUTED_VALUE"""),"Other") -> Other | Y23: =IFERROR(__xludf.DUMMYFUNCTION("""COMPUTED_VALUE"""),"Other") -> Other | Z23: =IFERROR(__xludf.DUMMYFUNCTION("""COMPUTED_VALUE"""),"Other") -> Other | AA23: =IFERROR(__xludf.DUMMYFUNCTION("""COMPUTED_VALUE"""),"Other") -> Other | AB23: =IFERROR(__xludf.DUMMYFUNCTION("""COMPUTED_VALUE"""),"Other") -> Other | ... AD23: =IFERROR(__xludf.DUMMYFUNCTION("""COMPUTED_VALUE"""),"Other") -> Other
A24: =O24 -> Granite 4.0 | H24: =R24 | L24: =IFERROR(__xludf.DUMMYFUNCTION("""COMPUTED_VALUE"""),"Qwen3.5") -> Qwen3.5 | M24: =IFERROR(__xludf.DUMMYFUNCTION("""COMPUTED_VALUE"""),1.0) -> 1 | O24: Granite 4.0 | P24: =IFERROR(__xludf.DUMMYFUNCTION("""COMPUTED_VALUE"""),"Other") -> Other | Q24: Other | S24: =IFERROR(__xludf.DUMMYFUNCTION("""COMPUTED_VALUE"""),"Other") -> Other | T24: =IFERROR(__xludf.DUMMYFUNCTION("""COMPUTED_VALUE"""),"Other") -> Other | U24: =IFERROR(__xludf.DUMMYFUNCTION("""COMPUTED_VALUE"""),"Other") -> Other | V24: =IFERROR(__xludf.DUMMYFUNCTION("""COMPUTED_VALUE"""),"Other") -> Other | W24: =IFERROR(__xludf.DUMMYFUNCTION("""COMPUTED_VALUE"""),"Other") -> Other | X24: =IFERROR(__xludf.DUMMYFUNCTION("""COMPUTED_VALUE"""),"Other") -> Other | Y24: =IFERROR(__xludf.DUMMYFUNCTION("""COMPUTED_VALUE"""),"Other") -> Other | Z24: =IFERROR(__xludf.DUMMYFUNCTION("""COMPUTED_VALUE"""),"Other") -> Other | ... AD24: =IFERROR(__xludf.DUMMYFUNCTION("""COMPUTED_VALUE"""),"Other") -> Other
A25: =O25 -> seed-oss | H25: =R25 | L25: =IFERROR(__xludf.DUMMYFUNCTION("""COMPUTED_VALUE"""),"Qwen3.6") -> Qwen3.6 | M25: =IFERROR(__xludf.DUMMYFUNCTION("""COMPUTED_VALUE"""),1.0) -> 1 | O25: seed-oss | P25: =IFERROR(__xludf.DUMMYFUNCTION("""COMPUTED_VALUE"""),"Other") -> Other | Q25: Other | S25: =IFERROR(__xludf.DUMMYFUNCTION("""COMPUTED_VALUE"""),"Other") -> Other | T25: =IFERROR(__xludf.DUMMYFUNCTION("""COMPUTED_VALUE"""),"Other") -> Other | U25: =IFERROR(__xludf.DUMMYFUNCTION("""COMPUTED_VALUE"""),"Other") -> Other | V25: =IFERROR(__xludf.DUMMYFUNCTION("""COMPUTED_VALUE"""),"Other") -> Other | W25: =IFERROR(__xludf.DUMMYFUNCTION("""COMPUTED_VALUE"""),"Other") -> Other | X25: =IFERROR(__xludf.DUMMYFUNCTION("""COMPUTED_VALUE"""),"Other") -> Other | Y25: =IFERROR(__xludf.DUMMYFUNCTION("""COMPUTED_VALUE"""),"Other") -> Other | Z25: =IFERROR(__xludf.DUMMYFUNCTION("""COMPUTED_VALUE"""),"Other") -> Other | ... AD25: =IFERROR(__xludf.DUMMYFUNCTION("""COMPUTED_VALUE"""),"Other") -> Other
A26: =O26 -> Qwen3 | D26: https://llm-stats.com/models/qwen3-32b | F26: =VLOOKUP($D26,'LLM Stats list of Model'!$B$2:$N1003,4,false) -> 2 | G26: =VLOOKUP($D26,'LLM Stats list of Model'!$B$2:$N1003,6,false) -> Qwen3 32B | H26: =R26 -> Qwen | I26: =VLOOKUP(H26,'Unique Organization'!C$2:D$13,2,FALSE) -> qwen | L26: =IFERROR(__xludf.DUMMYFUNCTION("""COMPUTED_VALUE"""),"Rnj-1") -> Rnj-1 | M26: =IFERROR(__xludf.DUMMYFUNCTION("""COMPUTED_VALUE"""),1.0) -> 1 | O26: Qwen3 | P26: =IFERROR(__xludf.DUMMYFUNCTION("""COMPUTED_VALUE"""),"Qwen") -> Qwen | Q26: Qwen | R26: =IFERROR(__xludf.DUMMYFUNCTION("""COMPUTED_VALUE"""),"Qwen") -> Qwen | S26: =IFERROR(__xludf.DUMMYFUNCTION("""COMPUTED_VALUE"""),"Other") -> Other | T26: =IFERROR(__xludf.DUMMYFUNCTION("""COMPUTED_VALUE"""),"Qwen") -> Qwen | U26: =IFERROR(__xludf.DUMMYFUNCTION("""COMPUTED_VALUE"""),"Other") -> Other | V26: =IFERROR(__xludf.DUMMYFUNCTION("""COMPUTED_VALUE"""),"Other") -> Other | W26: =IFERROR(__xludf.DUMMYFUNCTION("""COMPUTED_VALUE"""),"Other") -> Other | X26: =IFERROR(__xludf.DUMMYFUNCTION("""COMPUTED_VALUE"""),"Other") -> Other | Y26: =IFERROR(__xludf.DUMMYFUNCTION("""COMPUTED_VALUE"""),"Other") -> Other | Z26: =IFERROR(__xludf.DUMMYFUNCTION("""COMPUTED_VALUE"""),"Other") -> Other | AA26: =IFERROR(__xludf.DUMMYFUNCTION("""COMPUTED_VALUE"""),"Other") -> Other | AB26: =IFERROR(__xludf.DUMMYFUNCTION("""COMPUTED_VALUE"""),"Other") -> Other | ... AD26: =IFERROR(__xludf.DUMMYFUNCTION("""COMPUTED_VALUE"""),"Other") -> Other
A27: =O27 -> gpt-oss | D27: https://llm-stats.com/models/gpt-oss-20b | F27: =VLOOKUP($D27,'LLM Stats list of Model'!$B$2:$N1003,4,false) | G27: =VLOOKUP($D27,'LLM Stats list of Model'!$B$2:$N1003,6,false) -> GPT OSS 20B | H27: =R27 -> GPT | I27: =VLOOKUP(H27,'Unique Organization'!C$2:D$13,2,FALSE) -> openai | L27: =IFERROR(__xludf.DUMMYFUNCTION("""COMPUTED_VALUE"""),"deepseek-r1") -> deepseek-r1 | M27: =IFERROR(__xludf.DUMMYFUNCTION("""COMPUTED_VALUE"""),1.0) -> 1 | O27: gpt-oss | P27: =IFERROR(__xludf.DUMMYFUNCTION("""COMPUTED_VALUE"""),"Other") -> Other | Q27: Other | R27: =IFERROR(__xludf.DUMMYFUNCTION("""COMPUTED_VALUE"""),"GPT") -> GPT | S27: =IFERROR(__xludf.DUMMYFUNCTION("""COMPUTED_VALUE"""),"Other") -> Other | T27: =IFERROR(__xludf.DUMMYFUNCTION("""COMPUTED_VALUE"""),"Other") -> Other | U27: =IFERROR(__xludf.DUMMYFUNCTION("""COMPUTED_VALUE"""),"Other") -> Other | V27: =IFERROR(__xludf.DUMMYFUNCTION("""COMPUTED_VALUE"""),"Other") -> Other | W27: =IFERROR(__xludf.DUMMYFUNCTION("""COMPUTED_VALUE"""),"Other") -> Other | X27: =IFERROR(__xludf.DUMMYFUNCTION("""COMPUTED_VALUE"""),"Other") -> Other | Y27: =IFERROR(__xludf.DUMMYFUNCTION("""COMPUTED_VALUE"""),"Other") -> Other | Z27: =IFERROR(__xludf.DUMMYFUNCTION("""COMPUTED_VALUE"""),"Other") -> Other | ... AC27: =IFERROR(__xludf.DUMMYFUNCTION("""COMPUTED_VALUE"""),"Other") -> Other | AD27: =IFERROR(__xludf.DUMMYFUNCTION("""COMPUTED_VALUE"""),"GPT") -> GPT
A28: =O28 -> Qwen3-Coder | D28: https://llm-stats.com/models/qwen3-coder | F28: =VLOOKUP($D28,'LLM Stats list of Model'!$B$2:$N1003,4,false) -> 2 | G28: =VLOOKUP($D28,'LLM Stats list of Model'!$B$2:$N1003,6,false) -> Qwen3-Coder | H28: =R28 -> Qwen | I28: =VLOOKUP(H28,'Unique Organization'!C$2:D$13,2,FALSE) -> qwen | L28: =IFERROR(__xludf.DUMMYFUNCTION("""COMPUTED_VALUE"""),"gemma-3") -> gemma-3 | M28: =IFERROR(__xludf.DUMMYFUNCTION("""COMPUTED_VALUE"""),1.0) -> 1 | O28: Qwen3-Coder | P28: =IFERROR(__xludf.DUMMYFUNCTION("""COMPUTED_VALUE"""),"Qwen") -> Qwen | Q28: Qwen | R28: =IFERROR(__xludf.DUMMYFUNCTION("""COMPUTED_VALUE"""),"Qwen") -> Qwen | S28: =IFERROR(__xludf.DUMMYFUNCTION("""COMPUTED_VALUE"""),"Other") -> Other | T28: =IFERROR(__xludf.DUMMYFUNCTION("""COMPUTED_VALUE"""),"Qwen") -> Qwen | U28: =IFERROR(__xludf.DUMMYFUNCTION("""COMPUTED_VALUE"""),"Other") -> Other | V28: =IFERROR(__xludf.DUMMYFUNCTION("""COMPUTED_VALUE"""),"Other") -> Other | W28: =IFERROR(__xludf.DUMMYFUNCTION("""COMPUTED_VALUE"""),"Other") -> Other | X28: =IFERROR(__xludf.DUMMYFUNCTION("""COMPUTED_VALUE"""),"Other") -> Other | Y28: =IFERROR(__xludf.DUMMYFUNCTION("""COMPUTED_VALUE"""),"Other") -> Other | Z28: =IFERROR(__xludf.DUMMYFUNCTION("""COMPUTED_VALUE"""),"Other") -> Other | AA28: =IFERROR(__xludf.DUMMYFUNCTION("""COMPUTED_VALUE"""),"Other") -> Other | AB28: =IFERROR(__xludf.DUMMYFUNCTION("""COMPUTED_VALUE"""),"Other") -> Other | ... AD28: =IFERROR(__xludf.DUMMYFUNCTION("""COMPUTED_VALUE"""),"Other") -> Other
A29: =O29 -> Ernie-4.5 | H29: =R29 | L29: =IFERROR(__xludf.DUMMYFUNCTION("""COMPUTED_VALUE"""),"gemma-3n") -> gemma-3n | M29: =IFERROR(__xludf.DUMMYFUNCTION("""COMPUTED_VALUE"""),1.0) -> 1 | O29: Ernie-4.5 | P29: =IFERROR(__xludf.DUMMYFUNCTION("""COMPUTED_VALUE"""),"Other") -> Other | Q29: Other | S29: =IFERROR(__xludf.DUMMYFUNCTION("""COMPUTED_VALUE"""),"Other") -> Other | T29: =IFERROR(__xludf.DUMMYFUNCTION("""COMPUTED_VALUE"""),"Other") -> Other | U29: =IFERROR(__xludf.DUMMYFUNCTION("""COMPUTED_VALUE"""),"Other") -> Other | V29: =IFERROR(__xludf.DUMMYFUNCTION("""COMPUTED_VALUE"""),"Other") -> Other | W29: =IFERROR(__xludf.DUMMYFUNCTION("""COMPUTED_VALUE"""),"Other") -> Other | X29: =IFERROR(__xludf.DUMMYFUNCTION("""COMPUTED_VALUE"""),"Other") -> Other | Y29: =IFERROR(__xludf.DUMMYFUNCTION("""COMPUTED_VALUE"""),"Other") -> Other | Z29: =IFERROR(__xludf.DUMMYFUNCTION("""COMPUTED_VALUE"""),"Other") -> Other | ... AD29: =IFERROR(__xludf.DUMMYFUNCTION("""COMPUTED_VALUE"""),"Other") -> Other
A30: =O30 -> LFM2 | H30: =R30 | L30: =IFERROR(__xludf.DUMMYFUNCTION("""COMPUTED_VALUE"""),"gpt-oss") -> gpt-oss | M30: =IFERROR(__xludf.DUMMYFUNCTION("""COMPUTED_VALUE"""),1.0) -> 1 | O30: LFM2 | P30: =IFERROR(__xludf.DUMMYFUNCTION("""COMPUTED_VALUE"""),"Other") -> Other | Q30: Other | S30: =IFERROR(__xludf.DUMMYFUNCTION("""COMPUTED_VALUE"""),"Other") -> Other | T30: =IFERROR(__xludf.DUMMYFUNCTION("""COMPUTED_VALUE"""),"Other") -> Other | U30: =IFERROR(__xludf.DUMMYFUNCTION("""COMPUTED_VALUE"""),"Other") -> Other | V30: =IFERROR(__xludf.DUMMYFUNCTION("""COMPUTED_VALUE"""),"Other") -> Other | W30: =IFERROR(__xludf.DUMMYFUNCTION("""COMPUTED_VALUE"""),"Other") -> Other | X30: =IFERROR(__xludf.DUMMYFUNCTION("""COMPUTED_VALUE"""),"Other") -> Other | Y30: =IFERROR(__xludf.DUMMYFUNCTION("""COMPUTED_VALUE"""),"Other") -> Other | Z30: =IFERROR(__xludf.DUMMYFUNCTION("""COMPUTED_VALUE"""),"Other") -> Other | ... AD30: =IFERROR(__xludf.DUMMYFUNCTION("""COMPUTED_VALUE"""),"Other") -> Other
A31: =O31 -> Devstral | D31: https://llm-stats.com/models/devstral-small-2507 | F31: =VLOOKUP($D31,'LLM Stats list of Model'!$B$2:$N1003,4,false) | G31: =VLOOKUP($D31,'LLM Stats list of Model'!$B$2:$N1003,6,false) -> Devstral Small 1.1 | H31: =R31 -> Devstral | I31: =VLOOKUP(H31,'Unique Organization'!C$2:D$13,2,FALSE) -> mistral | L31: =IFERROR(__xludf.DUMMYFUNCTION("""COMPUTED_VALUE"""),"gpt-oss-safeguard") -> gpt-oss-safeguard | M31: =IFERROR(__xludf.DUMMYFUNCTION("""COMPUTED_VALUE"""),1.0) -> 1 | O31: Devstral | P31: =IFERROR(__xludf.DUMMYFUNCTION("""COMPUTED_VALUE"""),"Other") -> Other | Q31: Other | R31: =IFERROR(__xludf.DUMMYFUNCTION("""COMPUTED_VALUE"""),"Devstral") -> Devstral | S31: =IFERROR(__xludf.DUMMYFUNCTION("""COMPUTED_VALUE"""),"Other") -> Other | T31: =IFERROR(__xludf.DUMMYFUNCTION("""COMPUTED_VALUE"""),"Other") -> Other | U31: =IFERROR(__xludf.DUMMYFUNCTION("""COMPUTED_VALUE"""),"Other") -> Other | V31: =IFERROR(__xludf.DUMMYFUNCTION("""COMPUTED_VALUE"""),"Other") -> Other | W31: =IFERROR(__xludf.DUMMYFUNCTION("""COMPUTED_VALUE"""),"Other") -> Other | X31: =IFERROR(__xludf.DUMMYFUNCTION("""COMPUTED_VALUE"""),"Other") -> Other | Y31: =IFERROR(__xludf.DUMMYFUNCTION("""COMPUTED_VALUE"""),"Other") -> Other | Z31: =IFERROR(__xludf.DUMMYFUNCTION("""COMPUTED_VALUE"""),"Other") -> Other | AA31: =IFERROR(__xludf.DUMMYFUNCTION("""COMPUTED_VALUE"""),"Other") -> Other | AB31: =IFERROR(__xludf.DUMMYFUNCTION("""COMPUTED_VALUE"""),"Devstral") -> Devstral | AC31: =IFERROR(__xludf.DUMMYFUNCTION("""COMPUTED_VALUE"""),"Other") -> Other | AD31: =IFERROR(__xludf.DUMMYFUNCTION("""COMPUTED_VALUE"""),"Other") -> Other
A32: =O32 -> gemma-3n | D32: https://llm-stats.com/models/gemma-3n-e2b | F32: =VLOOKUP($D32,'LLM Stats list of Model'!$B$2:$N1003,4,false) | G32: =VLOOKUP($D32,'LLM Stats list of Model'!$B$2:$N1003,6,false) -> Gemma 3n E2B | H32: =R32 -> Gemma | I32: =VLOOKUP(H32,'Unique Organization'!C$2:D$13,2,FALSE) -> google | L32: =IFERROR(__xludf.DUMMYFUNCTION("""COMPUTED_VALUE"""),"minimax-m2") -> minimax-m2 | M32: =IFERROR(__xludf.DUMMYFUNCTION("""COMPUTED_VALUE"""),1.0) -> 1 | O32: gemma-3n | P32: =IFERROR(__xludf.DUMMYFUNCTION("""COMPUTED_VALUE"""),"Gemma") -> Gemma | Q32: Other | R32: =IFERROR(__xludf.DUMMYFUNCTION("""COMPUTED_VALUE"""),"Gemma") -> Gemma | S32: =IFERROR(__xludf.DUMMYFUNCTION("""COMPUTED_VALUE"""),"Other") -> Other | T32: =IFERROR(__xludf.DUMMYFUNCTION("""COMPUTED_VALUE"""),"Other") -> Other | U32: =IFERROR(__xludf.DUMMYFUNCTION("""COMPUTED_VALUE"""),"Gemma") -> Gemma | V32: =IFERROR(__xludf.DUMMYFUNCTION("""COMPUTED_VALUE"""),"Other") -> Other | W32: =IFERROR(__xludf.DUMMYFUNCTION("""COMPUTED_VALUE"""),"Other") -> Other | X32: =IFERROR(__xludf.DUMMYFUNCTION("""COMPUTED_VALUE"""),"Other") -> Other | Y32: =IFERROR(__xludf.DUMMYFUNCTION("""COMPUTED_VALUE"""),"Other") -> Other | Z32: =IFERROR(__xludf.DUMMYFUNCTION("""COMPUTED_VALUE"""),"Other") -> Other | AA32: =IFERROR(__xludf.DUMMYFUNCTION("""COMPUTED_VALUE"""),"Other") -> Other | AB32: =IFERROR(__xludf.DUMMYFUNCTION("""COMPUTED_VALUE"""),"Other") -> Other | AC32: =IFERROR(__xludf.DUMMYFUNCTION("""COMPUTED_VALUE"""),"Other") -> Other | AD32: =IFERROR(__xludf.DUMMYFUNCTION("""COMPUTED_VALUE"""),"Other") -> Other
A33: =O33 -> Mistral Small | D33: https://llm-stats.com/models/mistral-small-latest | F33: =VLOOKUP($D33,'LLM Stats list of Model'!$B$2:$N1003,4,false) | G33: =VLOOKUP($D33,'LLM Stats list of Model'!$B$2:$N1003,6,false) -> Mistral Small 4 | H33: =R33 -> Mistral | I33: =VLOOKUP(H33,'Unique Organization'!C$2:D$13,2,FALSE) -> mistral | L33: =IFERROR(__xludf.DUMMYFUNCTION("""COMPUTED_VALUE"""),"mistral-nemo") -> mistral-nemo | M33: =IFERROR(__xludf.DUMMYFUNCTION("""COMPUTED_VALUE"""),1.0) -> 1 | O33: Mistral Small | P33: =IFERROR(__xludf.DUMMYFUNCTION("""COMPUTED_VALUE"""),"Other") -> Other | Q33: Other | R33: =IFERROR(__xludf.DUMMYFUNCTION("""COMPUTED_VALUE"""),"Mistral") -> Mistral | S33: =IFERROR(__xludf.DUMMYFUNCTION("""COMPUTED_VALUE"""),"Other") -> Other | T33: =IFERROR(__xludf.DUMMYFUNCTION("""COMPUTED_VALUE"""),"Other") -> Other | U33: =IFERROR(__xludf.DUMMYFUNCTION("""COMPUTED_VALUE"""),"Other") -> Other | V33: =IFERROR(__xludf.DUMMYFUNCTION("""COMPUTED_VALUE"""),"Other") -> Other | W33: =IFERROR(__xludf.DUMMYFUNCTION("""COMPUTED_VALUE"""),"Other") -> Other | X33: =IFERROR(__xludf.DUMMYFUNCTION("""COMPUTED_VALUE"""),"Mistral") -> Mistral | Y33: =IFERROR(__xludf.DUMMYFUNCTION("""COMPUTED_VALUE"""),"Other") -> Other | Z33: =IFERROR(__xludf.DUMMYFUNCTION("""COMPUTED_VALUE"""),"Other") -> Other | AA33: =IFERROR(__xludf.DUMMYFUNCTION("""COMPUTED_VALUE"""),"Other") -> Other | AB33: =IFERROR(__xludf.DUMMYFUNCTION("""COMPUTED_VALUE"""),"Other") -> Other | AC33: =IFERROR(__xludf.DUMMYFUNCTION("""COMPUTED_VALUE"""),"Other") -> Other | AD33: =IFERROR(__xludf.DUMMYFUNCTION("""COMPUTED_VALUE"""),"Other") -> Other
A34: =O34 -> Magistral | D34: https://llm-stats.com/models/magistral-small-2506 | F34: =VLOOKUP($D34,'LLM Stats list of Model'!$B$2:$N1003,4,false) | G34: =VLOOKUP($D34,'LLM Stats list of Model'!$B$2:$N1003,6,false) -> Magistral Small 2506 | H34: =R34 -> Magistral | I34: =VLOOKUP(H34,'Unique Organization'!C$2:D$13,2,FALSE) -> mistral | L34: =IFERROR(__xludf.DUMMYFUNCTION("""COMPUTED_VALUE"""),"olmOCR") -> olmOCR | M34: =IFERROR(__xludf.DUMMYFUNCTION("""COMPUTED_VALUE"""),1.0) -> 1 | O34: Magistral | P34: =IFERROR(__xludf.DUMMYFUNCTION("""COMPUTED_VALUE"""),"Other") -> Other | Q34: Other | R34: =IFERROR(__xludf.DUMMYFUNCTION("""COMPUTED_VALUE"""),"Magistral") -> Magistral | S34: =IFERROR(__xludf.DUMMYFUNCTION("""COMPUTED_VALUE"""),"Other") -> Other | T34: =IFERROR(__xludf.DUMMYFUNCTION("""COMPUTED_VALUE"""),"Other") -> Other | U34: =IFERROR(__xludf.DUMMYFUNCTION("""COMPUTED_VALUE"""),"Other") -> Other | V34: =IFERROR(__xludf.DUMMYFUNCTION("""COMPUTED_VALUE"""),"Other") -> Other | W34: =IFERROR(__xludf.DUMMYFUNCTION("""COMPUTED_VALUE"""),"Other") -> Other | X34: =IFERROR(__xludf.DUMMYFUNCTION("""COMPUTED_VALUE"""),"Other") -> Other | Y34: =IFERROR(__xludf.DUMMYFUNCTION("""COMPUTED_VALUE"""),"Other") -> Other | Z34: =IFERROR(__xludf.DUMMYFUNCTION("""COMPUTED_VALUE"""),"Magistral") -> Magistral | AA34: =IFERROR(__xludf.DUMMYFUNCTION("""COMPUTED_VALUE"""),"Other") -> Other | AB34: =IFERROR(__xludf.DUMMYFUNCTION("""COMPUTED_VALUE"""),"Other") -> Other | AC34: =IFERROR(__xludf.DUMMYFUNCTION("""COMPUTED_VALUE"""),"Other") -> Other | AD34: =IFERROR(__xludf.DUMMYFUNCTION("""COMPUTED_VALUE"""),"Other") -> Other
A35: =O35 -> mistral-nemo | D35: https://llm-stats.com/models/mistral-nemo-instruct-2407 | F35: =VLOOKUP($D35,'LLM Stats list of Model'!$B$2:$N1003,4,false) | G35: =VLOOKUP($D35,'LLM Stats list of Model'!$B$2:$N1003,6,false) -> Mistral NeMo Instruct | H35: =R35 -> Mistral | I35: =VLOOKUP(H35,'Unique Organization'!C$2:D$13,2,FALSE) -> mistral | L35: =IFERROR(__xludf.DUMMYFUNCTION("""COMPUTED_VALUE"""),"phi-4") -> phi-4 | M35: =IFERROR(__xludf.DUMMYFUNCTION("""COMPUTED_VALUE"""),1.0) -> 1 | O35: mistral-nemo | P35: =IFERROR(__xludf.DUMMYFUNCTION("""COMPUTED_VALUE"""),"Other") -> Other | Q35: Other | R35: =IFERROR(__xludf.DUMMYFUNCTION("""COMPUTED_VALUE"""),"Mistral") -> Mistral | S35: =IFERROR(__xludf.DUMMYFUNCTION("""COMPUTED_VALUE"""),"Other") -> Other | T35: =IFERROR(__xludf.DUMMYFUNCTION("""COMPUTED_VALUE"""),"Other") -> Other | U35: =IFERROR(__xludf.DUMMYFUNCTION("""COMPUTED_VALUE"""),"Other") -> Other | V35: =IFERROR(__xludf.DUMMYFUNCTION("""COMPUTED_VALUE"""),"Other") -> Other | W35: =IFERROR(__xludf.DUMMYFUNCTION("""COMPUTED_VALUE"""),"Other") -> Other | X35: =IFERROR(__xludf.DUMMYFUNCTION("""COMPUTED_VALUE"""),"Mistral") -> Mistral | Y35: =IFERROR(__xludf.DUMMYFUNCTION("""COMPUTED_VALUE"""),"Other") -> Other | Z35: =IFERROR(__xludf.DUMMYFUNCTION("""COMPUTED_VALUE"""),"Other") -> Other | AA35: =IFERROR(__xludf.DUMMYFUNCTION("""COMPUTED_VALUE"""),"Other") -> Other | AB35: =IFERROR(__xludf.DUMMYFUNCTION("""COMPUTED_VALUE"""),"Other") -> Other | AC35: =IFERROR(__xludf.DUMMYFUNCTION("""COMPUTED_VALUE"""),"Other") -> Other | AD35: =IFERROR(__xludf.DUMMYFUNCTION("""COMPUTED_VALUE"""),"Other") -> Other
A36: =O36 -> qwen2.5-vl | D36: https://llm-stats.com/models/qwen2.5-vl-7b | F36: =VLOOKUP($D36,'LLM Stats list of Model'!$B$2:$N1003,4,false) -> 1 | G36: =VLOOKUP($D36,'LLM Stats list of Model'!$B$2:$N1003,6,false) -> Qwen2.5 VL 7B Instruct | H36: =R36 -> Qwen | I36: =VLOOKUP(H36,'Unique Organization'!C$2:D$13,2,FALSE) -> qwen | L36: =IFERROR(__xludf.DUMMYFUNCTION("""COMPUTED_VALUE"""),"phi-4-reasoning") -> phi-4-reasoning | M36: =IFERROR(__xludf.DUMMYFUNCTION("""COMPUTED_VALUE"""),1.0) -> 1 | O36: qwen2.5-vl | P36: =IFERROR(__xludf.DUMMYFUNCTION("""COMPUTED_VALUE"""),"Qwen") -> Qwen | Q36: Qwen | R36: =IFERROR(__xludf.DUMMYFUNCTION("""COMPUTED_VALUE"""),"Qwen") -> Qwen | S36: =IFERROR(__xludf.DUMMYFUNCTION("""COMPUTED_VALUE"""),"Other") -> Other | T36: =IFERROR(__xludf.DUMMYFUNCTION("""COMPUTED_VALUE"""),"Qwen") -> Qwen | U36: =IFERROR(__xludf.DUMMYFUNCTION("""COMPUTED_VALUE"""),"Other") -> Other | V36: =IFERROR(__xludf.DUMMYFUNCTION("""COMPUTED_VALUE"""),"Other") -> Other | W36: =IFERROR(__xludf.DUMMYFUNCTION("""COMPUTED_VALUE"""),"Other") -> Other | X36: =IFERROR(__xludf.DUMMYFUNCTION("""COMPUTED_VALUE"""),"Other") -> Other | Y36: =IFERROR(__xludf.DUMMYFUNCTION("""COMPUTED_VALUE"""),"Other") -> Other | Z36: =IFERROR(__xludf.DUMMYFUNCTION("""COMPUTED_VALUE"""),"Other") -> Other | AA36: =IFERROR(__xludf.DUMMYFUNCTION("""COMPUTED_VALUE"""),"Other") -> Other | AB36: =IFERROR(__xludf.DUMMYFUNCTION("""COMPUTED_VALUE"""),"Other") -> Other | ... AD36: =IFERROR(__xludf.DUMMYFUNCTION("""COMPUTED_VALUE"""),"Other") -> Other
A37: =O37 -> gemma-3 | D37: https://llm-stats.com/models/gemma-3-1b-it | F37: =VLOOKUP($D37,'LLM Stats list of Model'!$B$2:$N1003,4,false) | G37: =VLOOKUP($D37,'LLM Stats list of Model'!$B$2:$N1003,6,false) -> Gemma 3 1B | H37: =R37 -> Gemma | I37: =VLOOKUP(H37,'Unique Organization'!C$2:D$13,2,FALSE) -> google | L37: =IFERROR(__xludf.DUMMYFUNCTION("""COMPUTED_VALUE"""),"qwen2.5-vl") -> qwen2.5-vl | M37: =IFERROR(__xludf.DUMMYFUNCTION("""COMPUTED_VALUE"""),1.0) -> 1 | O37: gemma-3 | P37: =IFERROR(__xludf.DUMMYFUNCTION("""COMPUTED_VALUE"""),"Gemma") -> Gemma | Q37: Other | R37: =IFERROR(__xludf.DUMMYFUNCTION("""COMPUTED_VALUE"""),"Gemma") -> Gemma | S37: =IFERROR(__xludf.DUMMYFUNCTION("""COMPUTED_VALUE"""),"Other") -> Other | T37: =IFERROR(__xludf.DUMMYFUNCTION("""COMPUTED_VALUE"""),"Other") -> Other | U37: =IFERROR(__xludf.DUMMYFUNCTION("""COMPUTED_VALUE"""),"Gemma") -> Gemma | V37: =IFERROR(__xludf.DUMMYFUNCTION("""COMPUTED_VALUE"""),"Other") -> Other | W37: =IFERROR(__xludf.DUMMYFUNCTION("""COMPUTED_VALUE"""),"Other") -> Other | X37: =IFERROR(__xludf.DUMMYFUNCTION("""COMPUTED_VALUE"""),"Other") -> Other | Y37: =IFERROR(__xludf.DUMMYFUNCTION("""COMPUTED_VALUE"""),"Other") -> Other | Z37: =IFERROR(__xludf.DUMMYFUNCTION("""COMPUTED_VALUE"""),"Other") -> Other | AA37: =IFERROR(__xludf.DUMMYFUNCTION("""COMPUTED_VALUE"""),"Other") -> Other | AB37: =IFERROR(__xludf.DUMMYFUNCTION("""COMPUTED_VALUE"""),"Other") -> Other | AC37: =IFERROR(__xludf.DUMMYFUNCTION("""COMPUTED_VALUE"""),"Other") -> Other | AD37: =IFERROR(__xludf.DUMMYFUNCTION("""COMPUTED_VALUE"""),"Other") -> Other
A38: =O38 -> phi-4-reasoning | D38: https://llm-stats.com/models/phi-4-reasoning | F38: =VLOOKUP($D38,'LLM Stats list of Model'!$B$2:$N1003,4,false) | G38: =VLOOKUP($D38,'LLM Stats list of Model'!$B$2:$N1003,6,false) -> Phi 4 Reasoning | H38: =R38 -> Phi | I38: =VLOOKUP(H38,'Unique Organization'!C$2:D$13,2,FALSE) -> microsoft | L38: =IFERROR(__xludf.DUMMYFUNCTION("""COMPUTED_VALUE"""),"seed-oss") -> seed-oss | M38: =IFERROR(__xludf.DUMMYFUNCTION("""COMPUTED_VALUE"""),1.0) -> 1 | O38: phi-4-reasoning | P38: =IFERROR(__xludf.DUMMYFUNCTION("""COMPUTED_VALUE"""),"Other") -> Other | Q38: Other | R38: =IFERROR(__xludf.DUMMYFUNCTION("""COMPUTED_VALUE"""),"Phi") -> Phi | S38: =IFERROR(__xludf.DUMMYFUNCTION("""COMPUTED_VALUE"""),"Other") -> Other | T38: =IFERROR(__xludf.DUMMYFUNCTION("""COMPUTED_VALUE"""),"Other") -> Other | U38: =IFERROR(__xludf.DUMMYFUNCTION("""COMPUTED_VALUE"""),"Other") -> Other | V38: =IFERROR(__xludf.DUMMYFUNCTION("""COMPUTED_VALUE"""),"Other") -> Other | W38: =IFERROR(__xludf.DUMMYFUNCTION("""COMPUTED_VALUE"""),"Phi") -> Phi | X38: =IFERROR(__xludf.DUMMYFUNCTION("""COMPUTED_VALUE"""),"Other") -> Other | Y38: =IFERROR(__xludf.DUMMYFUNCTION("""COMPUTED_VALUE"""),"Other") -> Other | Z38: =IFERROR(__xludf.DUMMYFUNCTION("""COMPUTED_VALUE"""),"Other") -> Other | AA38: =IFERROR(__xludf.DUMMYFUNCTION("""COMPUTED_VALUE"""),"Other") -> Other | AB38: =IFERROR(__xludf.DUMMYFUNCTION("""COMPUTED_VALUE"""),"Other") -> Other | AC38: =IFERROR(__xludf.DUMMYFUNCTION("""COMPUTED_VALUE"""),"Other") -> Other | AD38: =IFERROR(__xludf.DUMMYFUNCTION("""COMPUTED_VALUE"""),"Other") -> Other
A39: =O39 -> phi-4 | D39: https://llm-stats.com/models/phi-4 | F39: =VLOOKUP($D39,'LLM Stats list of Model'!$B$2:$N1003,4,false) | G39: =VLOOKUP($D39,'LLM Stats list of Model'!$B$2:$N1003,6,false) -> Phi 4 | H39: =R39 -> Phi | I39: =VLOOKUP(H39,'Unique Organization'!C$2:D$13,2,FALSE) -> microsoft | O39: phi-4 | P39: =IFERROR(__xludf.DUMMYFUNCTION("""COMPUTED_VALUE"""),"Other") -> Other | Q39: Other | R39: =IFERROR(__xludf.DUMMYFUNCTION("""COMPUTED_VALUE"""),"Phi") -> Phi | S39: =IFERROR(__xludf.DUMMYFUNCTION("""COMPUTED_VALUE"""),"Other") -> Other | T39: =IFERROR(__xludf.DUMMYFUNCTION("""COMPUTED_VALUE"""),"Other") -> Other | U39: =IFERROR(__xludf.DUMMYFUNCTION("""COMPUTED_VALUE"""),"Other") -> Other | V39: =IFERROR(__xludf.DUMMYFUNCTION("""COMPUTED_VALUE"""),"Other") -> Other | W39: =IFERROR(__xludf.DUMMYFUNCTION("""COMPUTED_VALUE"""),"Phi") -> Phi | X39: =IFERROR(__xludf.DUMMYFUNCTION("""COMPUTED_VALUE"""),"Other") -> Other | Y39: =IFERROR(__xludf.DUMMYFUNCTION("""COMPUTED_VALUE"""),"Other") -> Other | Z39: =IFERROR(__xludf.DUMMYFUNCTION("""COMPUTED_VALUE"""),"Other") -> Other | AA39: =IFERROR(__xludf.DUMMYFUNCTION("""COMPUTED_VALUE"""),"Other") -> Other | AB39: =IFERROR(__xludf.DUMMYFUNCTION("""COMPUTED_VALUE"""),"Other") -> Other | AC39: =IFERROR(__xludf.DUMMYFUNCTION("""COMPUTED_VALUE"""),"Other") -> Other | AD39: =IFERROR(__xludf.DUMMYFUNCTION("""COMPUTED_VALUE"""),"Other") -> Other
A40: =O40 -> Codestral | D40: https://llm-stats.com/models/codestral-22b | F40: =VLOOKUP($D40,'LLM Stats list of Model'!$B$2:$N1003,4,false) | G40: =VLOOKUP($D40,'LLM Stats list of Model'!$B$2:$N1003,6,false) -> Codestral-22B | H40: =R40 -> Codestral | I40: =VLOOKUP(H40,'Unique Organization'!C$2:D$13,2,FALSE) -> mistral | O40: Codestral | P40: =IFERROR(__xludf.DUMMYFUNCTION("""COMPUTED_VALUE"""),"Other") -> Other | Q40: Other | R40: =IFERROR(__xludf.DUMMYFUNCTION("""COMPUTED_VALUE"""),"Codestral") -> Codestral | S40: =IFERROR(__xludf.DUMMYFUNCTION("""COMPUTED_VALUE"""),"Other") -> Other | T40: =IFERROR(__xludf.DUMMYFUNCTION("""COMPUTED_VALUE"""),"Other") -> Other | U40: =IFERROR(__xludf.DUMMYFUNCTION("""COMPUTED_VALUE"""),"Other") -> Other | V40: =IFERROR(__xludf.DUMMYFUNCTION("""COMPUTED_VALUE"""),"Other") -> Other | W40: =IFERROR(__xludf.DUMMYFUNCTION("""COMPUTED_VALUE"""),"Other") -> Other | X40: =IFERROR(__xludf.DUMMYFUNCTION("""COMPUTED_VALUE"""),"Other") -> Other | Y40: =IFERROR(__xludf.DUMMYFUNCTION("""COMPUTED_VALUE"""),"Codestral") -> Codestral | Z40: =IFERROR(__xludf.DUMMYFUNCTION("""COMPUTED_VALUE"""),"Other") -> Other | AA40: =IFERROR(__xludf.DUMMYFUNCTION("""COMPUTED_VALUE"""),"Other") -> Other | AB40: =IFERROR(__xludf.DUMMYFUNCTION("""COMPUTED_VALUE"""),"Other") -> Other | AC40: =IFERROR(__xludf.DUMMYFUNCTION("""COMPUTED_VALUE"""),"Other") -> Other | AD40: =IFERROR(__xludf.DUMMYFUNCTION("""COMPUTED_VALUE"""),"Other") -> Other
A41: =O41 -> Mistral | D41: https://llm-stats.com/models/mistral-small-latest | F41: =VLOOKUP($D41,'LLM Stats list of Model'!$B$2:$N1003,4,false) | G41: =VLOOKUP($D41,'LLM Stats list of Model'!$B$2:$N1003,6,false) -> Mistral Small 4 | H41: =R41 -> Mistral | I41: =VLOOKUP(H41,'Unique Organization'!C$2:D$13,2,FALSE) -> mistral | O41: Mistral | P41: =IFERROR(__xludf.DUMMYFUNCTION("""COMPUTED_VALUE"""),"Other") -> Other | Q41: Other | R41: =IFERROR(__xludf.DUMMYFUNCTION("""COMPUTED_VALUE"""),"Mistral") -> Mistral | S41: =IFERROR(__xludf.DUMMYFUNCTION("""COMPUTED_VALUE"""),"Other") -> Other | T41: =IFERROR(__xludf.DUMMYFUNCTION("""COMPUTED_VALUE"""),"Other") -> Other | U41: =IFERROR(__xludf.DUMMYFUNCTION("""COMPUTED_VALUE"""),"Other") -> Other | V41: =IFERROR(__xludf.DUMMYFUNCTION("""COMPUTED_VALUE"""),"Other") -> Other | W41: =IFERROR(__xludf.DUMMYFUNCTION("""COMPUTED_VALUE"""),"Other") -> Other | X41: =IFERROR(__xludf.DUMMYFUNCTION("""COMPUTED_VALUE"""),"Mistral") -> Mistral | Y41: =IFERROR(__xludf.DUMMYFUNCTION("""COMPUTED_VALUE"""),"Other") -> Other | Z41: =IFERROR(__xludf.DUMMYFUNCTION("""COMPUTED_VALUE"""),"Other") -> Other | AA41: =IFERROR(__xludf.DUMMYFUNCTION("""COMPUTED_VALUE"""),"Other") -> Other | AB41: =IFERROR(__xludf.DUMMYFUNCTION("""COMPUTED_VALUE"""),"Other") -> Other | AC41: =IFERROR(__xludf.DUMMYFUNCTION("""COMPUTED_VALUE"""),"Other") -> Other | AD41: =IFERROR(__xludf.DUMMYFUNCTION("""COMPUTED_VALUE"""),"Other") -> Other
A42: =O42 -> Qwen3 (1st Generation) | D42: https://llm-stats.com/models/qwen3-32b | F42: =VLOOKUP($D42,'LLM Stats list of Model'!$B$2:$N1003,4,false) -> 2 | G42: =VLOOKUP($D42,'LLM Stats list of Model'!$B$2:$N1003,6,false) -> Qwen3 32B | H42: =R42 -> Qwen | I42: =VLOOKUP(H42,'Unique Organization'!C$2:D$13,2,FALSE) -> qwen | O42: Qwen3 (1st Generation) | P42: =IFERROR(__xludf.DUMMYFUNCTION("""COMPUTED_VALUE"""),"Qwen") -> Qwen | Q42: Qwen | R42: =IFERROR(__xludf.DUMMYFUNCTION("""COMPUTED_VALUE"""),"Qwen") -> Qwen | S42: =IFERROR(__xludf.DUMMYFUNCTION("""COMPUTED_VALUE"""),"Other") -> Other | T42: =IFERROR(__xludf.DUMMYFUNCTION("""COMPUTED_VALUE"""),"Qwen") -> Qwen | U42: =IFERROR(__xludf.DUMMYFUNCTION("""COMPUTED_VALUE"""),"Other") -> Other | V42: =IFERROR(__xludf.DUMMYFUNCTION("""COMPUTED_VALUE"""),"Other") -> Other | W42: =IFERROR(__xludf.DUMMYFUNCTION("""COMPUTED_VALUE"""),"Other") -> Other | X42: =IFERROR(__xludf.DUMMYFUNCTION("""COMPUTED_VALUE"""),"Other") -> Other | Y42: =IFERROR(__xludf.DUMMYFUNCTION("""COMPUTED_VALUE"""),"Other") -> Other | Z42: =IFERROR(__xludf.DUMMYFUNCTION("""COMPUTED_VALUE"""),"Other") -> Other | AA42: =IFERROR(__xludf.DUMMYFUNCTION("""COMPUTED_VALUE"""),"Other") -> Other | AB42: =IFERROR(__xludf.DUMMYFUNCTION("""COMPUTED_VALUE"""),"Other") -> Other | ... AD42: =IFERROR(__xludf.DUMMYFUNCTION("""COMPUTED_VALUE"""),"Other") -> Other
A43: =O43 -> deepseek-r1 | D43: https://llm-stats.com/models/deepseek-r1 | F43: =VLOOKUP($D43,'LLM Stats list of Model'!$B$2:$N1003,4,false) | G43: =VLOOKUP($D43,'LLM Stats list of Model'!$B$2:$N1003,6,false) -> DeepSeek-R1 | H43: =R43 -> Deepseek | I43: =VLOOKUP(H43,'Unique Organization'!C$2:D$13,2,FALSE) -> deepseek | O43: deepseek-r1 | P43: =IFERROR(__xludf.DUMMYFUNCTION("""COMPUTED_VALUE"""),"Other") -> Other | Q43: Other | R43: =IFERROR(__xludf.DUMMYFUNCTION("""COMPUTED_VALUE"""),"Deepseek") -> Deepseek | S43: =IFERROR(__xludf.DUMMYFUNCTION("""COMPUTED_VALUE"""),"Other") -> Other | T43: =IFERROR(__xludf.DUMMYFUNCTION("""COMPUTED_VALUE"""),"Other") -> Other | U43: =IFERROR(__xludf.DUMMYFUNCTION("""COMPUTED_VALUE"""),"Other") -> Other | V43: =IFERROR(__xludf.DUMMYFUNCTION("""COMPUTED_VALUE"""),"Other") -> Other | W43: =IFERROR(__xludf.DUMMYFUNCTION("""COMPUTED_VALUE"""),"Other") -> Other | X43: =IFERROR(__xludf.DUMMYFUNCTION("""COMPUTED_VALUE"""),"Other") -> Other | Y43: =IFERROR(__xludf.DUMMYFUNCTION("""COMPUTED_VALUE"""),"Other") -> Other | Z43: =IFERROR(__xludf.DUMMYFUNCTION("""COMPUTED_VALUE"""),"Other") -> Other | AA43: =IFERROR(__xludf.DUMMYFUNCTION("""COMPUTED_VALUE"""),"Deepseek") -> Deepseek | AB43: =IFERROR(__xludf.DUMMYFUNCTION("""COMPUTED_VALUE"""),"Other") -> Other | AC43: =IFERROR(__xludf.DUMMYFUNCTION("""COMPUTED_VALUE"""),"Other") -> Other | AD43: =IFERROR(__xludf.DUMMYFUNCTION("""COMPUTED_VALUE"""),"Other") -> Other
A44: Extra | P44: =IFERROR(__xludf.DUMMYFUNCTION("""COMPUTED_VALUE"""),"") | R44: =IFERROR(__xludf.DUMMYFUNCTION("""COMPUTED_VALUE"""),"") | S44: =IFERROR(__xludf.DUMMYFUNCTION("""COMPUTED_VALUE"""),"") | T44: =IFERROR(__xludf.DUMMYFUNCTION("""COMPUTED_VALUE"""),"") | U44: =IFERROR(__xludf.DUMMYFUNCTION("""COMPUTED_VALUE"""),"") | V44: =IFERROR(__xludf.DUMMYFUNCTION("""COMPUTED_VALUE"""),"") | W44: =IFERROR(__xludf.DUMMYFUNCTION("""COMPUTED_VALUE"""),"") | X44: =IFERROR(__xludf.DUMMYFUNCTION("""COMPUTED_VALUE"""),"") | Y44: =IFERROR(__xludf.DUMMYFUNCTION("""COMPUTED_VALUE"""),"") | ... AD44: =IFERROR(__xludf.DUMMYFUNCTION("""COMPUTED_VALUE"""),"")
A45: =O45 | B45: =P45 | D45: https://llm-stats.com/models/gemma-4-e4b-it | E45: 6.33 | F45: =VLOOKUP($D45,'LLM Stats list of Model'!$B$2:$N1003,4,false) | G45: =VLOOKUP($D45,'LLM Stats list of Model'!$B$2:$N1003,6,false) -> Gemma 4 E4B | H45: =R45 | P45: =IFERROR(__xludf.DUMMYFUNCTION("""COMPUTED_VALUE"""),"") | R45: =IFERROR(__xludf.DUMMYFUNCTION("""COMPUTED_VALUE"""),"") | S45: =IFERROR(__xludf.DUMMYFUNCTION("""COMPUTED_VALUE"""),"") | T45: =IFERROR(__xludf.DUMMYFUNCTION("""COMPUTED_VALUE"""),"") | U45: =IFERROR(__xludf.DUMMYFUNCTION("""COMPUTED_VALUE"""),"") | V45: =IFERROR(__xludf.DUMMYFUNCTION("""COMPUTED_VALUE"""),"") | W45: =IFERROR(__xludf.DUMMYFUNCTION("""COMPUTED_VALUE"""),"") | X45: =IFERROR(__xludf.DUMMYFUNCTION("""COMPUTED_VALUE"""),"") | Y45: =IFERROR(__xludf.DUMMYFUNCTION("""COMPUTED_VALUE"""),"") | ... AD45: =IFERROR(__xludf.DUMMYFUNCTION("""COMPUTED_VALUE"""),"")
A46: =O46 | B46: =P46 | C46: Yes | D46: https://llm-stats.com/models/gemma-4-e2b-it | E46: 4.41 | F46: =VLOOKUP($D46,'LLM Stats list of Model'!$B$2:$N1003,4,false) | G46: =VLOOKUP($D46,'LLM Stats list of Model'!$B$2:$N1003,6,false) -> Gemma 4 E2B | P46: =IFERROR(__xludf.DUMMYFUNCTION("""COMPUTED_VALUE"""),"") | R46: =IFERROR(__xludf.DUMMYFUNCTION("""COMPUTED_VALUE"""),"") | S46: =IFERROR(__xludf.DUMMYFUNCTION("""COMPUTED_VALUE"""),"") | T46: =IFERROR(__xludf.DUMMYFUNCTION("""COMPUTED_VALUE"""),"") | U46: =IFERROR(__xludf.DUMMYFUNCTION("""COMPUTED_VALUE"""),"") | V46: =IFERROR(__xludf.DUMMYFUNCTION("""COMPUTED_VALUE"""),"") | W46: =IFERROR(__xludf.DUMMYFUNCTION("""COMPUTED_VALUE"""),"") | X46: =IFERROR(__xludf.DUMMYFUNCTION("""COMPUTED_VALUE"""),"") | Y46: =IFERROR(__xludf.DUMMYFUNCTION("""COMPUTED_VALUE"""),"") | ... AD46: =IFERROR(__xludf.DUMMYFUNCTION("""COMPUTED_VALUE"""),"")
A47: =O47 | B47: =P47 | D47: https://llm-stats.com/models/qwen3.5-9b | E47: 6.55 | F47: =VLOOKUP($D47,'LLM Stats list of Model'!$B$2:$N1003,4,false) -> 2 | G47: =VLOOKUP($D47,'LLM Stats list of Model'!$B$2:$N1003,6,false) -> Qwen3.5-9B | P47: =IFERROR(__xludf.DUMMYFUNCTION("""COMPUTED_VALUE"""),"") | R47: =IFERROR(__xludf.DUMMYFUNCTION("""COMPUTED_VALUE"""),"") | S47: =IFERROR(__xludf.DUMMYFUNCTION("""COMPUTED_VALUE"""),"") | T47: =IFERROR(__xludf.DUMMYFUNCTION("""COMPUTED_VALUE"""),"") | U47: =IFERROR(__xludf.DUMMYFUNCTION("""COMPUTED_VALUE"""),"") | V47: =IFERROR(__xludf.DUMMYFUNCTION("""COMPUTED_VALUE"""),"") | W47: =IFERROR(__xludf.DUMMYFUNCTION("""COMPUTED_VALUE"""),"") | X47: =IFERROR(__xludf.DUMMYFUNCTION("""COMPUTED_VALUE"""),"") | Y47: =IFERROR(__xludf.DUMMYFUNCTION("""COMPUTED_VALUE"""),"") | ... AD47: =IFERROR(__xludf.DUMMYFUNCTION("""COMPUTED_VALUE"""),"")
A48: =O48 | B48: =P48 | D48: https://llm-stats.com/models/nemotron-3-nano-30b-a3b | E48: 2.84 | F48: =VLOOKUP($D48,'LLM Stats list of Model'!$B$2:$N1003,4,false) | G48: =VLOOKUP($D48,'LLM Stats list of Model'!$B$2:$N1003,6,false) -> Nemotron 3 Nano (30B A3B) | P48: =IFERROR(__xludf.DUMMYFUNCTION("""COMPUTED_VALUE"""),"") | R48: =IFERROR(__xludf.DUMMYFUNCTION("""COMPUTED_VALUE"""),"") | S48: =IFERROR(__xludf.DUMMYFUNCTION("""COMPUTED_VALUE"""),"") | T48: =IFERROR(__xludf.DUMMYFUNCTION("""COMPUTED_VALUE"""),"") | U48: =IFERROR(__xludf.DUMMYFUNCTION("""COMPUTED_VALUE"""),"") | V48: =IFERROR(__xludf.DUMMYFUNCTION("""COMPUTED_VALUE"""),"") | W48: =IFERROR(__xludf.DUMMYFUNCTION("""COMPUTED_VALUE"""),"") | X48: =IFERROR(__xludf.DUMMYFUNCTION("""COMPUTED_VALUE"""),"") | Y48: =IFERROR(__xludf.DUMMYFUNCTION("""COMPUTED_VALUE"""),"") | ... AD48: =IFERROR(__xludf.DUMMYFUNCTION("""COMPUTED_VALUE"""),"")
A49: =O49 | B49: =P49 | C49: Yes | D49: https://llm-stats.com/models/ministral-3-3b-base-2512 | F49: =VLOOKUP($D49,'LLM Stats list of Model'!$B$2:$N1003,4,false) | G49: =VLOOKUP($D49,'LLM Stats list of Model'!$B$2:$N1003,6,false) -> Ministral 3 (3B Base 2512) | P49: =IFERROR(__xludf.DUMMYFUNCTION("""COMPUTED_VALUE"""),"") | R49: =IFERROR(__xludf.DUMMYFUNCTION("""COMPUTED_VALUE"""),"") | S49: =IFERROR(__xludf.DUMMYFUNCTION("""COMPUTED_VALUE"""),"") | T49: =IFERROR(__xludf.DUMMYFUNCTION("""COMPUTED_VALUE"""),"") | U49: =IFERROR(__xludf.DUMMYFUNCTION("""COMPUTED_VALUE"""),"") | V49: =IFERROR(__xludf.DUMMYFUNCTION("""COMPUTED_VALUE"""),"") | W49: =IFERROR(__xludf.DUMMYFUNCTION("""COMPUTED_VALUE"""),"") | X49: =IFERROR(__xludf.DUMMYFUNCTION("""COMPUTED_VALUE"""),"") | Y49: =IFERROR(__xludf.DUMMYFUNCTION("""COMPUTED_VALUE"""),"") | ... AD49: =IFERROR(__xludf.DUMMYFUNCTION("""COMPUTED_VALUE"""),"")
B50: =P50 | D50: https://llm-stats.com/models/qwen3-vl-4b-instruct | F50: =VLOOKUP($D50,'LLM Stats list of Model'!$B$2:$N1003,4,false) -> 2 | G50: =VLOOKUP($D50,'LLM Stats list of Model'!$B$2:$N1003,6,false) -> Qwen3 VL 4B Instruct | P50: =IFERROR(__xludf.DUMMYFUNCTION("""COMPUTED_VALUE"""),"") | R50: =IFERROR(__xludf.DUMMYFUNCTION("""COMPUTED_VALUE"""),"") | S50: =IFERROR(__xludf.DUMMYFUNCTION("""COMPUTED_VALUE"""),"") | T50: =IFERROR(__xludf.DUMMYFUNCTION("""COMPUTED_VALUE"""),"") | U50: =IFERROR(__xludf.DUMMYFUNCTION("""COMPUTED_VALUE"""),"") | V50: =IFERROR(__xludf.DUMMYFUNCTION("""COMPUTED_VALUE"""),"") | W50: =IFERROR(__xludf.DUMMYFUNCTION("""COMPUTED_VALUE"""),"") | X50: =IFERROR(__xludf.DUMMYFUNCTION("""COMPUTED_VALUE"""),"") | Y50: =IFERROR(__xludf.DUMMYFUNCTION("""COMPUTED_VALUE"""),"") | ... AD50: =IFERROR(__xludf.DUMMYFUNCTION("""COMPUTED_VALUE"""),"")
A51: Lfm2.5 1.2B | B51: =P51 | F51: =VLOOKUP($D51,'LLM Stats list of Model'!$B$2:$N1003,4,false) -> #N/A | G51: =VLOOKUP($D51,'LLM Stats list of Model'!$B$2:$N1003,6,false) -> #N/A | P51: =IFERROR(__xludf.DUMMYFUNCTION("""COMPUTED_VALUE"""),"") | R51: =IFERROR(__xludf.DUMMYFUNCTION("""COMPUTED_VALUE"""),"") | S51: =IFERROR(__xludf.DUMMYFUNCTION("""COMPUTED_VALUE"""),"") | T51: =IFERROR(__xludf.DUMMYFUNCTION("""COMPUTED_VALUE"""),"") | U51: =IFERROR(__xludf.DUMMYFUNCTION("""COMPUTED_VALUE"""),"") | V51: =IFERROR(__xludf.DUMMYFUNCTION("""COMPUTED_VALUE"""),"") | W51: =IFERROR(__xludf.DUMMYFUNCTION("""COMPUTED_VALUE"""),"") | X51: =IFERROR(__xludf.DUMMYFUNCTION("""COMPUTED_VALUE"""),"") | Y51: =IFERROR(__xludf.DUMMYFUNCTION("""COMPUTED_VALUE"""),"") | ... AD51: =IFERROR(__xludf.DUMMYFUNCTION("""COMPUTED_VALUE"""),"")
A52: Rnj 1 | B52: =P52 | F52: =VLOOKUP($D52,'LLM Stats list of Model'!$B$2:$N1003,4,false) -> #N/A | G52: =VLOOKUP($D52,'LLM Stats list of Model'!$B$2:$N1003,6,false) -> #N/A | P52: =IFERROR(__xludf.DUMMYFUNCTION("""COMPUTED_VALUE"""),"") | R52: =IFERROR(__xludf.DUMMYFUNCTION("""COMPUTED_VALUE"""),"") | S52: =IFERROR(__xludf.DUMMYFUNCTION("""COMPUTED_VALUE"""),"") | T52: =IFERROR(__xludf.DUMMYFUNCTION("""COMPUTED_VALUE"""),"") | U52: =IFERROR(__xludf.DUMMYFUNCTION("""COMPUTED_VALUE"""),"") | V52: =IFERROR(__xludf.DUMMYFUNCTION("""COMPUTED_VALUE"""),"") | W52: =IFERROR(__xludf.DUMMYFUNCTION("""COMPUTED_VALUE"""),"") | X52: =IFERROR(__xludf.DUMMYFUNCTION("""COMPUTED_VALUE"""),"") | Y52: =IFERROR(__xludf.DUMMYFUNCTION("""COMPUTED_VALUE"""),"") | ... AD52: =IFERROR(__xludf.DUMMYFUNCTION("""COMPUTED_VALUE"""),"")
A53: Olmocr 2 7B | B53: =P53 | F53: =VLOOKUP($D53,'LLM Stats list of Model'!$B$2:$N1003,4,false) -> #N/A | G53: =VLOOKUP($D53,'LLM Stats list of Model'!$B$2:$N1003,6,false) -> #N/A | P53: =IFERROR(__xludf.DUMMYFUNCTION("""COMPUTED_VALUE"""),"") | R53: =IFERROR(__xludf.DUMMYFUNCTION("""COMPUTED_VALUE"""),"") | S53: =IFERROR(__xludf.DUMMYFUNCTION("""COMPUTED_VALUE"""),"") | T53: =IFERROR(__xludf.DUMMYFUNCTION("""COMPUTED_VALUE"""),"") | U53: =IFERROR(__xludf.DUMMYFUNCTION("""COMPUTED_VALUE"""),"") | V53: =IFERROR(__xludf.DUMMYFUNCTION("""COMPUTED_VALUE"""),"") | W53: =IFERROR(__xludf.DUMMYFUNCTION("""COMPUTED_VALUE"""),"") | X53: =IFERROR(__xludf.DUMMYFUNCTION("""COMPUTED_VALUE"""),"") | Y53: =IFERROR(__xludf.DUMMYFUNCTION("""COMPUTED_VALUE"""),"") | ... AD53: =IFERROR(__xludf.DUMMYFUNCTION("""COMPUTED_VALUE"""),"")
A54: Qwen3 VL 8B | B54: skipped for old model | F54: =VLOOKUP($D54,'LLM Stats list of Model'!$B$2:$N1003,4,false) -> #N/A | G54: =VLOOKUP($D54,'LLM Stats list of Model'!$B$2:$N1003,6,false) -> #N/A | P54: =IFERROR(__xludf.DUMMYFUNCTION("""COMPUTED_VALUE"""),"") | R54: =IFERROR(__xludf.DUMMYFUNCTION("""COMPUTED_VALUE"""),"") | S54: =IFERROR(__xludf.DUMMYFUNCTION("""COMPUTED_VALUE"""),"") | T54: =IFERROR(__xludf.DUMMYFUNCTION("""COMPUTED_VALUE"""),"") | U54: =IFERROR(__xludf.DUMMYFUNCTION("""COMPUTED_VALUE"""),"") | V54: =IFERROR(__xludf.DUMMYFUNCTION("""COMPUTED_VALUE"""),"") | W54: =IFERROR(__xludf.DUMMYFUNCTION("""COMPUTED_VALUE"""),"") | X54: =IFERROR(__xludf.DUMMYFUNCTION("""COMPUTED_VALUE"""),"") | Y54: =IFERROR(__xludf.DUMMYFUNCTION("""COMPUTED_VALUE"""),"") | ... AD54: =IFERROR(__xludf.DUMMYFUNCTION("""COMPUTED_VALUE"""),"")
A55: Granite 4 H Tiny | B55: =P55 | F55: =VLOOKUP($D55,'LLM Stats list of Model'!$B$2:$N1003,4,false) -> #N/A | G55: =VLOOKUP($D55,'LLM Stats list of Model'!$B$2:$N1003,6,false) -> #N/A | P55: =IFERROR(__xludf.DUMMYFUNCTION("""COMPUTED_VALUE"""),"") | R55: =IFERROR(__xludf.DUMMYFUNCTION("""COMPUTED_VALUE"""),"") | S55: =IFERROR(__xludf.DUMMYFUNCTION("""COMPUTED_VALUE"""),"") | T55: =IFERROR(__xludf.DUMMYFUNCTION("""COMPUTED_VALUE"""),"") | U55: =IFERROR(__xludf.DUMMYFUNCTION("""COMPUTED_VALUE"""),"") | V55: =IFERROR(__xludf.DUMMYFUNCTION("""COMPUTED_VALUE"""),"") | W55: =IFERROR(__xludf.DUMMYFUNCTION("""COMPUTED_VALUE"""),"") | X55: =IFERROR(__xludf.DUMMYFUNCTION("""COMPUTED_VALUE"""),"") | Y55: =IFERROR(__xludf.DUMMYFUNCTION("""COMPUTED_VALUE"""),"") | ... AD55: =IFERROR(__xludf.DUMMYFUNCTION("""COMPUTED_VALUE"""),"")
A56: Qwen3 VL 8B | B56: =P56 | F56: =VLOOKUP($D56,'LLM Stats list of Model'!$B$2:$N1003,4,false) -> #N/A | G56: =VLOOKUP($D56,'LLM Stats list of Model'!$B$2:$N1003,6,false) -> #N/A | P56: =IFERROR(__xludf.DUMMYFUNCTION("""COMPUTED_VALUE"""),"") | R56: =IFERROR(__xludf.DUMMYFUNCTION("""COMPUTED_VALUE"""),"") | S56: =IFERROR(__xludf.DUMMYFUNCTION("""COMPUTED_VALUE"""),"") | T56: =IFERROR(__xludf.DUMMYFUNCTION("""COMPUTED_VALUE"""),"") | U56: =IFERROR(__xludf.DUMMYFUNCTION("""COMPUTED_VALUE"""),"") | V56: =IFERROR(__xludf.DUMMYFUNCTION("""COMPUTED_VALUE"""),"") | W56: =IFERROR(__xludf.DUMMYFUNCTION("""COMPUTED_VALUE"""),"") | X56: =IFERROR(__xludf.DUMMYFUNCTION("""COMPUTED_VALUE"""),"") | Y56: =IFERROR(__xludf.DUMMYFUNCTION("""COMPUTED_VALUE"""),"") | ... AD56: =IFERROR(__xludf.DUMMYFUNCTION("""COMPUTED_VALUE"""),"")
B57: =P57 | F57: =VLOOKUP($D57,'LLM Stats list of Model'!$B$2:$N1003,4,false) -> #N/A | G57: =VLOOKUP($D57,'LLM Stats list of Model'!$B$2:$N1003,6,false) -> #N/A | P57: =IFERROR(__xludf.DUMMYFUNCTION("""COMPUTED_VALUE"""),"") | R57: =IFERROR(__xludf.DUMMYFUNCTION("""COMPUTED_VALUE"""),"") | S57: =IFERROR(__xludf.DUMMYFUNCTION("""COMPUTED_VALUE"""),"") | T57: =IFERROR(__xludf.DUMMYFUNCTION("""COMPUTED_VALUE"""),"") | U57: =IFERROR(__xludf.DUMMYFUNCTION("""COMPUTED_VALUE"""),"") | V57: =IFERROR(__xludf.DUMMYFUNCTION("""COMPUTED_VALUE"""),"") | W57: =IFERROR(__xludf.DUMMYFUNCTION("""COMPUTED_VALUE"""),"") | X57: =IFERROR(__xludf.DUMMYFUNCTION("""COMPUTED_VALUE"""),"") | Y57: =IFERROR(__xludf.DUMMYFUNCTION("""COMPUTED_VALUE"""),"") | ... AD57: =IFERROR(__xludf.DUMMYFUNCTION("""COMPUTED_VALUE"""),"")
B58: =P58 | F58: =VLOOKUP($D58,'LLM Stats list of Model'!$B$2:$N1003,4,false) -> #N/A | G58: =VLOOKUP($D58,'LLM Stats list of Model'!$B$2:$N1003,6,false) -> #N/A | P58: =IFERROR(__xludf.DUMMYFUNCTION("""COMPUTED_VALUE"""),"") | R58: =IFERROR(__xludf.DUMMYFUNCTION("""COMPUTED_VALUE"""),"") | S58: =IFERROR(__xludf.DUMMYFUNCTION("""COMPUTED_VALUE"""),"") | T58: =IFERROR(__xludf.DUMMYFUNCTION("""COMPUTED_VALUE"""),"") | U58: =IFERROR(__xludf.DUMMYFUNCTION("""COMPUTED_VALUE"""),"") | V58: =IFERROR(__xludf.DUMMYFUNCTION("""COMPUTED_VALUE"""),"") | W58: =IFERROR(__xludf.DUMMYFUNCTION("""COMPUTED_VALUE"""),"") | X58: =IFERROR(__xludf.DUMMYFUNCTION("""COMPUTED_VALUE"""),"") | Y58: =IFERROR(__xludf.DUMMYFUNCTION("""COMPUTED_VALUE"""),"") | ... AD58: =IFERROR(__xludf.DUMMYFUNCTION("""COMPUTED_VALUE"""),"")
B59: =P59 | P59: =IFERROR(__xludf.DUMMYFUNCTION("""COMPUTED_VALUE"""),"") | R59: =IFERROR(__xludf.DUMMYFUNCTION("""COMPUTED_VALUE"""),"") | S59: =IFERROR(__xludf.DUMMYFUNCTION("""COMPUTED_VALUE"""),"") | T59: =IFERROR(__xludf.DUMMYFUNCTION("""COMPUTED_VALUE"""),"") | U59: =IFERROR(__xludf.DUMMYFUNCTION("""COMPUTED_VALUE"""),"") | V59: =IFERROR(__xludf.DUMMYFUNCTION("""COMPUTED_VALUE"""),"") | W59: =IFERROR(__xludf.DUMMYFUNCTION("""COMPUTED_VALUE"""),"") | X59: =IFERROR(__xludf.DUMMYFUNCTION("""COMPUTED_VALUE"""),"") | Y59: =IFERROR(__xludf.DUMMYFUNCTION("""COMPUTED_VALUE"""),"") | ... AD59: =IFERROR(__xludf.DUMMYFUNCTION("""COMPUTED_VALUE"""),"")
B60: =P60 | P60: =IFERROR(__xludf.DUMMYFUNCTION("""COMPUTED_VALUE"""),"") | R60: =IFERROR(__xludf.DUMMYFUNCTION("""COMPUTED_VALUE"""),"") | S60: =IFERROR(__xludf.DUMMYFUNCTION("""COMPUTED_VALUE"""),"") | T60: =IFERROR(__xludf.DUMMYFUNCTION("""COMPUTED_VALUE"""),"") | U60: =IFERROR(__xludf.DUMMYFUNCTION("""COMPUTED_VALUE"""),"") | V60: =IFERROR(__xludf.DUMMYFUNCTION("""COMPUTED_VALUE"""),"") | W60: =IFERROR(__xludf.DUMMYFUNCTION("""COMPUTED_VALUE"""),"") | X60: =IFERROR(__xludf.DUMMYFUNCTION("""COMPUTED_VALUE"""),"") | Y60: =IFERROR(__xludf.DUMMYFUNCTION("""COMPUTED_VALUE"""),"") | ... AD60: =IFERROR(__xludf.DUMMYFUNCTION("""COMPUTED_VALUE"""),"")
P61: =IFERROR(__xludf.DUMMYFUNCTION("""COMPUTED_VALUE"""),"") | R61: =IFERROR(__xludf.DUMMYFUNCTION("""COMPUTED_VALUE"""),"") | S61: =IFERROR(__xludf.DUMMYFUNCTION("""COMPUTED_VALUE"""),"") | T61: =IFERROR(__xludf.DUMMYFUNCTION("""COMPUTED_VALUE"""),"") | U61: =IFERROR(__xludf.DUMMYFUNCTION("""COMPUTED_VALUE"""),"") | V61: =IFERROR(__xludf.DUMMYFUNCTION("""COMPUTED_VALUE"""),"") | W61: =IFERROR(__xludf.DUMMYFUNCTION("""COMPUTED_VALUE"""),"") | X61: =IFERROR(__xludf.DUMMYFUNCTION("""COMPUTED_VALUE"""),"") | Y61: =IFERROR(__xludf.DUMMYFUNCTION("""COMPUTED_VALUE"""),"") | ... AD61: =IFERROR(__xludf.DUMMYFUNCTION("""COMPUTED_VALUE"""),"")
P62: =IFERROR(__xludf.DUMMYFUNCTION("""COMPUTED_VALUE"""),"") | R62: =IFERROR(__xludf.DUMMYFUNCTION("""COMPUTED_VALUE"""),"") | S62: =IFERROR(__xludf.DUMMYFUNCTION("""COMPUTED_VALUE"""),"") | T62: =IFERROR(__xludf.DUMMYFUNCTION("""COMPUTED_VALUE"""),"") | U62: =IFERROR(__xludf.DUMMYFUNCTION("""COMPUTED_VALUE"""),"") | V62: =IFERROR(__xludf.DUMMYFUNCTION("""COMPUTED_VALUE"""),"") | W62: =IFERROR(__xludf.DUMMYFUNCTION("""COMPUTED_VALUE"""),"") | X62: =IFERROR(__xludf.DUMMYFUNCTION("""COMPUTED_VALUE"""),"") | Y62: =IFERROR(__xludf.DUMMYFUNCTION("""COMPUTED_VALUE"""),"") | ... AD62: =IFERROR(__xludf.DUMMYFUNCTION("""COMPUTED_VALUE"""),"")
P63: =IFERROR(__xludf.DUMMYFUNCTION("""COMPUTED_VALUE"""),"") | R63: =IFERROR(__xludf.DUMMYFUNCTION("""COMPUTED_VALUE"""),"") | S63: =IFERROR(__xludf.DUMMYFUNCTION("""COMPUTED_VALUE"""),"") | T63: =IFERROR(__xludf.DUMMYFUNCTION("""COMPUTED_VALUE"""),"") | U63: =IFERROR(__xludf.DUMMYFUNCTION("""COMPUTED_VALUE"""),"") | V63: =IFERROR(__xludf.DUMMYFUNCTION("""COMPUTED_VALUE"""),"") | W63: =IFERROR(__xludf.DUMMYFUNCTION("""COMPUTED_VALUE"""),"") | X63: =IFERROR(__xludf.DUMMYFUNCTION("""COMPUTED_VALUE"""),"") | Y63: =IFERROR(__xludf.DUMMYFUNCTION("""COMPUTED_VALUE"""),"") | ... AD63: =IFERROR(__xludf.DUMMYFUNCTION("""COMPUTED_VALUE"""),"")
P64: =IFERROR(__xludf.DUMMYFUNCTION("""COMPUTED_VALUE"""),"") | R64: =IFERROR(__xludf.DUMMYFUNCTION("""COMPUTED_VALUE"""),"") | S64: =IFERROR(__xludf.DUMMYFUNCTION("""COMPUTED_VALUE"""),"") | T64: =IFERROR(__xludf.DUMMYFUNCTION("""COMPUTED_VALUE"""),"") | U64: =IFERROR(__xludf.DUMMYFUNCTION("""COMPUTED_VALUE"""),"") | V64: =IFERROR(__xludf.DUMMYFUNCTION("""COMPUTED_VALUE"""),"") | W64: =IFERROR(__xludf.DUMMYFUNCTION("""COMPUTED_VALUE"""),"") | X64: =IFERROR(__xludf.DUMMYFUNCTION("""COMPUTED_VALUE"""),"") | Y64: =IFERROR(__xludf.DUMMYFUNCTION("""COMPUTED_VALUE"""),"") | ... AD64: =IFERROR(__xludf.DUMMYFUNCTION("""COMPUTED_VALUE"""),"")
P65: =IFERROR(__xludf.DUMMYFUNCTION("""COMPUTED_VALUE"""),"") | R65: =IFERROR(__xludf.DUMMYFUNCTION("""COMPUTED_VALUE"""),"") | S65: =IFERROR(__xludf.DUMMYFUNCTION("""COMPUTED_VALUE"""),"") | T65: =IFERROR(__xludf.DUMMYFUNCTION("""COMPUTED_VALUE"""),"") | U65: =IFERROR(__xludf.DUMMYFUNCTION("""COMPUTED_VALUE"""),"") | V65: =IFERROR(__xludf.DUMMYFUNCTION("""COMPUTED_VALUE"""),"") | W65: =IFERROR(__xludf.DUMMYFUNCTION("""COMPUTED_VALUE"""),"") | X65: =IFERROR(__xludf.DUMMYFUNCTION("""COMPUTED_VALUE"""),"") | Y65: =IFERROR(__xludf.DUMMYFUNCTION("""COMPUTED_VALUE"""),"") | ... AD65: =IFERROR(__xludf.DUMMYFUNCTION("""COMPUTED_VALUE"""),"")
P66: =IFERROR(__xludf.DUMMYFUNCTION("""COMPUTED_VALUE"""),"") | R66: =IFERROR(__xludf.DUMMYFUNCTION("""COMPUTED_VALUE"""),"") | S66: =IFERROR(__xludf.DUMMYFUNCTION("""COMPUTED_VALUE"""),"") | T66: =IFERROR(__xludf.DUMMYFUNCTION("""COMPUTED_VALUE"""),"") | U66: =IFERROR(__xludf.DUMMYFUNCTION("""COMPUTED_VALUE"""),"") | V66: =IFERROR(__xludf.DUMMYFUNCTION("""COMPUTED_VALUE"""),"") | W66: =IFERROR(__xludf.DUMMYFUNCTION("""COMPUTED_VALUE"""),"") | X66: =IFERROR(__xludf.DUMMYFUNCTION("""COMPUTED_VALUE"""),"") | Y66: =IFERROR(__xludf.DUMMYFUNCTION("""COMPUTED_VALUE"""),"") | ... AD66: =IFERROR(__xludf.DUMMYFUNCTION("""COMPUTED_VALUE"""),"")
P67: =IFERROR(__xludf.DUMMYFUNCTION("""COMPUTED_VALUE"""),"") | R67: =IFERROR(__xludf.DUMMYFUNCTION("""COMPUTED_VALUE"""),"") | S67: =IFERROR(__xludf.DUMMYFUNCTION("""COMPUTED_VALUE"""),"") | T67: =IFERROR(__xludf.DUMMYFUNCTION("""COMPUTED_VALUE"""),"") | U67: =IFERROR(__xludf.DUMMYFUNCTION("""COMPUTED_VALUE"""),"") | V67: =IFERROR(__xludf.DUMMYFUNCTION("""COMPUTED_VALUE"""),"") | W67: =IFERROR(__xludf.DUMMYFUNCTION("""COMPUTED_VALUE"""),"") | X67: =IFERROR(__xludf.DUMMYFUNCTION("""COMPUTED_VALUE"""),"") | Y67: =IFERROR(__xludf.DUMMYFUNCTION("""COMPUTED_VALUE"""),"") | ... AD67: =IFERROR(__xludf.DUMMYFUNCTION("""COMPUTED_VALUE"""),"")
P68: =IFERROR(__xludf.DUMMYFUNCTION("""COMPUTED_VALUE"""),"") | R68: =IFERROR(__xludf.DUMMYFUNCTION("""COMPUTED_VALUE"""),"") | S68: =IFERROR(__xludf.DUMMYFUNCTION("""COMPUTED_VALUE"""),"") | T68: =IFERROR(__xludf.DUMMYFUNCTION("""COMPUTED_VALUE"""),"") | U68: =IFERROR(__xludf.DUMMYFUNCTION("""COMPUTED_VALUE"""),"") | V68: =IFERROR(__xludf.DUMMYFUNCTION("""COMPUTED_VALUE"""),"") | W68: =IFERROR(__xludf.DUMMYFUNCTION("""COMPUTED_VALUE"""),"") | X68: =IFERROR(__xludf.DUMMYFUNCTION("""COMPUTED_VALUE"""),"") | Y68: =IFERROR(__xludf.DUMMYFUNCTION("""COMPUTED_VALUE"""),"") | ... AD68: =IFERROR(__xludf.DUMMYFUNCTION("""COMPUTED_VALUE"""),"")
P69: =IFERROR(__xludf.DUMMYFUNCTION("""COMPUTED_VALUE"""),"") | R69: =IFERROR(__xludf.DUMMYFUNCTION("""COMPUTED_VALUE"""),"") | S69: =IFERROR(__xludf.DUMMYFUNCTION("""COMPUTED_VALUE"""),"") | T69: =IFERROR(__xludf.DUMMYFUNCTION("""COMPUTED_VALUE"""),"") | U69: =IFERROR(__xludf.DUMMYFUNCTION("""COMPUTED_VALUE"""),"") | V69: =IFERROR(__xludf.DUMMYFUNCTION("""COMPUTED_VALUE"""),"") | W69: =IFERROR(__xludf.DUMMYFUNCTION("""COMPUTED_VALUE"""),"") | X69: =IFERROR(__xludf.DUMMYFUNCTION("""COMPUTED_VALUE"""),"") | Y69: =IFERROR(__xludf.DUMMYFUNCTION("""COMPUTED_VALUE"""),"") | ... AD69: =IFERROR(__xludf.DUMMYFUNCTION("""COMPUTED_VALUE"""),"")
P70: =IFERROR(__xludf.DUMMYFUNCTION("""COMPUTED_VALUE"""),"") | R70: =IFERROR(__xludf.DUMMYFUNCTION("""COMPUTED_VALUE"""),"") | S70: =IFERROR(__xludf.DUMMYFUNCTION("""COMPUTED_VALUE"""),"") | T70: =IFERROR(__xludf.DUMMYFUNCTION("""COMPUTED_VALUE"""),"") | U70: =IFERROR(__xludf.DUMMYFUNCTION("""COMPUTED_VALUE"""),"") | V70: =IFERROR(__xludf.DUMMYFUNCTION("""COMPUTED_VALUE"""),"") | W70: =IFERROR(__xludf.DUMMYFUNCTION("""COMPUTED_VALUE"""),"") | X70: =IFERROR(__xludf.DUMMYFUNCTION("""COMPUTED_VALUE"""),"") | Y70: =IFERROR(__xludf.DUMMYFUNCTION("""COMPUTED_VALUE"""),"") | ... AD70: =IFERROR(__xludf.DUMMYFUNCTION("""COMPUTED_VALUE"""),"")
P71: =IFERROR(__xludf.DUMMYFUNCTION("""COMPUTED_VALUE"""),"") | R71: =IFERROR(__xludf.DUMMYFUNCTION("""COMPUTED_VALUE"""),"") | S71: =IFERROR(__xludf.DUMMYFUNCTION("""COMPUTED_VALUE"""),"") | T71: =IFERROR(__xludf.DUMMYFUNCTION("""COMPUTED_VALUE"""),"") | U71: =IFERROR(__xludf.DUMMYFUNCTION("""COMPUTED_VALUE"""),"") | V71: =IFERROR(__xludf.DUMMYFUNCTION("""COMPUTED_VALUE"""),"") | W71: =IFERROR(__xludf.DUMMYFUNCTION("""COMPUTED_VALUE"""),"") | X71: =IFERROR(__xludf.DUMMYFUNCTION("""COMPUTED_VALUE"""),"") | Y71: =IFERROR(__xludf.DUMMYFUNCTION("""COMPUTED_VALUE"""),"") | ... AD71: =IFERROR(__xludf.DUMMYFUNCTION("""COMPUTED_VALUE"""),"")
P72: =IFERROR(__xludf.DUMMYFUNCTION("""COMPUTED_VALUE"""),"") | R72: =IFERROR(__xludf.DUMMYFUNCTION("""COMPUTED_VALUE"""),"") | S72: =IFERROR(__xludf.DUMMYFUNCTION("""COMPUTED_VALUE"""),"") | T72: =IFERROR(__xludf.DUMMYFUNCTION("""COMPUTED_VALUE"""),"") | U72: =IFERROR(__xludf.DUMMYFUNCTION("""COMPUTED_VALUE"""),"") | V72: =IFERROR(__xludf.DUMMYFUNCTION("""COMPUTED_VALUE"""),"") | W72: =IFERROR(__xludf.DUMMYFUNCTION("""COMPUTED_VALUE"""),"") | X72: =IFERROR(__xludf.DUMMYFUNCTION("""COMPUTED_VALUE"""),"") | Y72: =IFERROR(__xludf.DUMMYFUNCTION("""COMPUTED_VALUE"""),"") | ... AD72: =IFERROR(__xludf.DUMMYFUNCTION("""COMPUTED_VALUE"""),"")
... P1003: =IFERROR(__xludf.DUMMYFUNCTION("""COMPUTED_VALUE"""),"") | R1003: =IFERROR(__xludf.DUMMYFUNCTION("""COMPUTED_VALUE"""),"") | S1003: =IFERROR(__xludf.DUMMYFUNCTION("""COMPUTED_VALUE"""),"") | T1003: =IFERROR(__xludf.DUMMYFUNCTION("""COMPUTED_VALUE"""),"") | U1003: =IFERROR(__xludf.DUMMYFUNCTION("""COMPUTED_VALUE"""),"") | V1003: =IFERROR(__xludf.DUMMYFUNCTION("""COMPUTED_VALUE"""),"") | W1003: =IFERROR(__xludf.DUMMYFUNCTION("""COMPUTED_VALUE"""),"") | X1003: =IFERROR(__xludf.DUMMYFUNCTION("""COMPUTED_VALUE"""),"") | Y1003: =IFERROR(__xludf.DUMMYFUNCTION("""COMPUTED_VALUE"""),"") | ... AD1003: =IFERROR(__xludf.DUMMYFUNCTION("""COMPUTED_VALUE"""),"")

Sheet raw Ollama Model
A1: Model Link | B1: Model Name | C1: Description | D1: Tags | F1: Downloads/Pulls | G1: Tag | I1: Updated
A2: https://ollama.com/library/nemotron3 | B2: nemotron3 | C2: NVIDIA Nemotron 3 Nano Omni is a multimodal large language model that unifies video, audio, image, and text understanding to support enterprise-grade Q&A, summarization, transcription, and document intelligence workflows. | D2: vision | E2: 33b | F2: 509.7K | G2: 4 | H2: Tags | I2: 1 week ago
A3: https://ollama.com/library/qwen3.6 | B3: qwen3.6 | C3: Qwen3.6 delivers substantial upgrades in agentic coding and thinking preservation than previous Qwen models. | D3: vision | E3: 27b | F3: 866.1K | G3: 22 | H3: Tags | I3: 1 week ago | J3: 35b
A4: https://ollama.com/library/kimi-k2.6 | B4: kimi-k2.6 | C4: Kimi K2.6 is an open-source, native multimodal agentic model that advances practical capabilities in long-horizon coding, coding-driven design, proactive autonomous execution, and swarm-based task orchestration. | D4: vision | F4: 196.9K | G4: 1 | H4: Tag | I4: 2 weeks ago
A5: https://ollama.com/library/glm-5.1 | B5: glm-5.1 | C5: GLM-5.1 is our next-generation flagship model for agentic engineering, with significantly stronger coding capabilities than its predecessor. It achieves state-of-the-art performance on SWE-Bench Pro and leads GLM-5 by a wide margin. | D5: tools | F5: 243K | G5: 1 | H5: Tag | I5: 4 weeks ago
A6: https://ollama.com/library/granite4.1 | B6: granite4.1 | D6: tools | E6: 3b | F6: 36.7K | G6: 46 | H6: Tags | I6: 6 days ago | J6: 8b | K6: 30b
A7: https://ollama.com/library/deepseek-v4-flash | B7: deepseek-v4-flash | C7: DeepSeek-V4-Flash is a preview of the DeepSeek-V4 series, a Mixture-of-Experts model with 284B total parameters and 13B activated, built for efficient reasoning across a 1M-token context window. | D7: tools | F7: 46.4K | G7: 1 | H7: Tag | I7: 1 week ago
A8: https://ollama.com/library/deepseek-v4-pro | B8: deepseek-v4-pro | C8: DeepSeek-V4-Pro is a frontier Mixture-of-Experts model with a 1M-token context window and three reasoning modes. | D8: tools | F8: 37.3K | G8: 1 | H8: Tag | I8: 1 week ago
A9: https://ollama.com/library/mistral-medium-3.5 | B9: mistral-medium-3.5 | C9: Mistral Medium 3.5 is the first flagship model of Mistral AI that merged instruction-following, reasoning, and coding in a single set of 128B weights. | D9: vision | E9: 128b | F9: 11.4K | G9: 5 | H9: Tags | I9: 8 hours ago
A10: https://ollama.com/library/medgemma | B10: medgemma | C10: MedGemma is a collection of Gemma 3 variants that are trained for performance on medical text and image comprehension. | D10: vision | E10: 4b | F10: 20.9K | G10: 9 | H10: Tags | I10: 2 weeks ago | J10: 27b
A11: https://ollama.com/library/medgemma1.5 | B11: medgemma1.5 | C11: MedGemma 1.5 4B is an updated version of the MedGemma 4B model. | D11: vision | E11: 4b | F11: 12.4K | G11: 5 | H11: Tags | I11: 2 weeks ago
A12: https://ollama.com/library/laguna-xs.2 | B12: laguna-xs.2 | C12: Laguna XS.2 is a 33B total parameter Mixture-of-Experts model with 3B activated parameters per token designed for agentic coding and long-horizon work on a local machine. | D12: tools | F12: 6107 | G12: 7 | H12: Tags | I12: 1 week ago
A13: https://ollama.com/library/gemma4 | B13: gemma4 | C13: Gemma 4 models are designed to deliver frontier-level performance at each size. They are well-suited for reasoning, agentic workflows, coding, and multimodal understanding. | D13: vision | E13: e2b | F13: 7M | G13: 30 | H13: Tags | I13: 14 hours ago | J13: e4b | K13: 26b
A14: https://ollama.com/library/qwen3.5 | B14: qwen3.5 | C14: Qwen 3.5 is a family of open-source multimodal models that delivers exceptional utility and performance. | D14: vision | E14: 0.8b | F14: 8.6M | G14: 58 | H14: Tags | I14: 1 month ago | J14: 2b | K14: 4b
A15: https://ollama.com/library/lfm2 | B15: lfm2 | C15: LFM2 is a family of hybrid models designed for on-device deployment. LFM2-24B-A2B is the largest model in the family, scaling the architecture to 24 billion parameters while keeping inference efficient. | D15: tools | E15: 24b | F15: 1.1M | G15: 6 | H15: Tags | I15: 2 months ago
A16: https://ollama.com/library/qwen3-coder-next | B16: qwen3-coder-next | C16: Qwen3-Coder-Next is a coding-focused language model from Alibaba's Qwen team, optimized for agentic coding workflows and local development. | D16: tools | F16: 1.2M | G16: 4 | H16: Tags | I16: 2 months ago
A17: https://ollama.com/library/translategemma | B17: translategemma | C17: A new collection of open translation models built on Gemma 3, helping people communicate across 55 languages. | D17: vision | E17: 4b | F17: 1.3M | G17: 13 | H17: Tags | I17: 3 months ago | J17: 12b | K17: 27b
A18: https://ollama.com/library/glm-4.7-flash | B18: glm-4.7-flash | C18: As the strongest model in the 30B class, GLM-4.7-Flash offers a new option for lightweight deployment that balances performance and efficiency. | D18: tools | F18: 1.2M | G18: 4 | H18: Tags | I18: 3 months ago
A19: https://ollama.com/library/lfm2.5-thinking | B19: lfm2.5-thinking | C19: LFM2.5 is a new family of hybrid models designed for on-device deployment. | D19: tools | E19: 1.2b | F19: 1.2M | G19: 5 | H19: Tags | I19: 3 months ago
A20: https://ollama.com/library/ministral-3 | B20: ministral-3 | C20: The Ministral 3 family is designed for edge deployment, capable of running on a wide range of hardware. | D20: vision | E20: 3b | F20: 1.1M | G20: 16 | H20: Tags | I20: 4 months ago | J20: 8b | K20: 14b
A21: https://ollama.com/library/nemotron-3-super | B21: nemotron-3-super | C21: NVIDIA Nemotron 3 Super is a 120B open MoE model activating just 12B parameters to deliver maximum compute efficiency and accuracy for complex multi-agent applications. | D21: tools | E21: 120b | F21: 388.6K | G21: 7 | H21: Tags | I21: 1 month ago
A22: https://ollama.com/library/minimax-m2.7 | B22: minimax-m2.7 | C22: MiniMax's M2-series model for coding, agentic workflows, and professional productivity. | D22: tools | F22: 219.5K | G22: 1 | H22: Tag | I22: 1 month ago
A23: https://ollama.com/library/devstral-small-2 | B23: devstral-small-2 | C23: 24B model that excels at using tools to explore codebases, editing multiple files and power software engineering agents. | D23: vision | E23: 24b | F23: 816.4K | G23: 6 | H23: Tags | I23: 4 months ago
A24: https://ollama.com/library/glm-ocr | B24: glm-ocr | C24: GLM-OCR is a multimodal OCR model for complex document understanding, built on the GLM-V encoder–decoder architecture. | D24: vision | F24: 424.5K | G24: 3 | H24: Tags | I24: 3 months ago
A25: https://ollama.com/library/glm-5 | B25: glm-5 | C25: A strong reasoning and agentic model from Z.ai with 744B total parameters (40B active), built for complex systems engineering and long-horizon tasks. | D25: tools | F25: 311.6K | G25: 1 | H25: Tag | I25: 2 months ago
A26: https://ollama.com/library/minimax-m2.5 | B26: minimax-m2.5 | C26: MiniMax-M2.5 is a state-of-the-art large language model designed for real-world productivity and coding tasks. | D26: tools | F26: 282.2K | G26: 1 | H26: Tag | I26: 2 months ago
A27: https://ollama.com/library/qwen3-next | B27: qwen3-next | C27: The first installment in the Qwen3-Next series with strong performance in terms of both parameter efficiency and inference speed. | D27: tools | E27: 80b | F27: 537.6K | G27: 10 | H27: Tags | I27: 4 months ago
A28: https://ollama.com/library/rnj-1 | B28: rnj-1 | C28: Rnj-1 is a family of 8B parameter open-weight, dense models trained from scratch by Essential AI, optimized for code and STEM with capabilities on par with SOTA open-weight models. | D28: tools | E28: 8b | F28: 455.5K | G28: 6 | H28: Tags | I28: 4 months ago
A29: https://ollama.com/library/nemotron-cascade-2 | B29: nemotron-cascade-2 | C29: An open 30B MoE model from NVIDIA with 3B activated parameters that delivers strong reasoning and agentic capabilities. | D29: tools | E29: 30b | F29: 110.9K | G29: 3 | H29: Tags | I29: 1 month ago
A30: https://ollama.com/library/kimi-k2.5 | B30: kimi-k2.5 | C30: Kimi K2.5 is an open-source, native multimodal agentic model that seamlessly integrates vision and language understanding with advanced agentic capabilities, instant and thinking modes, as well as conversational and agentic paradigms. | D30: vision | F30: 271.5K | G30: 1 | H30: Tag | I30: 3 months ago
A31: https://ollama.com/library/nemotron-3-nano | B31: nemotron-3-nano | C31: Nemotron-3-Nano is a new Standard for Efficient, Open, and Intelligent Agentic Models, now updated with a 4B parameter count model. | D31: tools | E31: 4b | F31: 424.3K | G31: 9 | H31: Tags | I31: 1 month ago | J31: 30b
A32: https://ollama.com/library/olmo-3 | B32: olmo-3 | C32: Olmo is a series of Open language models designed to enable the science of language models. These models are pre-trained on the Dolma 3 dataset and post-trained on the Dolci datasets. | E32: 7b | F32: 421.8K | G32: 15 | H32: Tags | I32: 4 months ago | J32: 32b
A33: https://ollama.com/library/deepseek-ocr | B33: deepseek-ocr | C33: DeepSeek-OCR is a vision-language model that can perform token-efficient OCR. | D33: vision | E33: 3b | F33: 436.7K | G33: 3 | H33: Tags | I33: 5 months ago
A34: https://ollama.com/library/olmo-3.1 | B34: olmo-3.1 | C34: Olmo is a series of Open language models designed to enable the science of language models. These models are pre-trained on the Dolma 3 dataset and post-trained on the Dolci datasets. | D34: tools | E34: 32b | F34: 268.7K | G34: 10 | H34: Tags | I34: 4 months ago
A35: https://ollama.com/library/gemini-3-flash-preview | B35: gemini-3-flash-preview | C35: Gemini 3 Flash offers frontier intelligence built for speed at a fraction of the cost. | D35: vision | F35: 259.6K | G35: 2 | H35: Tags | I35: 4 months ago
A36: https://ollama.com/library/glm-4.7 | B36: glm-4.7 | C36: Advancing the Coding Capability | D36: tools | F36: 208.3K | G36: 1 | H36: Tag | I36: 4 months ago
A37: https://ollama.com/library/devstral-2 | B37: devstral-2 | C37: 123B model that excels at using tools to explore codebases, editing multiple files and power software engineering agents. | D37: tools | E37: 123b | F37: 210.4K | G37: 6 | H37: Tags | I37: 4 months ago
A38: https://ollama.com/library/deepseek-v3.2 | B38: deepseek-v3.2 | C38: DeepSeek-V3.2, a model that harmonizes high computational efficiency with superior reasoning and agent performance. | D38: tools | F38: 202.2K | G38: 1 | H38: Tag | I38: 4 months ago
A39: https://ollama.com/library/nomic-embed-text-v2-moe | B39: nomic-embed-text-v2-moe | C39: nomic-embed-text-v2-moe is a multilingual MoE text embedding model that excels at multilingual retrieval. | D39: embedding | F39: 199K | G39: 1 | H39: Tag | I39: 4 months ago
A40: https://ollama.com/library/minimax-m2.1 | B40: minimax-m2.1 | C40: Exceptional multilingual capabilities to elevate code engineering | D40: tools | F40: 154.5K | G40: 1 | H40: Tag | I40: 4 months ago
A41: https://ollama.com/library/functiongemma | B41: functiongemma | C41: FunctionGemma is a specialized version of Google's Gemma 3 270M model fine-tuned explicitly for function calling. | D41: tools | E41: 270m | F41: 154.5K | G41: 4 | H41: Tags | I41: 4 months ago
A42: https://ollama.com/library/cogito-2.1 | B42: cogito-2.1 | C42: The Cogito v2.1 LLMs are instruction tuned generative models. All models are released under MIT license for commercial use. | E42: 671b | F42: 179.8K | G42: 6 | H42: Tags | I42: 5 months ago
A43: https://ollama.com/library/mistral-large-3 | B43: mistral-large-3 | C43: A general-purpose multimodal mixture-of-experts model for production-grade tasks and enterprise workloads. | D43: vision | F43: 47.5K | G43: 1 | H43: Tag | I43: 5 months ago
A44: https://ollama.com/library/gpt-oss | B44: gpt-oss | C44: OpenAI’s open-weight models designed for powerful reasoning, agentic tasks, and versatile developer use cases. | D44: tools | E44: 20b | F44: 9.4M | G44: 5 | H44: Tags | I44: 6 months ago | J44: 120b
A45: https://ollama.com/library/qwen3-vl | B45: qwen3-vl | C45: The most powerful vision-language model in the Qwen model family to date. | D45: vision | E45: 2b | F45: 3.6M | G45: 59 | H45: Tags | I45: 6 months ago | J45: 4b | K45: 8b
A46: https://ollama.com/library/qwen3-coder | B46: qwen3-coder | C46: Alibaba's performant long context models for agentic and coding tasks. | D46: tools | E46: 30b | F46: 5.2M | G46: 10 | H46: Tags | I46: 7 months ago | J46: 480b
A47: https://ollama.com/library/qwen3-embedding | B47: qwen3-embedding | C47: Building upon the foundational models of the Qwen3 series, Qwen3 Embedding provides a comprehensive range of text embeddings models in various sizes | D47: embedding | E47: 0.6b | F47: 1.8M | G47: 12 | H47: Tags | I47: 7 months ago | J47: 4b | K47: 8b
A48: https://ollama.com/library/granite4 | B48: granite4 | C48: Granite 4 features improved instruction following (IF) and tool-calling capabilities, making them more effective in enterprise applications. | D48: tools | E48: 350m | F48: 1.2M | G48: 17 | H48: Tags | I48: 6 months ago | J48: 1b | K48: 3b
A49: https://ollama.com/library/mistral-small3.2 | B49: mistral-small3.2 | C49: An update to Mistral Small that improves on function calling, instruction following, and less repetition errors. | D49: vision | E49: 24b | F49: 1.9M | G49: 5 | H49: Tags | I49: 10 months ago
A50: https://ollama.com/library/embeddinggemma | B50: embeddinggemma | C50: EmbeddingGemma is a 300M parameter embedding model from Google. | D50: embedding | E50: 300m | F50: 1.1M | G50: 5 | H50: Tags | I50: 7 months ago
A51: https://ollama.com/library/qwen2.5vl | B51: qwen2.5vl | C51: Flagship vision-language model of Qwen and also a significant leap from the previous Qwen2-VL. | D51: vision | E51: 3b | F51: 1.9M | G51: 17 | H51: Tags | I51: 11 months ago | J51: 7b | K51: 32b
A52: https://ollama.com/library/gemma3n | B52: gemma3n | C52: Gemma 3n models are designed for efficient execution on everyday devices such as laptops, tablets or phones. | E52: e2b | F52: 1.6M | G52: 9 | H52: Tags | I52: 10 months ago | J52: e4b
A53: https://ollama.com/library/magistral | B53: magistral | C53: Magistral is a small, efficient reasoning model with 24B parameters. | D53: tools | E53: 24b | F53: 1.4M | G53: 5 | H53: Tags | I53: 10 months ago
A54: https://ollama.com/library/deepseek-v3.1 | B54: deepseek-v3.1 | C54: DeepSeek-V3.1-Terminus is a hybrid model that supports both thinking mode and non-thinking mode. | D54: tools | E54: 671b | F54: 669.6K | G54: 8 | H54: Tags | I54: 7 months ago
A55: https://ollama.com/library/devstral | B55: devstral | C55: Devstral: the best open source model for coding agents | D55: tools | E55: 24b | F55: 934.9K | G55: 5 | H55: Tags | I55: 10 months ago
A56: https://ollama.com/library/minimax-m2 | B56: minimax-m2 | C56: MiniMax M2 is a high-efficiency large language model built for coding and agentic workflows. | D56: tools | F56: 216.3K | G56: 1 | H56: Tag | I56: 6 months ago
A57: https://ollama.com/library/glm-4.6 | B57: glm-4.6 | C57: Advanced agentic, reasoning and coding capabilities. | D57: tools | F57: 220.6K | G57: 1 | H57: Tag | I57: 6 months ago
A58: https://ollama.com/library/kimi-k2-thinking | B58: kimi-k2-thinking | C58: Kimi K2 Thinking, Moonshot AI's best open-source thinking model. | D58: tools | F58: 170.8K | G58: 1 | H58: Tag | I58: 6 months ago
A59: https://ollama.com/library/gpt-oss-safeguard | B59: gpt-oss-safeguard | C59: gpt-oss-safeguard-20b and gpt-oss-safeguard-120b are safety reasoning models built-upon gpt-oss | D59: tools | E59: 20b | F59: 137.9K | G59: 3 | H59: Tags | I59: 6 months ago | J59: 120b
A60: https://ollama.com/library/kimi-k2 | B60: kimi-k2 | C60: A state-of-the-art mixture-of-experts (MoE) language model. Kimi K2-Instruct-0905 demonstrates significant improvements in performance on public benchmarks and real-world coding agent tasks. | D60: tools | F60: 63.9K | G60: 1 | H60: Tag | I60: 7 months ago
A61: https://ollama.com/library/deepseek-r1 | B61: deepseek-r1 | C61: DeepSeek-R1 is a family of open reasoning models with performance approaching that of leading models, such as O3 and Gemini 2.5 Pro. | D61: tools | E61: 1.5b | F61: 84.7M | G61: 35 | H61: Tags | I61: 10 months ago | J61: 7b | K61: 8b
A62: https://ollama.com/library/llama3.1 | B62: llama3.1 | C62: Llama 3.1 is a new state-of-the-art model from Meta available in 8B, 70B and 405B parameter sizes. | D62: tools | E62: 8b | F62: 114M | G62: 93 | H62: Tags | I62: 1 year ago | J62: 70b | K62: 405b
A63: https://ollama.com/library/llama3.2 | B63: llama3.2 | C63: Meta's Llama 3.2 goes small with 1B and 3B models. | D63: tools | E63: 1b | F63: 68.1M | G63: 63 | H63: Tags | I63: 1 year ago | J63: 3b
A64: https://ollama.com/library/gemma3 | B64: gemma3 | C64: The current, most capable model that runs on a single GPU. | D64: vision | E64: 270m | F64: 36.4M | G64: 29 | H64: Tags | I64: 5 months ago | J64: 1b | K64: 4b
A65: https://ollama.com/library/qwen3 | B65: qwen3 | C65: Qwen3 is the latest generation of large language models in Qwen series, offering a comprehensive suite of dense and mixture-of-experts (MoE) models. | D65: tools | E65: 0.6b | F65: 28.3M | G65: 58 | H65: Tags | I65: 6 months ago | J65: 1.7b | K65: 4b
A66: https://ollama.com/library/nomic-embed-text | B66: nomic-embed-text | C66: A high-performing open embedding model with a large token context window. | D66: embedding | F66: 68.4M | G66: 3 | H66: Tags | I66: 2 years ago
A67: https://ollama.com/library/qwen2.5 | B67: qwen2.5 | C67: Qwen2.5 models are pretrained on Alibaba's latest large-scale dataset, encompassing up to 18 trillion tokens. The model supports up to 128K tokens and has multilingual support. | D67: tools | E67: 0.5b | F67: 29.3M | G67: 133 | H67: Tags | I67: 1 year ago | J67: 1.5b | K67: 3b
A68: https://ollama.com/library/gemma2 | B68: gemma2 | C68: Google Gemma 2 is a high-performing and efficient model available in three sizes: 2B, 9B, and 27B. | E68: 2b | F68: 22.4M | G68: 94 | H68: Tags | I68: 1 year ago | J68: 9b | K68: 27b
A69: https://ollama.com/library/llama3 | B69: llama3 | C69: Meta Llama 3: The most capable openly available LLM to date | E69: 8b | F69: 23.7M | G69: 68 | H69: Tags | I69: 1 year ago | J69: 70b
A70: https://ollama.com/library/qwen2.5-coder | B70: qwen2.5-coder | C70: The latest series of Code-Specific Qwen models, with significant improvements in code generation, code reasoning, and code fixing. | D70: tools | E70: 0.5b | F70: 15.2M | G70: 199 | H70: Tags | I70: 11 months ago | J70: 1.5b | K70: 3b
A71: https://ollama.com/library/mistral | B71: mistral | C71: The 7B model released by Mistral AI, updated to version 0.3. | D71: tools | E71: 7b | F71: 29M | G71: 84 | H71: Tags | I71: 9 months ago
A72: https://ollama.com/library/phi3 | B72: phi3 | C72: Phi-3 is a family of lightweight 3B (Mini) and 14B (Medium) state-of-the-art open models by Microsoft. | E72: 3.8b | F72: 17.4M | G72: 72 | H72: Tags | I72: 1 year ago | J72: 14b
A73: https://ollama.com/library/phi4 | B73: phi4 | C73: Phi-4 is a 14B parameter, state-of-the-art open model from Microsoft. | E73: 14b | F73: 7.5M | G73: 5 | H73: Tags | I73: 1 year ago
A74: https://ollama.com/library/llava | B74: llava | C74: 🌋 LLaVA is a novel end-to-end trained large multimodal model that combines a vision encoder and Vicuna for general-purpose visual and language understanding. Updated to version 1.6. | D74: vision | E74: 7b | F74: 14M | G74: 98 | H74: Tags | I74: 2 years ago | J74: 13b | K74: 34b
A75: https://ollama.com/library/mxbai-embed-large | B75: mxbai-embed-large | C75: State-of-the-art large embedding model from mixedbread.ai | D75: embedding | E75: 335m | F75: 10.3M | G75: 4 | H75: Tags | I75: 1 year ago
A76: https://ollama.com/library/deepseek-v3 | B76: deepseek-v3 | C76: A strong Mixture-of-Experts (MoE) language model with 671B total parameters with 37B activated for each token. | E76: 671b | F76: 3.8M | G76: 5 | H76: Tags | I76: 1 year ago
A77: https://ollama.com/library/dolphin3 | B77: dolphin3 | C77: Dolphin 3.0 Llama 3.1 8B 🐬 is the next generation of the Dolphin series of instruct-tuned models designed to be the ultimate general purpose local model, enabling coding, math, agentic, function calling, and general use cases. | E77: 8b | F77: 3.8M | G77: 5 | H77: Tags | I77: 1 year ago
A78: https://ollama.com/library/olmo2 | B78: olmo2 | C78: OLMo 2 is a new family of 7B and 13B models trained on up to 5T tokens. These models are on par with or better than equivalently sized fully open models, and competitive with open-weight models such as Llama 3.1 on English academic benchmarks. | E78: 7b | F78: 3.7M | G78: 9 | H78: Tags | I78: 1 year ago | J78: 13b
A79: https://ollama.com/library/llama3.2-vision | B79: llama3.2-vision | C79: Llama 3.2 Vision is a collection of instruction-tuned image reasoning generative models in 11B and 90B sizes. | D79: vision | E79: 11b | F79: 4.5M | G79: 9 | H79: Tags | I79: 11 months ago | J79: 90b
A80: https://ollama.com/library/minicpm-v | B80: minicpm-v | C80: A series of multimodal LLMs (MLLMs) designed for vision-language understanding. | D80: vision | E80: 8b | F80: 5.1M | G80: 17 | H80: Tags | I80: 1 year ago
A81: https://ollama.com/library/llama3.3 | B81: llama3.3 | C81: New state of the art 70B model. Llama 3.3 70B offers similar performance compared to the Llama 3.1 405B model. | D81: tools | E81: 70b | F81: 3.8M | G81: 14 | H81: Tags | I81: 1 year ago
A82: https://ollama.com/library/qwen2 | B82: qwen2 | C82: Qwen2 is a new series of large language models from Alibaba group | D82: tools | E82: 0.5b | F82: 5.8M | G82: 97 | H82: Tags | I82: 1 year ago | J82: 1.5b | K82: 7b
A83: https://ollama.com/library/gemma | B83: gemma | C83: Gemma is a family of lightweight, state-of-the-art open models built by Google DeepMind. Updated to version 1.1 | E83: 2b | F83: 7M | G83: 102 | H83: Tags | I83: 2 years ago | J83: 7b
A84: https://ollama.com/library/qwen | B84: qwen | C84: Qwen 1.5 is a series of large language models by Alibaba Cloud spanning from 0.5B to 110B parameters | E84: 0.5b | F84: 6.6M | G84: 379 | H84: Tags | I84: 2 years ago | J84: 1.8b | K84: 4b
A85: https://ollama.com/library/smollm2 | B85: smollm2 | C85: SmolLM2 is a family of compact language models available in three size: 135M, 360M, and 1.7B parameters. | D85: tools | E85: 135m | F85: 3.4M | G85: 49 | H85: Tags | I85: 1 year ago | J85: 360m | K85: 1.7b
A86: https://ollama.com/library/mistral-nemo | B86: mistral-nemo | C86: A state-of-the-art 12B model with 128k context length, built by Mistral AI in collaboration with NVIDIA. | D86: tools | E86: 12b | F86: 4.3M | G86: 17 | H86: Tags | I86: 9 months ago
A87: https://ollama.com/library/granite3.1-moe | B87: granite3.1-moe | C87: The IBM Granite 1B and 3B models are long-context mixture of experts (MoE) Granite models from IBM designed for low latency usage. | D87: tools | E87: 1b | F87: 2.9M | G87: 33 | H87: Tags | I87: 1 year ago | J87: 3b
A88: https://ollama.com/library/bge-m3 | B88: bge-m3 | C88: BGE-M3 is a new model from BAAI distinguished for its versatility in Multi-Functionality, Multi-Linguality, and Multi-Granularity. | D88: embedding | E88: 567m | F88: 4.1M | G88: 3 | H88: Tags | I88: 1 year ago
A89: https://ollama.com/library/cogito | B89: cogito | C89: Cogito v1 Preview is a family of hybrid reasoning models by Deep Cogito that outperform the best available open models of the same size, including counterparts from LLaMA, DeepSeek, and Qwen across most standard benchmarks. | D89: tools | E89: 3b | F89: 2M | G89: 20 | H89: Tags | I89: 1 year ago | J89: 8b | K89: 14b
A90: https://ollama.com/library/falcon3 | B90: falcon3 | C90: A family of efficient AI models under 10B parameters performant in science, math, and coding through innovative training techniques. | E90: 1b | F90: 2.6M | G90: 17 | H90: Tags | I90: 1 year ago | J90: 3b | K90: 7b
A91: https://ollama.com/library/llama2 | B91: llama2 | C91: Llama 2 is a collection of foundation language models ranging from 7B to 70B parameters. | E91: 7b | F91: 6.8M | G91: 102 | H91: Tags | I91: 2 years ago | J91: 13b | K91: 70b
A92: https://ollama.com/library/phi4-reasoning | B92: phi4-reasoning | C92: Phi 4 reasoning and reasoning plus are 14-billion parameter open-weight reasoning models that rival much larger models on complex reasoning tasks. | E92: 14b | F92: 1.5M | G92: 9 | H92: Tags | I92: 1 year ago
A93: https://ollama.com/library/mistral-small | B93: mistral-small | C93: Mistral Small 3 sets a new benchmark in the “small” Large Language Models category below 70B. | D93: tools | E93: 22b | F93: 3M | G93: 21 | H93: Tags | I93: 1 year ago | J93: 24b
A94: https://ollama.com/library/llama4 | B94: llama4 | C94: Meta's latest collection of multimodal models. | D94: vision | E94: 16x17b | F94: 1.6M | G94: 11 | H94: Tags | I94: 10 months ago | J94: 128x17b
A95: https://ollama.com/library/tinyllama | B95: tinyllama | C95: The TinyLlama project is an open endeavor to train a compact 1.1B Llama model on 3 trillion tokens. | E95: 1.1b | F95: 4.8M | G95: 36 | H95: Tags | I95: 2 years ago
A96: https://ollama.com/library/qwq | B96: qwq | C96: QwQ is the reasoning model of the Qwen series. | D96: tools | E96: 32b | F96: 2.2M | G96: 8 | H96: Tags | I96: 1 year ago
A97: https://ollama.com/library/codellama | B97: codellama | C97: A large language model that can use text prompts to generate and discuss code. | E97: 7b | F97: 5.5M | G97: 199 | H97: Tags | I97: 1 year ago | J97: 13b | K97: 34b
A98: https://ollama.com/library/deepseek-coder | B98: deepseek-coder | C98: DeepSeek Coder is a capable coding model trained on two trillion code and natural language tokens. | E98: 1.3b | F98: 4.1M | G98: 102 | H98: Tags | I98: 2 years ago | J98: 6.7b | K98: 33b
A99: https://ollama.com/library/snowflake-arctic-embed | B99: snowflake-arctic-embed | C99: A suite of text embedding models by Snowflake, optimized for performance. | D99: embedding | E99: 22m | F99: 3.1M | G99: 16 | H99: Tags | I99: 2 years ago | J99: 33m | K99: 110m
A100: https://ollama.com/library/codegemma | B100: codegemma | C100: CodeGemma is a collection of powerful, lightweight models that can perform a variety of coding tasks like fill-in-the-middle code completion, code generation, natural language understanding, mathematical reasoning, and instruction following. | E100: 2b | F100: 3M | G100: 85 | H100: Tags | I100: 1 year ago | J100: 7b
...

Sheet Unique Organization
E1: -
B2: {=TRANSPOSE('Unique LMStudio'!S2:AM3)} -> https://llm-stats.com/organizations/nvidia | C2: Nemotron | D2: =SUBSTITUTE(B2,"https://llm-stats.com/organizations/","") -> nvidia | E2: - | F2: =VLOOKUP(B2,'LLM Stats Organization'!C$2:D995,2,false) -> 12 | G2: =VLOOKUP(B2,'LLM Stats Organization'!C$2:H995,6,false) -> 7
B3: https://llm-stats.com/organizations/qwen | C3: Qwen | D3: =SUBSTITUTE(B3,"https://llm-stats.com/organizations/","") -> qwen | E3: - | F3: =VLOOKUP(B3,'LLM Stats Organization'!C$2:D995,2,false) -> 3 | G3: =VLOOKUP(B3,'LLM Stats Organization'!C$2:H995,6,false) -> 51
B4: https://llm-stats.com/organizations/google | C4: Gemma | D4: =SUBSTITUTE(B4,"https://llm-stats.com/organizations/","") -> google | E4: - | F4: =VLOOKUP(B4,'LLM Stats Organization'!C$2:D995,2,false) -> 8 | G4: =VLOOKUP(B4,'LLM Stats Organization'!C$2:H995,6,false) -> 44
B5: https://llm-stats.com/organizations/zai-org | C5: GLM | D5: =SUBSTITUTE(B5,"https://llm-stats.com/organizations/","") -> zai-org | E5: - | F5: =VLOOKUP(B5,'LLM Stats Organization'!C$2:D995,2,false) -> 7 | G5: =VLOOKUP(B5,'LLM Stats Organization'!C$2:H995,6,false) -> 11
B6: https://llm-stats.com/organizations/microsoft | C6: Phi | D6: =SUBSTITUTE(B6,"https://llm-stats.com/organizations/","") -> microsoft | E6: - | F6: =VLOOKUP(B6,'LLM Stats Organization'!C$2:D995,2,false) -> 28 | G6: =VLOOKUP(B6,'LLM Stats Organization'!C$2:H995,6,false) -> 9
B7: https://llm-stats.com/organizations/mistral | C7: Mistral | D7: =SUBSTITUTE(B7,"https://llm-stats.com/organizations/","") -> mistral | E7: - | F7: =VLOOKUP(B7,'LLM Stats Organization'!C$2:D995,2,false) -> 11 | G7: =VLOOKUP(B7,'LLM Stats Organization'!C$2:H995,6,false) -> 32
B8: https://llm-stats.com/organizations/mistral | C8: Codestral | D8: =SUBSTITUTE(B8,"https://llm-stats.com/organizations/","") -> mistral | E8: - | F8: =VLOOKUP(B8,'LLM Stats Organization'!C$2:D995,2,false) -> 11 | G8: =VLOOKUP(B8,'LLM Stats Organization'!C$2:H995,6,false) -> 32
B9: https://llm-stats.com/organizations/mistral | C9: Magistral | D9: =SUBSTITUTE(B9,"https://llm-stats.com/organizations/","") -> mistral | E9: - | F9: =VLOOKUP(B9,'LLM Stats Organization'!C$2:D995,2,false) -> 11 | G9: =VLOOKUP(B9,'LLM Stats Organization'!C$2:H995,6,false) -> 32
B10: https://llm-stats.com/organizations/deepseek | C10: Deepseek | D10: =SUBSTITUTE(B10,"https://llm-stats.com/organizations/","") -> deepseek | E10: - | F10: =VLOOKUP(B10,'LLM Stats Organization'!C$2:D995,2,false) -> 2 | G10: =VLOOKUP(B10,'LLM Stats Organization'!C$2:H995,6,false) -> 23
B11: https://llm-stats.com/organizations/mistral | C11: Devstral | D11: =SUBSTITUTE(B11,"https://llm-stats.com/organizations/","") -> mistral | E11: - | F11: =VLOOKUP(B11,'LLM Stats Organization'!C$2:D995,2,false) -> 11 | G11: =VLOOKUP(B11,'LLM Stats Organization'!C$2:H995,6,false) -> 32
B12: https://llm-stats.com/organizations/mistral | C12: Ministral | D12: =SUBSTITUTE(B12,"https://llm-stats.com/organizations/","") -> mistral | E12: - | F12: =VLOOKUP(B12,'LLM Stats Organization'!C$2:D995,2,false) -> 11 | G12: =VLOOKUP(B12,'LLM Stats Organization'!C$2:H995,6,false) -> 32
B13: https://llm-stats.com/organizations/openai | C13: GPT | D13: =SUBSTITUTE(B13,"https://llm-stats.com/organizations/","") -> openai | E13: - | F13: =VLOOKUP(B13,'LLM Stats Organization'!C$2:D995,2,false) -> 1 | G13: =VLOOKUP(B13,'LLM Stats Organization'!C$2:H995,6,false) -> 58
B14: https://www.together.ai/models/lfm2-24b-a2b | E14: - | F14: =VLOOKUP(B14,'LLM Stats Organization'!C$2:D995,2,false) -> #N/A
B15: https://huggingface.co/EssentialAI/rnj-1 | E15: - | F15: =VLOOKUP(B15,'LLM Stats Organization'!C$2:D995,2,false) -> #N/A
B16: https://allenai.org/blog/olmo3 | E16: - | F16: =VLOOKUP(B16,'LLM Stats Organization'!C$2:D995,2,false) -> #N/A
B17: https://olmocr.allenai.org/ | E17: - | F17: =VLOOKUP(B17,'LLM Stats Organization'!C$2:D995,2,false) -> #N/A
B18: https://huggingface.co/MiniMaxAI/MiniMax-M2 | E18: - | F18: =VLOOKUP(B18,'LLM Stats Organization'!C$2:D995,2,false) -> #N/A
B19: https://ernie.baidu.com/ | E19: - | F19: =VLOOKUP(B19,'LLM Stats Organization'!C$2:D995,2,false) -> #N/A
B20: https://github.com/ByteDance-Seed/seed-oss | E20: - | F20: =VLOOKUP(B20,'LLM Stats Organization'!C$2:D995,2,false) -> #N/A
B21: https://www.ibm.com/granite/docs/models/granite | E21: - | F21: =VLOOKUP(B21,'LLM Stats Organization'!C$2:D995,2,false) -> #N/A
E22: - | F22: =VLOOKUP(B22,'LLM Stats Organization'!C$2:D995,2,false) -> #N/A
B23: https://llm-stats.com/organizations/moonshotai | E23: - | F23: =VLOOKUP(B23,'LLM Stats Organization'!C$2:H995,2,false) -> 4 | G23: =VLOOKUP(B23,'LLM Stats Organization'!C$2:H995,6,false) -> 8
B24: https://llm-stats.com/organizations/anthropic | E24: - | F24: =VLOOKUP(B24,'LLM Stats Organization'!C$2:D995,2,false) -> 5 | G24: =VLOOKUP(B24,'LLM Stats Organization'!C$2:H995,6,false) -> 17
B25: https://llm-stats.com/organizations/meta | E25: - | F25: =VLOOKUP(B25,'LLM Stats Organization'!C$2:D995,2,false) -> 6 | G25: =VLOOKUP(B25,'LLM Stats Organization'!C$2:H995,6,false) -> 10
B26: https://llm-stats.com/organizations/minimax | E26: - | F26: =VLOOKUP(B26,'LLM Stats Organization'!C$2:D995,2,false) -> 9 | G26: =VLOOKUP(B26,'LLM Stats Organization'!C$2:H995,6,false) -> 13
B27: https://llm-stats.com/organizations/xiaomi | E27: - | F27: =VLOOKUP(B27,'LLM Stats Organization'!C$2:D995,2,false) -> 10 | G27: =VLOOKUP(B27,'LLM Stats Organization'!C$2:H995,6,false) -> 3
B28: https://llm-stats.com/organizations/xai | E28: - | F28: =VLOOKUP(B28,'LLM Stats Organization'!C$2:D995,2,false) -> 13 | G28: =VLOOKUP(B28,'LLM Stats Organization'!C$2:H995,6,false) -> 23
B29: https://llm-stats.com/organizations/sarvamai | E29: - | F29: =VLOOKUP(B29,'LLM Stats Organization'!C$2:D995,2,false) -> 14 | G29: =VLOOKUP(B29,'LLM Stats Organization'!C$2:H995,6,false) -> 2
B30: https://llm-stats.com/organizations/inceptionlabs | E30: - | F30: =VLOOKUP(B30,'LLM Stats Organization'!C$2:D995,2,false) -> 15 | G30: =VLOOKUP(B30,'LLM Stats Organization'!C$2:H995,6,false) -> 1
B31: https://llm-stats.com/organizations/bytedance | E31: - | F31: =VLOOKUP(B31,'LLM Stats Organization'!C$2:D995,2,false) -> 16 | G31: =VLOOKUP(B31,'LLM Stats Organization'!C$2:H995,6,false) -> 9
B32: https://llm-stats.com/organizations/openbmb | E32: - | F32: =VLOOKUP(B32,'LLM Stats Organization'!C$2:D995,2,false) -> 17 | G32: =VLOOKUP(B32,'LLM Stats Organization'!C$2:H995,6,false) -> 1
B33: https://llm-stats.com/organizations/meituan | E33: - | F33: =VLOOKUP(B33,'LLM Stats Organization'!C$2:D995,2,false) -> 18 | G33: =VLOOKUP(B33,'LLM Stats Organization'!C$2:H995,6,false) -> 4
B34: https://llm-stats.com/organizations/stepfun | E34: - | F34: =VLOOKUP(B34,'LLM Stats Organization'!C$2:D995,2,false) -> 19 | G34: =VLOOKUP(B34,'LLM Stats Organization'!C$2:H995,6,false) -> 2
B35: https://llm-stats.com/organizations/baidu | E35: - | F35: =VLOOKUP(B35,'LLM Stats Organization'!C$2:D995,2,false) -> 20 | G35: =VLOOKUP(B35,'LLM Stats Organization'!C$2:H995,6,false) -> 2
B36: https://llm-stats.com/organizations/black-forest-labs | E36: - | F36: =VLOOKUP(B36,'LLM Stats Organization'!C$2:D995,2,false) -> 21 | G36: =VLOOKUP(B36,'LLM Stats Organization'!C$2:H995,6,false) -> 8
B37: https://llm-stats.com/organizations/wanvideo | E37: - | F37: =VLOOKUP(B37,'LLM Stats Organization'!C$2:D995,2,false) -> 22 | G37: =VLOOKUP(B37,'LLM Stats Organization'!C$2:H995,6,false) -> 4
B38: https://llm-stats.com/organizations/kling | E38: - | F38: =VLOOKUP(B38,'LLM Stats Organization'!C$2:D995,2,false) -> 23 | G38: =VLOOKUP(B38,'LLM Stats Organization'!C$2:H995,6,false) -> 3
B39: https://llm-stats.com/organizations/lg | E39: - | F39: =VLOOKUP(B39,'LLM Stats Organization'!C$2:D995,2,false) -> 24 | G39: =VLOOKUP(B39,'LLM Stats Organization'!C$2:H995,6,false) -> 1
B40: https://llm-stats.com/organizations/cartesia | E40: - | F40: =VLOOKUP(B40,'LLM Stats Organization'!C$2:D995,2,false) -> 25 | G40: =VLOOKUP(B40,'LLM Stats Organization'!C$2:H995,6,false) -> 4
B41: https://llm-stats.com/organizations/luma | E41: - | F41: =VLOOKUP(B41,'LLM Stats Organization'!C$2:D995,2,false) -> 26 | G41: =VLOOKUP(B41,'LLM Stats Organization'!C$2:H995,6,false) -> 4
B42: https://llm-stats.com/organizations/ibm | E42: - | F42: =VLOOKUP(B42,'LLM Stats Organization'!C$2:D995,2,false) -> 27 | G42: =VLOOKUP(B42,'LLM Stats Organization'!C$2:H995,6,false) -> 3
B43: https://llm-stats.com/organizations/rime | E43: - | F43: =VLOOKUP(B43,'LLM Stats Organization'!C$2:D995,2,false) -> 29 | G43: =VLOOKUP(B43,'LLM Stats Organization'!C$2:H995,6,false) -> 1
B44: https://llm-stats.com/organizations/elevenlabs | E44: - | F44: =VLOOKUP(B44,'LLM Stats Organization'!C$2:D995,2,false) -> 30 | G44: =VLOOKUP(B44,'LLM Stats Organization'!C$2:H995,6,false) -> 5
B45: https://llm-stats.com/organizations/reve-ai | E45: - | F45: =VLOOKUP(B45,'LLM Stats Organization'!C$2:D995,2,false) -> 31 | G45: =VLOOKUP(B45,'LLM Stats Organization'!C$2:H995,6,false) -> 1
B46: https://llm-stats.com/organizations/amazon | E46: - | F46: =VLOOKUP(B46,'LLM Stats Organization'!C$2:D995,2,false) -> 32 | G46: =VLOOKUP(B46,'LLM Stats Organization'!C$2:H995,6,false) -> 3
B47: https://llm-stats.com/organizations/runway | E47: - | F47: =VLOOKUP(B47,'LLM Stats Organization'!C$2:D995,2,false) -> 33 | G47: =VLOOKUP(B47,'LLM Stats Organization'!C$2:H995,6,false) -> 4
B48: https://llm-stats.com/organizations/fireworks | E48: - | F48: =VLOOKUP(B48,'LLM Stats Organization'!C$2:D995,2,false) -> 34 | G48: =VLOOKUP(B48,'LLM Stats Organization'!C$2:H995,6,false) -> 2
B49: https://llm-stats.com/organizations/playai | E49: - | F49: =VLOOKUP(B49,'LLM Stats Organization'!C$2:D995,2,false) -> 35 | G49: =VLOOKUP(B49,'LLM Stats Organization'!C$2:H995,6,false) -> 1
B50: https://llm-stats.com/organizations/deepgram | E50: - | F50: =VLOOKUP(B50,'LLM Stats Organization'!C$2:D995,2,false) -> 36 | G50: =VLOOKUP(B50,'LLM Stats Organization'!C$2:H995,6,false) -> 6
B51: https://llm-stats.com/organizations/recraft-ai | E51: - | F51: =VLOOKUP(B51,'LLM Stats Organization'!C$2:D995,2,false) -> 37 | G51: =VLOOKUP(B51,'LLM Stats Organization'!C$2:H995,6,false) -> 1
B52: https://llm-stats.com/organizations/inworld | E52: - | F52: =VLOOKUP(B52,'LLM Stats Organization'!C$2:D995,2,false) -> 38 | G52: =VLOOKUP(B52,'LLM Stats Organization'!C$2:H995,6,false) -> 2
B53: https://llm-stats.com/organizations/cohere | E53: - | F53: =VLOOKUP(B53,'LLM Stats Organization'!C$2:D995,2,false) -> 39 | G53: =VLOOKUP(B53,'LLM Stats Organization'!C$2:H995,6,false) -> 1
B54: https://llm-stats.com/organizations/ai21 | E54: - | F54: =VLOOKUP(B54,'LLM Stats Organization'!C$2:D995,2,false) -> 40 | G54: =VLOOKUP(B54,'LLM Stats Organization'!C$2:H995,6,false) -> 2
B55: https://llm-stats.com/organizations/nous-research | E55: - | F55: =VLOOKUP(B55,'LLM Stats Organization'!C$2:D995,2,false) -> 41 | G55: =VLOOKUP(B55,'LLM Stats Organization'!C$2:H995,6,false) -> 1
B56: https://llm-stats.com/organizations/assemblyai | E56: - | F56: =VLOOKUP(B56,'LLM Stats Organization'!C$2:D995,2,false) -> 42 | G56: =VLOOKUP(B56,'LLM Stats Organization'!C$2:H995,6,false) -> 3
B57: https://llm-stats.com/organizations/tencent | E57: - | F57: =VLOOKUP(B57,'LLM Stats Organization'!C$2:D995,2,false) -> 43 | G57: =VLOOKUP(B57,'LLM Stats Organization'!C$2:H995,6,false) -> 1
B58: https://llm-stats.com/organizations/unknown | E58: - | F58: =VLOOKUP(B58,'LLM Stats Organization'!C$2:D995,2,false) -> 44 | G58: =VLOOKUP(B58,'LLM Stats Organization'!C$2:H995,6,false) -> 0
E59: -
E60: -
E61: -
E62: -
E63: -
E64: -
E65: -
E66: -
E67: -
E68: -
E69: -
E70: -
... E995: -

Sheet Ollama Model
A1: Model Link | B1: Model Name | C1: Status | M1: Description | N1: Downloads/Pulls | O1: Updated | Q1: Tag | R1: Tag | S1: Tag | T1: Tag | U1: Tag
A2: https://ollama.com/library/llama3.1 | B2: llama3.1 | F2: https://llm-stats.com/models/llama-3.1-8b-instruct | G2: =VLOOKUP(B2,'LLM Stats list of Model'!C$2:I1001,7,FALSE) -> #N/A | H2: =VLOOKUP(B2,'LLM Stats list of Model'!C$2:I1001,2,FALSE) -> #N/A | I2: =VLOOKUP(F2,'LLM Stats list of Model'!B$2:I1001,8,FALSE) -> 45474 | J2: =VLOOKUP(F2,'LLM Stats list of Model'!B$2:I1001,3,FALSE) | K2: =IF(ISNA(G2),I2,G2) -> 45474 | L2: =IF(ISNA(H2),J2,H2) | M2: Llama 3.1 is a new state-of-the-art model from Meta available in 8B, 70B and 405B parameter sizes. | N2: 114M | O2: 1 year ago | P2: Tags | Q2: 93 | R2: tools | S2: 8b | T2: 70b | U2: 405b
A3: https://ollama.com/library/phi3 | B3: phi3 | F3: https://llm-stats.com/models/phi-3.5-mini-instruct | G3: =VLOOKUP(B3,'LLM Stats list of Model'!C$2:I1001,7,FALSE) -> #N/A | H3: =VLOOKUP(B3,'LLM Stats list of Model'!C$2:I1001,2,FALSE) -> #N/A | I3: =VLOOKUP(F3,'LLM Stats list of Model'!B$2:I1001,8,FALSE) -> 45505 | J3: =VLOOKUP(F3,'LLM Stats list of Model'!B$2:I1001,3,FALSE) -> microsoft | K3: =IF(ISNA(G3),I3,G3) -> 45505 | L3: =IF(ISNA(H3),J3,H3) -> microsoft | M3: Phi-3 is a family of lightweight 3B (Mini) and 14B (Medium) state-of-the-art open models by Microsoft. | N3: 17.4M | O3: 1 year ago | P3: Tags | Q3: 72 | S3: 3.8b | T3: 14b
A4: https://ollama.com/library/qwen2.5-coder | B4: qwen2.5-coder | F4: https://llm-stats.com/models/qwen-2.5-coder-7b-instruct | G4: =VLOOKUP(B4,'LLM Stats list of Model'!C$2:I1001,7,FALSE) -> #N/A | H4: =VLOOKUP(B4,'LLM Stats list of Model'!C$2:I1001,2,FALSE) -> #N/A | I4: =VLOOKUP(F4,'LLM Stats list of Model'!B$2:I1001,8,FALSE) -> 45536 | J4: =VLOOKUP(F4,'LLM Stats list of Model'!B$2:I1001,3,FALSE) -> qwen | K4: =IF(ISNA(G4),I4,G4) -> 45536 | L4: =IF(ISNA(H4),J4,H4) -> qwen | M4: The latest series of Code-Specific Qwen models, with significant improvements in code generation, code reasoning, and code fixing. | N4: 15.2M | O4: 11 months ago | P4: Tags | Q4: 199 | R4: tools | S4: 0.5b | T4: 1.5b | U4: 3b
A5: https://ollama.com/library/mistral | B5: mistral | F5: https://llm-stats.com/models/mistral-small-2409 | G5: =VLOOKUP(B5,'LLM Stats list of Model'!C$2:I1001,7,FALSE) -> #N/A | H5: =VLOOKUP(B5,'LLM Stats list of Model'!C$2:I1001,2,FALSE) -> #N/A | I5: =VLOOKUP(F5,'LLM Stats list of Model'!B$2:I1001,8,FALSE) -> 45536 | J5: =VLOOKUP(F5,'LLM Stats list of Model'!B$2:I1001,3,FALSE) -> mistral | K5: =IF(ISNA(G5),I5,G5) -> 45536 | L5: =IF(ISNA(H5),J5,H5) -> mistral | M5: The 7B model released by Mistral AI, updated to version 0.3. | N5: 29M | O5: 9 months ago | P5: Tags | Q5: 84 | R5: tools | S5: 7b
A6: https://ollama.com/library/llama3.2-vision | B6: llama3.2-vision | F6: https://llm-stats.com/models/llama-3.2-3b-instruct | G6: =VLOOKUP(B6,'LLM Stats list of Model'!C$2:I1001,7,FALSE) -> #N/A | H6: =VLOOKUP(B6,'LLM Stats list of Model'!C$2:I1001,2,FALSE) -> #N/A | I6: =VLOOKUP(F6,'LLM Stats list of Model'!B$2:I1001,8,FALSE) -> 45536 | J6: =VLOOKUP(F6,'LLM Stats list of Model'!B$2:I1001,3,FALSE) | K6: =IF(ISNA(G6),I6,G6) -> 45536 | L6: =IF(ISNA(H6),J6,H6) | M6: Llama 3.2 Vision is a collection of instruction-tuned image reasoning generative models in 11B and 90B sizes. | N6: 4.5M | O6: 11 months ago | P6: Tags | Q6: 9 | R6: vision | S6: 11b | T6: 90b
A7: https://ollama.com/library/phi4 | B7: phi4 | F7: https://llm-stats.com/models/phi-4 | G7: =VLOOKUP(B7,'LLM Stats list of Model'!C$2:I1001,7,FALSE) -> #N/A | H7: =VLOOKUP(B7,'LLM Stats list of Model'!C$2:I1001,2,FALSE) -> #N/A | I7: =VLOOKUP(F7,'LLM Stats list of Model'!B$2:I1001,8,FALSE) -> 45627 | J7: =VLOOKUP(F7,'LLM Stats list of Model'!B$2:I1001,3,FALSE) -> microsoft | K7: =IF(ISNA(G7),I7,G7) -> 45627 | L7: =IF(ISNA(H7),J7,H7) -> microsoft | M7: Phi-4 is a 14B parameter, state-of-the-art open model from Microsoft. | N7: 7.5M | O7: 1 year ago | P7: Tags | Q7: 5 | S7: 14b
A8: https://ollama.com/library/deepseek-v3 | B8: deepseek-v3 | F8: https://llm-stats.com/models/deepseek-v3 | G8: =VLOOKUP(B8,'LLM Stats list of Model'!C$2:I1001,7,FALSE) -> 45627 | H8: =VLOOKUP(B8,'LLM Stats list of Model'!C$2:I1001,2,FALSE) -> deepseek | I8: =VLOOKUP(F8,'LLM Stats list of Model'!B$2:I1001,8,FALSE) -> 45627 | J8: =VLOOKUP(F8,'LLM Stats list of Model'!B$2:I1001,3,FALSE) -> deepseek | K8: =IF(ISNA(G8),I8,G8) -> 45627 | L8: =IF(ISNA(H8),J8,H8) -> deepseek | M8: A strong Mixture-of-Experts (MoE) language model with 671B total parameters with 37B activated for each token. | N8: 3.8M | O8: 1 year ago | P8: Tags | Q8: 5 | S8: 671b
A9: https://ollama.com/library/llama3.3 | B9: llama3.3 | F9: https://llm-stats.com/models/llama-3.3-70b-instruct | G9: =VLOOKUP(B9,'LLM Stats list of Model'!C$2:I1001,7,FALSE) -> #N/A | H9: =VLOOKUP(B9,'LLM Stats list of Model'!C$2:I1001,2,FALSE) -> #N/A | I9: =VLOOKUP(F9,'LLM Stats list of Model'!B$2:I1001,8,FALSE) -> 45627 | J9: =VLOOKUP(F9,'LLM Stats list of Model'!B$2:I1001,3,FALSE) | K9: =IF(ISNA(G9),I9,G9) -> 45627 | L9: =IF(ISNA(H9),J9,H9) | M9: New state of the art 70B model. Llama 3.3 70B offers similar performance compared to the Llama 3.1 405B model. | N9: 3.8M | O9: 1 year ago | P9: Tags | Q9: 14 | R9: tools | S9: 70b
A10: https://ollama.com/library/qwen3-coder | B10: qwen3-coder | F10: https://llm-stats.com/models/qwen3-coder | G10: =VLOOKUP(B10,'LLM Stats list of Model'!C$2:I1001,7,FALSE) -> 45658 | H10: =VLOOKUP(B10,'LLM Stats list of Model'!C$2:I1001,2,FALSE) -> qwen | I10: =VLOOKUP(F10,'LLM Stats list of Model'!B$2:I1001,8,FALSE) -> 45658 | J10: =VLOOKUP(F10,'LLM Stats list of Model'!B$2:I1001,3,FALSE) -> qwen | K10: =IF(ISNA(G10),I10,G10) -> 45658 | L10: =IF(ISNA(H10),J10,H10) -> qwen | M10: Alibaba's performant long context models for agentic and coding tasks. | N10: 5.2M | O10: 7 months ago | P10: Tags | Q10: 10 | R10: tools | S10: 30b | T10: 480b
A11: https://ollama.com/library/qwen2.5vl | B11: qwen2.5vl | F11: https://llm-stats.com/models/qwen2.5-vl-7b | G11: =VLOOKUP(B11,'LLM Stats list of Model'!C$2:I1001,7,FALSE) -> #N/A | H11: =VLOOKUP(B11,'LLM Stats list of Model'!C$2:I1001,2,FALSE) -> #N/A | I11: =VLOOKUP(F11,'LLM Stats list of Model'!B$2:I1001,8,FALSE) -> 45658 | J11: =VLOOKUP(F11,'LLM Stats list of Model'!B$2:I1001,3,FALSE) -> qwen | K11: =IF(ISNA(G11),I11,G11) -> 45658 | L11: =IF(ISNA(H11),J11,H11) -> qwen | M11: Flagship vision-language model of Qwen and also a significant leap from the previous Qwen2-VL. | N11: 1.9M | O11: 11 months ago | P11: Tags | Q11: 17 | R11: vision | S11: 3b | T11: 7b | U11: 32b
A12: https://ollama.com/library/deepseek-v3.1 | B12: deepseek-v3.1 | C12: Skipped due to old | G12: =VLOOKUP(B12,'LLM Stats list of Model'!C$2:I1001,7,FALSE) -> 45658 | H12: =VLOOKUP(B12,'LLM Stats list of Model'!C$2:I1001,2,FALSE) -> deepseek | I12: =VLOOKUP(F12,'LLM Stats list of Model'!B$2:I1001,8,FALSE) -> #N/A | J12: =VLOOKUP(F12,'LLM Stats list of Model'!B$2:I1001,3,FALSE) -> #N/A | K12: =IF(ISNA(G12),I12,G12) -> 45658 | L12: =IF(ISNA(H12),J12,H12) -> deepseek | M12: DeepSeek-V3.1-Terminus is a hybrid model that supports both thinking mode and non-thinking mode. | N12: 669.6K | O12: 7 months ago | P12: Tags | Q12: 8 | R12: tools | S12: 671b
A13: https://ollama.com/library/deepseek-r1 | B13: deepseek-r1 | F13: https://llm-stats.com/models/deepseek-r1 | G13: =VLOOKUP(B13,'LLM Stats list of Model'!C$2:I1001,7,FALSE) -> 45658 | H13: =VLOOKUP(B13,'LLM Stats list of Model'!C$2:I1001,2,FALSE) -> deepseek | I13: =VLOOKUP(F13,'LLM Stats list of Model'!B$2:I1001,8,FALSE) -> 45658 | J13: =VLOOKUP(F13,'LLM Stats list of Model'!B$2:I1001,3,FALSE) -> deepseek | K13: =IF(ISNA(G13),I13,G13) -> 45658 | L13: =IF(ISNA(H13),J13,H13) -> deepseek | M13: DeepSeek-R1 is a family of open reasoning models with performance approaching that of leading models, such as O3 and Gemini 2.5 Pro. | N13: 84.7M | O13: 10 months ago | P13: Tags | Q13: 35 | R13: tools | S13: 1.5b | T13: 7b | U13: 8b
A14: https://ollama.com/library/gemma3 | B14: gemma3 | F14: https://llm-stats.com/models/gemma-3-1b-it | G14: =VLOOKUP(B14,'LLM Stats list of Model'!C$2:I1001,7,FALSE) -> #N/A | H14: =VLOOKUP(B14,'LLM Stats list of Model'!C$2:I1001,2,FALSE) -> #N/A | I14: =VLOOKUP(F14,'LLM Stats list of Model'!B$2:I1001,8,FALSE) -> 45717 | J14: =VLOOKUP(F14,'LLM Stats list of Model'!B$2:I1001,3,FALSE) -> google | K14: =IF(ISNA(G14),I14,G14) -> 45717 | L14: =IF(ISNA(H14),J14,H14) -> google | M14: The current, most capable model that runs on a single GPU. | N14: 36.4M | O14: 5 months ago | P14: Tags | Q14: 29 | R14: vision | S14: 270m | T14: 1b | U14: 4b
A15: https://ollama.com/library/qwen3 | B15: qwen3 | F15: https://llm-stats.com/models/qwen3-32b | G15: =VLOOKUP(B15,'LLM Stats list of Model'!C$2:I1001,7,FALSE) -> #N/A | H15: =VLOOKUP(B15,'LLM Stats list of Model'!C$2:I1001,2,FALSE) -> #N/A | I15: =VLOOKUP(F15,'LLM Stats list of Model'!B$2:I1001,8,FALSE) -> 45748 | J15: =VLOOKUP(F15,'LLM Stats list of Model'!B$2:I1001,3,FALSE) -> qwen | K15: =IF(ISNA(G15),I15,G15) -> 45748 | L15: =IF(ISNA(H15),J15,H15) -> qwen | M15: Qwen3 is the latest generation of large language models in Qwen series, offering a comprehensive suite of dense and mixture-of-experts (MoE) models. | N15: 28.3M | O15: 6 months ago | P15: Tags | Q15: 58 | R15: tools | S15: 0.6b | T15: 1.7b | U15: 4b
A16: https://ollama.com/library/mistral-small3.2 | B16: mistral-small3.2 | F16: https://llm-stats.com/models/mistral-small-3.2-24b-instruct-2506 | G16: =VLOOKUP(B16,'LLM Stats list of Model'!C$2:I1001,7,FALSE) -> #N/A | H16: =VLOOKUP(B16,'LLM Stats list of Model'!C$2:I1001,2,FALSE) -> #N/A | I16: =VLOOKUP(F16,'LLM Stats list of Model'!B$2:I1001,8,FALSE) -> 45809 | J16: =VLOOKUP(F16,'LLM Stats list of Model'!B$2:I1001,3,FALSE) -> mistral | K16: =IF(ISNA(G16),I16,G16) -> 45809 | L16: =IF(ISNA(H16),J16,H16) -> mistral | M16: An update to Mistral Small that improves on function calling, instruction following, and less repetition errors. | N16: 1.9M | O16: 10 months ago | P16: Tags | Q16: 5 | R16: vision | S16: 24b
A17: https://ollama.com/library/gemma3n | B17: gemma3n | F17: https://llm-stats.com/models/gemma-3n-e2b | G17: =VLOOKUP(B17,'LLM Stats list of Model'!C$2:I1001,7,FALSE) -> #N/A | H17: =VLOOKUP(B17,'LLM Stats list of Model'!C$2:I1001,2,FALSE) -> #N/A | I17: =VLOOKUP(F17,'LLM Stats list of Model'!B$2:I1001,8,FALSE) -> 45809 | J17: =VLOOKUP(F17,'LLM Stats list of Model'!B$2:I1001,3,FALSE) -> google | K17: =IF(ISNA(G17),I17,G17) -> 45809 | L17: =IF(ISNA(H17),J17,H17) -> google | M17: Gemma 3n models are designed for efficient execution on everyday devices such as laptops, tablets or phones. | N17: 1.6M | O17: 10 months ago | P17: Tags | Q17: 9 | S17: e2b | T17: e4b
A18: https://ollama.com/library/magistral | B18: magistral | F18: https://llm-stats.com/models/magistral-small-2506 | G18: =VLOOKUP(B18,'LLM Stats list of Model'!C$2:I1001,7,FALSE) -> #N/A | H18: =VLOOKUP(B18,'LLM Stats list of Model'!C$2:I1001,2,FALSE) -> #N/A | I18: =VLOOKUP(F18,'LLM Stats list of Model'!B$2:I1001,8,FALSE) -> 45809 | J18: =VLOOKUP(F18,'LLM Stats list of Model'!B$2:I1001,3,FALSE) -> mistral | K18: =IF(ISNA(G18),I18,G18) -> 45809 | L18: =IF(ISNA(H18),J18,H18) -> mistral | M18: Magistral is a small, efficient reasoning model with 24B parameters. | N18: 1.4M | O18: 10 months ago | P18: Tags | Q18: 5 | R18: tools | S18: 24b
A19: https://ollama.com/library/devstral-small-2 | B19: devstral-small-2 | F19: https://llm-stats.com/models/devstral-small-2507 | G19: =VLOOKUP(B19,'LLM Stats list of Model'!C$2:I1001,7,FALSE) -> #N/A | H19: =VLOOKUP(B19,'LLM Stats list of Model'!C$2:I1001,2,FALSE) -> #N/A | I19: =VLOOKUP(F19,'LLM Stats list of Model'!B$2:I1001,8,FALSE) -> 45839 | J19: =VLOOKUP(F19,'LLM Stats list of Model'!B$2:I1001,3,FALSE) -> mistral | K19: =IF(ISNA(G19),I19,G19) -> 45839 | L19: =IF(ISNA(H19),J19,H19) -> mistral | M19: 24B model that excels at using tools to explore codebases, editing multiple files and power software engineering agents. | N19: 816.4K | O19: 4 months ago | P19: Tags | Q19: 6 | R19: vision | S19: 24b
A20: https://ollama.com/library/devstral-2 | B20: devstral-2 | F20: https://llm-stats.com/models/devstral-small-2507 | G20: =VLOOKUP(B20,'LLM Stats list of Model'!C$2:I1001,7,FALSE) -> #N/A | H20: =VLOOKUP(B20,'LLM Stats list of Model'!C$2:I1001,2,FALSE) -> #N/A | I20: =VLOOKUP(F20,'LLM Stats list of Model'!B$2:I1001,8,FALSE) -> 45839 | J20: =VLOOKUP(F20,'LLM Stats list of Model'!B$2:I1001,3,FALSE) -> mistral | K20: =IF(ISNA(G20),I20,G20) -> 45839 | L20: =IF(ISNA(H20),J20,H20) -> mistral | M20: 123B model that excels at using tools to explore codebases, editing multiple files and power software engineering agents. | N20: 210.4K | O20: 4 months ago | P20: Tags | Q20: 6 | R20: tools | S20: 123b
A21: https://ollama.com/library/devstral | B21: devstral | F21: https://llm-stats.com/models/devstral-small-2507 | G21: =VLOOKUP(B21,'LLM Stats list of Model'!C$2:I1001,7,FALSE) -> #N/A | H21: =VLOOKUP(B21,'LLM Stats list of Model'!C$2:I1001,2,FALSE) -> #N/A | I21: =VLOOKUP(F21,'LLM Stats list of Model'!B$2:I1001,8,FALSE) -> 45839 | J21: =VLOOKUP(F21,'LLM Stats list of Model'!B$2:I1001,3,FALSE) -> mistral | K21: =IF(ISNA(G21),I21,G21) -> 45839 | L21: =IF(ISNA(H21),J21,H21) -> mistral | M21: Devstral: the best open source model for coding agents | N21: 934.9K | O21: 10 months ago | P21: Tags | Q21: 5 | R21: tools | S21: 24b
A22: https://ollama.com/library/kimi-k2 | B22: kimi-k2 | D22: MoonshotAI | F22: https://llm-stats.com/models/kimi-k2-base | G22: =VLOOKUP(B22,'LLM Stats list of Model'!C$2:I1001,7,FALSE) -> #N/A | H22: =VLOOKUP(B22,'LLM Stats list of Model'!C$2:I1001,2,FALSE) -> #N/A | I22: =VLOOKUP(F22,'LLM Stats list of Model'!B$2:I1001,8,FALSE) -> 45839 | J22: =VLOOKUP(F22,'LLM Stats list of Model'!B$2:I1001,3,FALSE) -> moonshotai | K22: =IF(ISNA(G22),I22,G22) -> 45839 | L22: =IF(ISNA(H22),J22,H22) -> moonshotai | M22: A state-of-the-art mixture-of-experts (MoE) language model. Kimi K2-Instruct-0905 demonstrates significant improvements in performance on public benchmarks and real-world coding agent tasks. | N22: 63.9K | O22: 7 months ago | P22: Tag | Q22: 1 | R22: tools
A23: https://ollama.com/library/gpt-oss | B23: gpt-oss | F23: https://llm-stats.com/models/gpt-oss-20b | G23: =VLOOKUP(B23,'LLM Stats list of Model'!C$2:I1001,7,FALSE) -> #N/A | H23: =VLOOKUP(B23,'LLM Stats list of Model'!C$2:I1001,2,FALSE) -> #N/A | I23: =VLOOKUP(F23,'LLM Stats list of Model'!B$2:I1001,8,FALSE) -> 45870 | J23: =VLOOKUP(F23,'LLM Stats list of Model'!B$2:I1001,3,FALSE) -> openai | K23: =IF(ISNA(G23),I23,G23) -> 45870 | L23: =IF(ISNA(H23),J23,H23) -> openai | M23: OpenAI’s open-weight models designed for powerful reasoning, agentic tasks, and versatile developer use cases. | N23: 9.4M | O23: 6 months ago | P23: Tags | Q23: 5 | R23: tools | S23: 20b | T23: 120b
A24: https://ollama.com/library/mistral-large-3 | B24: mistral-large-3 | F24: https://llm-stats.com/models/mistral-large-3-2509 | G24: =VLOOKUP(B24,'LLM Stats list of Model'!C$2:I1001,7,FALSE) -> #N/A | H24: =VLOOKUP(B24,'LLM Stats list of Model'!C$2:I1001,2,FALSE) -> #N/A | I24: =VLOOKUP(F24,'LLM Stats list of Model'!B$2:I1001,8,FALSE) -> 45901 | J24: =VLOOKUP(F24,'LLM Stats list of Model'!B$2:I1001,3,FALSE) -> mistral | K24: =IF(ISNA(G24),I24,G24) -> 45901 | L24: =IF(ISNA(H24),J24,H24) -> mistral | M24: A general-purpose multimodal mixture-of-experts model for production-grade tasks and enterprise workloads. | N24: 47.5K | O24: 5 months ago | P24: Tag | Q24: 1 | R24: vision
A25: https://ollama.com/library/qwen3-vl | B25: qwen3-vl | F25: https://llm-stats.com/models/qwen3-vl-4b-instruct | G25: =VLOOKUP(B25,'LLM Stats list of Model'!C$2:I1001,7,FALSE) -> #N/A | H25: =VLOOKUP(B25,'LLM Stats list of Model'!C$2:I1001,2,FALSE) -> #N/A | I25: =VLOOKUP(F25,'LLM Stats list of Model'!B$2:I1001,8,FALSE) -> 45901 | J25: =VLOOKUP(F25,'LLM Stats list of Model'!B$2:I1001,3,FALSE) -> qwen | K25: =IF(ISNA(G25),I25,G25) -> 45901 | L25: =IF(ISNA(H25),J25,H25) -> qwen | M25: The most powerful vision-language model in the Qwen model family to date. | N25: 3.6M | O25: 6 months ago | P25: Tags | Q25: 59 | R25: vision | S25: 2b | T25: 4b | U25: 8b
A26: https://ollama.com/library/glm-4.6 | B26: glm-4.6 | F26: https://llm-stats.com/models/glm-4.6 | G26: =VLOOKUP(B26,'LLM Stats list of Model'!C$2:I1001,7,FALSE) -> 45901 | H26: =VLOOKUP(B26,'LLM Stats list of Model'!C$2:I1001,2,FALSE) -> zai-org | I26: =VLOOKUP(F26,'LLM Stats list of Model'!B$2:I1001,8,FALSE) -> 45901 | J26: =VLOOKUP(F26,'LLM Stats list of Model'!B$2:I1001,3,FALSE) -> zai-org | K26: =IF(ISNA(G26),I26,G26) -> 45901 | L26: =IF(ISNA(H26),J26,H26) -> zai-org | M26: Advanced agentic, reasoning and coding capabilities. | N26: 220.6K | O26: 6 months ago | P26: Tag | Q26: 1 | R26: tools
A27: https://ollama.com/library/kimi-k2-thinking | B27: kimi-k2-thinking | D27: MoonshotAI | F27: https://llm-stats.com/models/kimi-k2-thinking-0905 | G27: =VLOOKUP(B27,'LLM Stats list of Model'!C$2:I1001,7,FALSE) -> #N/A | H27: =VLOOKUP(B27,'LLM Stats list of Model'!C$2:I1001,2,FALSE) -> #N/A | I27: =VLOOKUP(F27,'LLM Stats list of Model'!B$2:I1001,8,FALSE) -> 45901 | J27: =VLOOKUP(F27,'LLM Stats list of Model'!B$2:I1001,3,FALSE) -> moonshotai | K27: =IF(ISNA(G27),I27,G27) -> 45901 | L27: =IF(ISNA(H27),J27,H27) -> moonshotai | M27: Kimi K2 Thinking, Moonshot AI's best open-source thinking model. | N27: 170.8K | O27: 6 months ago | P27: Tag | Q27: 1 | R27: tools
A28: https://ollama.com/library/nemotron3 | B28: nemotron3 | F28: https://llm-stats.com/models/nemotron-3-nano-30b-a3b | G28: =VLOOKUP(B28,'LLM Stats list of Model'!C$2:I1001,7,FALSE) -> #N/A | H28: =VLOOKUP(B28,'LLM Stats list of Model'!C$2:I1001,2,FALSE) -> #N/A | I28: =VLOOKUP(F28,'LLM Stats list of Model'!B$2:I1001,8,FALSE) -> 45992 | J28: =VLOOKUP(F28,'LLM Stats list of Model'!B$2:I1001,3,FALSE) -> nvidia | K28: =IF(ISNA(G28),I28,G28) -> 45992 | L28: =IF(ISNA(H28),J28,H28) -> nvidia | M28: NVIDIA Nemotron 3 Nano Omni is a multimodal large language model that unifies video, audio, image, and text understanding to support enterprise-grade Q&A, summarization, transcription, and document intelligence workflows. | N28: 509.7K | O28: 1 week ago | P28: Tags | Q28: 4 | R28: vision | S28: 33b
A29: https://ollama.com/library/ministral-3 | B29: ministral-3 | F29: https://llm-stats.com/models/ministral-3-3b-base-2512 | G29: =VLOOKUP(B29,'LLM Stats list of Model'!C$2:I1001,7,FALSE) -> #N/A | H29: =VLOOKUP(B29,'LLM Stats list of Model'!C$2:I1001,2,FALSE) -> #N/A | I29: =VLOOKUP(F29,'LLM Stats list of Model'!B$2:I1001,8,FALSE) -> 45992 | J29: =VLOOKUP(F29,'LLM Stats list of Model'!B$2:I1001,3,FALSE) -> mistral | K29: =IF(ISNA(G29),I29,G29) -> 45992 | L29: =IF(ISNA(H29),J29,H29) -> mistral | M29: The Ministral 3 family is designed for edge deployment, capable of running on a wide range of hardware. | N29: 1.1M | O29: 4 months ago | P29: Tags | Q29: 16 | R29: vision | S29: 3b | T29: 8b | U29: 14b
A30: https://ollama.com/library/nemotron-3-nano | B30: nemotron-3-nano | F30: https://llm-stats.com/models/nemotron-3-nano-30b-a3b | G30: =VLOOKUP(B30,'LLM Stats list of Model'!C$2:I1001,7,FALSE) -> #N/A | H30: =VLOOKUP(B30,'LLM Stats list of Model'!C$2:I1001,2,FALSE) -> #N/A | I30: =VLOOKUP(F30,'LLM Stats list of Model'!B$2:I1001,8,FALSE) -> 45992 | J30: =VLOOKUP(F30,'LLM Stats list of Model'!B$2:I1001,3,FALSE) -> nvidia | K30: =IF(ISNA(G30),I30,G30) -> 45992 | L30: =IF(ISNA(H30),J30,H30) -> nvidia | M30: Nemotron-3-Nano is a new Standard for Efficient, Open, and Intelligent Agentic Models, now updated with a 4B parameter count model. | N30: 424.3K | O30: 1 month ago | P30: Tags | Q30: 9 | R30: tools | S30: 4b | T30: 30b
A31: https://ollama.com/library/gemini-3-flash-preview | B31: gemini-3-flash-preview | G31: =VLOOKUP(B31,'LLM Stats list of Model'!C$2:I1001,7,FALSE) -> 45992 | H31: =VLOOKUP(B31,'LLM Stats list of Model'!C$2:I1001,2,FALSE) -> google | I31: =VLOOKUP(F31,'LLM Stats list of Model'!B$2:I1001,8,FALSE) -> #N/A | J31: =VLOOKUP(F31,'LLM Stats list of Model'!B$2:I1001,3,FALSE) -> #N/A | K31: =IF(ISNA(G31),I31,G31) -> 45992 | L31: =IF(ISNA(H31),J31,H31) -> google | M31: Gemini 3 Flash offers frontier intelligence built for speed at a fraction of the cost. | N31: 259.6K | O31: 4 months ago | P31: Tags | Q31: 2 | R31: vision
A32: https://ollama.com/library/glm-4.7 | B32: glm-4.7 | G32: =VLOOKUP(B32,'LLM Stats list of Model'!C$2:I1001,7,FALSE) -> 45992 | H32: =VLOOKUP(B32,'LLM Stats list of Model'!C$2:I1001,2,FALSE) -> zai-org | I32: =VLOOKUP(F32,'LLM Stats list of Model'!B$2:I1001,8,FALSE) -> #N/A | J32: =VLOOKUP(F32,'LLM Stats list of Model'!B$2:I1001,3,FALSE) -> #N/A | K32: =IF(ISNA(G32),I32,G32) -> 45992 | L32: =IF(ISNA(H32),J32,H32) -> zai-org | M32: Advancing the Coding Capability | N32: 208.3K | O32: 4 months ago | P32: Tag | Q32: 1 | R32: tools
A33: https://ollama.com/library/deepseek-v3.2 | B33: deepseek-v3.2 | C33: Skipped | F33: https://llm-stats.com/models/deepseek-v3.1 | G33: =VLOOKUP(B33,'LLM Stats list of Model'!C$2:I1001,7,FALSE) -> 45992 | H33: =VLOOKUP(B33,'LLM Stats list of Model'!C$2:I1001,2,FALSE) -> deepseek | I33: =VLOOKUP(F33,'LLM Stats list of Model'!B$2:I1001,8,FALSE) -> 45658 | J33: =VLOOKUP(F33,'LLM Stats list of Model'!B$2:I1001,3,FALSE) -> deepseek | K33: =IF(ISNA(G33),I33,G33) -> 45992 | L33: =IF(ISNA(H33),J33,H33) -> deepseek | M33: DeepSeek-V3.2, a model that harmonizes high computational efficiency with superior reasoning and agent performance. | N33: 202.2K | O33: 4 months ago | P33: Tag | Q33: 1 | R33: tools
A34: https://ollama.com/library/glm-4.7-flash | B34: glm-4.7-flash | C34: Too big | F34: https://llm-stats.com/models/glm-4.7-flash | G34: =VLOOKUP(B34,'LLM Stats list of Model'!C$2:I1001,7,FALSE) -> 46023 | H34: =VLOOKUP(B34,'LLM Stats list of Model'!C$2:I1001,2,FALSE) -> zai-org | I34: =VLOOKUP(F34,'LLM Stats list of Model'!B$2:I1001,8,FALSE) -> 46023 | J34: =VLOOKUP(F34,'LLM Stats list of Model'!B$2:I1001,3,FALSE) -> zai-org | K34: =IF(ISNA(G34),I34,G34) -> 46023 | L34: =IF(ISNA(H34),J34,H34) -> zai-org | M34: As the strongest model in the 30B class, GLM-4.7-Flash offers a new option for lightweight deployment that balances performance and efficiency. | N34: 1.2M | O34: 3 months ago | P34: Tags | Q34: 4 | R34: tools
A35: https://ollama.com/library/kimi-k2.5 | B35: kimi-k2.5 | D35: MoonshotAI | F35: https://llm-stats.com/models/kimi-k2.5 | G35: =VLOOKUP(B35,'LLM Stats list of Model'!C$2:I1001,7,FALSE) -> 46023 | H35: =VLOOKUP(B35,'LLM Stats list of Model'!C$2:I1001,2,FALSE) -> moonshotai | I35: =VLOOKUP(F35,'LLM Stats list of Model'!B$2:I1001,8,FALSE) -> 46023 | J35: =VLOOKUP(F35,'LLM Stats list of Model'!B$2:I1001,3,FALSE) -> moonshotai | K35: =IF(ISNA(G35),I35,G35) -> 46023 | L35: =IF(ISNA(H35),J35,H35) -> moonshotai | M35: Kimi K2.5 is an open-source, native multimodal agentic model that seamlessly integrates vision and language understanding with advanced agentic capabilities, instant and thinking modes, as well as conversational and agentic paradigms. | N35: 271.5K | O35: 3 months ago | P35: Tag | Q35: 1 | R35: vision
A36: https://ollama.com/library/glm-5 | B36: glm-5 | F36: https://llm-stats.com/models/glm-5 | G36: =VLOOKUP(B36,'LLM Stats list of Model'!C$2:I1001,7,FALSE) -> 46054 | H36: =VLOOKUP(B36,'LLM Stats list of Model'!C$2:I1001,2,FALSE) -> zai-org | I36: =VLOOKUP(F36,'LLM Stats list of Model'!B$2:I1001,8,FALSE) -> 46054 | J36: =VLOOKUP(F36,'LLM Stats list of Model'!B$2:I1001,3,FALSE) -> zai-org | K36: =IF(ISNA(G36),I36,G36) -> 46054 | L36: =IF(ISNA(H36),J36,H36) -> zai-org | M36: A strong reasoning and agentic model from Z.ai with 744B total parameters (40B active), built for complex systems engineering and long-horizon tasks. | N36: 311.6K | O36: 2 months ago | P36: Tag | Q36: 1 | R36: tools
A37: https://ollama.com/library/qwen3.6 | B37: qwen3.6 | C37: Too big | F37: https://llm-stats.com/models/qwen3.6-27b | G37: =VLOOKUP(B37,'LLM Stats list of Model'!C$2:I1001,7,FALSE) -> #N/A | H37: =VLOOKUP(B37,'LLM Stats list of Model'!C$2:I1001,2,FALSE) -> #N/A | I37: =VLOOKUP(F37,'LLM Stats list of Model'!B$2:I1001,8,FALSE) -> 46113 | J37: =VLOOKUP(F37,'LLM Stats list of Model'!B$2:I1001,3,FALSE) -> qwen | K37: =IF(ISNA(G37),I37,G37) -> 46113 | L37: =IF(ISNA(H37),J37,H37) -> qwen | M37: Qwen3.6 delivers substantial upgrades in agentic coding and thinking preservation than previous Qwen models. | N37: 866.1K | O37: 1 week ago | P37: Tags | Q37: 22 | R37: vision | S37: 27b | T37: 35b
A38: https://ollama.com/library/kimi-k2.6 | B38: kimi-k2.6 | D38: MoonshotAI | F38: https://llm-stats.com/models/kimi-k2.6 | G38: =VLOOKUP(B38,'LLM Stats list of Model'!C$2:I1001,7,FALSE) -> 46113 | H38: =VLOOKUP(B38,'LLM Stats list of Model'!C$2:I1001,2,FALSE) -> moonshotai | I38: =VLOOKUP(F38,'LLM Stats list of Model'!B$2:I1001,8,FALSE) -> 46113 | J38: =VLOOKUP(F38,'LLM Stats list of Model'!B$2:I1001,3,FALSE) -> moonshotai | K38: =IF(ISNA(G38),I38,G38) -> 46113 | L38: =IF(ISNA(H38),J38,H38) -> moonshotai | M38: Kimi K2.6 is an open-source, native multimodal agentic model that advances practical capabilities in long-horizon coding, coding-driven design, proactive autonomous execution, and swarm-based task orchestration. | N38: 196.9K | O38: 2 weeks ago | P38: Tag | Q38: 1 | R38: vision
A39: https://ollama.com/library/glm-5.1 | B39: glm-5.1 | G39: =VLOOKUP(B39,'LLM Stats list of Model'!C$2:I1001,7,FALSE) -> 46113 | H39: =VLOOKUP(B39,'LLM Stats list of Model'!C$2:I1001,2,FALSE) -> zai-org | I39: =VLOOKUP(F39,'LLM Stats list of Model'!B$2:I1001,8,FALSE) -> #N/A | J39: =VLOOKUP(F39,'LLM Stats list of Model'!B$2:I1001,3,FALSE) -> #N/A | K39: =IF(ISNA(G39),I39,G39) -> 46113 | L39: =IF(ISNA(H39),J39,H39) -> zai-org | M39: GLM-5.1 is our next-generation flagship model for agentic engineering, with significantly stronger coding capabilities than its predecessor. It achieves state-of-the-art performance on SWE-Bench Pro and leads GLM-5 by a wide margin. | N39: 243K | O39: 4 weeks ago | P39: Tag | Q39: 1 | R39: tools
A40: https://ollama.com/library/deepseek-v4-flash | B40: deepseek-v4-flash | F40: https://llm-stats.com/models/deepseek-v4-flash-max | G40: =VLOOKUP(B40,'LLM Stats list of Model'!C$2:I1001,7,FALSE) -> #N/A | H40: =VLOOKUP(B40,'LLM Stats list of Model'!C$2:I1001,2,FALSE) -> #N/A | I40: =VLOOKUP(F40,'LLM Stats list of Model'!B$2:I1001,8,FALSE) -> 46113 | J40: =VLOOKUP(F40,'LLM Stats list of Model'!B$2:I1001,3,FALSE) -> deepseek | K40: =IF(ISNA(G40),I40,G40) -> 46113 | L40: =IF(ISNA(H40),J40,H40) -> deepseek | M40: DeepSeek-V4-Flash is a preview of the DeepSeek-V4 series, a Mixture-of-Experts model with 284B total parameters and 13B activated, built for efficient reasoning across a 1M-token context window. | N40: 46.4K | O40: 1 week ago | P40: Tag | Q40: 1 | R40: tools
A41: https://ollama.com/library/deepseek-v4-pro | B41: deepseek-v4-pro | F41: https://llm-stats.com/models/deepseek-v4-pro-max | G41: =VLOOKUP(B41,'LLM Stats list of Model'!C$2:I1001,7,FALSE) -> #N/A | H41: =VLOOKUP(B41,'LLM Stats list of Model'!C$2:I1001,2,FALSE) -> #N/A | I41: =VLOOKUP(F41,'LLM Stats list of Model'!B$2:I1001,8,FALSE) -> 46113 | J41: =VLOOKUP(F41,'LLM Stats list of Model'!B$2:I1001,3,FALSE) -> deepseek | K41: =IF(ISNA(G41),I41,G41) -> 46113 | L41: =IF(ISNA(H41),J41,H41) -> deepseek | M41: DeepSeek-V4-Pro is a frontier Mixture-of-Experts model with a 1M-token context window and three reasoning modes. | N41: 37.3K | O41: 1 week ago | P41: Tag | Q41: 1 | R41: tools
A42: https://ollama.com/library/gemma4 | B42: gemma4 | F42: https://llm-stats.com/models/gemma-4-e2b-it | G42: =VLOOKUP(B42,'LLM Stats list of Model'!C$2:I1001,7,FALSE) -> #N/A | H42: =VLOOKUP(B42,'LLM Stats list of Model'!C$2:I1001,2,FALSE) -> #N/A | I42: =VLOOKUP(F42,'LLM Stats list of Model'!B$2:I1001,8,FALSE) -> 46113 | J42: =VLOOKUP(F42,'LLM Stats list of Model'!B$2:I1001,3,FALSE) -> google | K42: =IF(ISNA(G42),I42,G42) -> 46113 | L42: =IF(ISNA(H42),J42,H42) -> google | M42: Gemma 4 models are designed to deliver frontier-level performance at each size. They are well-suited for reasoning, agentic workflows, coding, and multimodal understanding. | N42: 7M | O42: 14 hours ago | P42: Tags | Q42: 30 | R42: vision | S42: e2b | T42: e4b | U42: 26b
A43: https://ollama.com/library/granite4.1 | B43: granite4.1 | D43: Granite Team, IBM | G43: =VLOOKUP(B43,'LLM Stats list of Model'!C$2:I1001,7,FALSE) -> #N/A | H43: =VLOOKUP(B43,'LLM Stats list of Model'!C$2:I1001,2,FALSE) -> #N/A | I43: =VLOOKUP(F43,'LLM Stats list of Model'!B$2:I1001,8,FALSE) -> #N/A | J43: =VLOOKUP(F43,'LLM Stats list of Model'!B$2:I1001,3,FALSE) -> #N/A | K43: =IF(ISNA(G43),I43,G43) -> #N/A | L43: =IF(ISNA(H43),J43,H43) -> #N/A | N43: 36.7K | O43: 6 days ago | P43: Tags | Q43: 46 | R43: tools | S43: 3b | T43: 8b | U43: 30b
A44: https://ollama.com/library/mistral-medium-3.5 | B44: mistral-medium-3.5 | D44: Mistral | G44: =VLOOKUP(B44,'LLM Stats list of Model'!C$2:I1001,7,FALSE) -> #N/A | H44: =VLOOKUP(B44,'LLM Stats list of Model'!C$2:I1001,2,FALSE) -> #N/A | I44: =VLOOKUP(F44,'LLM Stats list of Model'!B$2:I1001,8,FALSE) -> #N/A | J44: =VLOOKUP(F44,'LLM Stats list of Model'!B$2:I1001,3,FALSE) -> #N/A | K44: =IF(ISNA(G44),I44,G44) -> #N/A | L44: =IF(ISNA(H44),J44,H44) -> #N/A | M44: Mistral Medium 3.5 is the first flagship model of Mistral AI that merged instruction-following, reasoning, and coding in a single set of 128B weights. | N44: 11.4K | O44: 8 hours ago | P44: Tags | Q44: 5 | R44: vision | S44: 128b
A45: https://ollama.com/library/medgemma | B45: medgemma | D45: Google Health | G45: =VLOOKUP(B45,'LLM Stats list of Model'!C$2:I1001,7,FALSE) -> #N/A | H45: =VLOOKUP(B45,'LLM Stats list of Model'!C$2:I1001,2,FALSE) -> #N/A | I45: =VLOOKUP(F45,'LLM Stats list of Model'!B$2:I1001,8,FALSE) -> #N/A | J45: =VLOOKUP(F45,'LLM Stats list of Model'!B$2:I1001,3,FALSE) -> #N/A | K45: =IF(ISNA(G45),I45,G45) -> #N/A | L45: =IF(ISNA(H45),J45,H45) -> #N/A | M45: MedGemma is a collection of Gemma 3 variants that are trained for performance on medical text and image comprehension. | N45: 20.9K | O45: 2 weeks ago | P45: Tags | Q45: 9 | R45: vision | S45: 4b | T45: 27b
A46: https://ollama.com/library/medgemma1.5 | B46: medgemma1.5 | D46: Google Health | G46: =VLOOKUP(B46,'LLM Stats list of Model'!C$2:I1001,7,FALSE) -> #N/A | H46: =VLOOKUP(B46,'LLM Stats list of Model'!C$2:I1001,2,FALSE) -> #N/A | I46: =VLOOKUP(F46,'LLM Stats list of Model'!B$2:I1001,8,FALSE) -> #N/A | J46: =VLOOKUP(F46,'LLM Stats list of Model'!B$2:I1001,3,FALSE) -> #N/A | K46: =IF(ISNA(G46),I46,G46) -> #N/A | L46: =IF(ISNA(H46),J46,H46) -> #N/A | M46: MedGemma 1.5 4B is an updated version of the MedGemma 4B model. | N46: 12.4K | O46: 2 weeks ago | P46: Tags | Q46: 5 | R46: vision | S46: 4b
A47: https://ollama.com/library/laguna-xs.2 | B47: laguna-xs.2 | D47: Poolside | G47: =VLOOKUP(B47,'LLM Stats list of Model'!C$2:I1001,7,FALSE) -> #N/A | H47: =VLOOKUP(B47,'LLM Stats list of Model'!C$2:I1001,2,FALSE) -> #N/A | I47: =VLOOKUP(F47,'LLM Stats list of Model'!B$2:I1001,8,FALSE) -> #N/A | J47: =VLOOKUP(F47,'LLM Stats list of Model'!B$2:I1001,3,FALSE) -> #N/A | K47: =IF(ISNA(G47),I47,G47) -> #N/A | L47: =IF(ISNA(H47),J47,H47) -> #N/A | M47: Laguna XS.2 is a 33B total parameter Mixture-of-Experts model with 3B activated parameters per token designed for agentic coding and long-horizon work on a local machine. | N47: 6107 | O47: 1 week ago | P47: Tags | Q47: 7 | R47: tools
A48: https://ollama.com/library/qwen3.5 | B48: qwen3.5 | C48: Skipped for Old Model | G48: =VLOOKUP(B48,'LLM Stats list of Model'!C$2:I1001,7,FALSE) -> #N/A | H48: =VLOOKUP(B48,'LLM Stats list of Model'!C$2:I1001,2,FALSE) -> #N/A | I48: =VLOOKUP(F48,'LLM Stats list of Model'!B$2:I1001,8,FALSE) -> #N/A | J48: =VLOOKUP(F48,'LLM Stats list of Model'!B$2:I1001,3,FALSE) -> #N/A | K48: =IF(ISNA(G48),I48,G48) -> #N/A | L48: =IF(ISNA(H48),J48,H48) -> #N/A | M48: Qwen 3.5 is a family of open-source multimodal models that delivers exceptional utility and performance. | N48: 8.6M | O48: 1 month ago | P48: Tags | Q48: 58 | R48: vision | S48: 0.8b | T48: 2b | U48: 4b
A49: https://ollama.com/library/lfm2 | B49: lfm2 | D49: Liquid | G49: =VLOOKUP(B49,'LLM Stats list of Model'!C$2:I1001,7,FALSE) -> #N/A | H49: =VLOOKUP(B49,'LLM Stats list of Model'!C$2:I1001,2,FALSE) -> #N/A | I49: =VLOOKUP(F49,'LLM Stats list of Model'!B$2:I1001,8,FALSE) -> #N/A | J49: =VLOOKUP(F49,'LLM Stats list of Model'!B$2:I1001,3,FALSE) -> #N/A | K49: =IF(ISNA(G49),I49,G49) -> #N/A | L49: =IF(ISNA(H49),J49,H49) -> #N/A | M49: LFM2 is a family of hybrid models designed for on-device deployment. LFM2-24B-A2B is the largest model in the family, scaling the architecture to 24 billion parameters while keeping inference efficient. | N49: 1.1M | O49: 2 months ago | P49: Tags | Q49: 6 | R49: tools | S49: 24b
A50: https://ollama.com/library/qwen3-coder-next | B50: qwen3-coder-next | D50: Qwen | G50: =VLOOKUP(B50,'LLM Stats list of Model'!C$2:I1001,7,FALSE) -> #N/A | H50: =VLOOKUP(B50,'LLM Stats list of Model'!C$2:I1001,2,FALSE) -> #N/A | I50: =VLOOKUP(F50,'LLM Stats list of Model'!B$2:I1001,8,FALSE) -> #N/A | J50: =VLOOKUP(F50,'LLM Stats list of Model'!B$2:I1001,3,FALSE) -> #N/A | K50: =IF(ISNA(G50),I50,G50) -> #N/A | L50: =IF(ISNA(H50),J50,H50) -> #N/A | M50: Qwen3-Coder-Next is a coding-focused language model from Alibaba's Qwen team, optimized for agentic coding workflows and local development. | N50: 1.2M | O50: 2 months ago | P50: Tags | Q50: 4 | R50: tools
A51: https://ollama.com/library/translategemma | B51: translategemma | D51: Google | F51: https://blog.google/innovation-and-ai/technology/developers-tools/translategemma/ | G51: =VLOOKUP(B51,'LLM Stats list of Model'!C$2:I1001,7,FALSE) -> #N/A | H51: =VLOOKUP(B51,'LLM Stats list of Model'!C$2:I1001,2,FALSE) -> #N/A | I51: =VLOOKUP(#REF!,'LLM Stats list of Model'!B$2:I1001,8,FALSE) -> #REF! | J51: =VLOOKUP(#REF!,'LLM Stats list of Model'!B$2:I1001,3,FALSE) -> #REF! | K51: =IF(ISNA(G51),I51,G51) -> #REF! | L51: =IF(ISNA(H51),J51,H51) -> #REF! | M51: A new collection of open translation models built on Gemma 3, helping people communicate across 55 languages. | N51: 1.3M | O51: 3 months ago | P51: Tags | Q51: 13 | R51: vision | S51: 4b | T51: 12b | U51: 27b
A52: https://ollama.com/library/lfm2.5-thinking | B52: lfm2.5-thinking | D52: Liquid | E52: https://artificialanalysis.ai/models/comparisons/lfm2-5-1-2b-thinking-vs-lfm2-5-1-2b-thinking | G52: =VLOOKUP(B52,'LLM Stats list of Model'!C$2:I1001,7,FALSE) -> #N/A | H52: =VLOOKUP(B52,'LLM Stats list of Model'!C$2:I1001,2,FALSE) -> #N/A | I52: =VLOOKUP(F52,'LLM Stats list of Model'!B$2:I1001,8,FALSE) -> #N/A | J52: =VLOOKUP(F52,'LLM Stats list of Model'!B$2:I1001,3,FALSE) -> #N/A | K52: =IF(ISNA(G52),I52,G52) -> #N/A | L52: =IF(ISNA(H52),J52,H52) -> #N/A | M52: LFM2.5 is a new family of hybrid models designed for on-device deployment. | N52: 1.2M | O52: 3 months ago | P52: Tags | Q52: 5 | R52: tools | S52: 1.2b
A53: https://ollama.com/library/nemotron-3-super | B53: nemotron-3-super | G53: =VLOOKUP(B53,'LLM Stats list of Model'!C$2:I1001,7,FALSE) -> #N/A | H53: =VLOOKUP(B53,'LLM Stats list of Model'!C$2:I1001,2,FALSE) -> #N/A | I53: =VLOOKUP(F53,'LLM Stats list of Model'!B$2:I1001,8,FALSE) -> #N/A | J53: =VLOOKUP(F53,'LLM Stats list of Model'!B$2:I1001,3,FALSE) -> #N/A | K53: =IF(ISNA(G53),I53,G53) -> #N/A | L53: =IF(ISNA(H53),J53,H53) -> #N/A | M53: NVIDIA Nemotron 3 Super is a 120B open MoE model activating just 12B parameters to deliver maximum compute efficiency and accuracy for complex multi-agent applications. | N53: 388.6K | O53: 1 month ago | P53: Tags | Q53: 7 | R53: tools | S53: 120b
A54: https://ollama.com/library/minimax-m2.7 | B54: minimax-m2.7 | D54: Minimax | G54: =VLOOKUP(B54,'LLM Stats list of Model'!C$2:I1001,7,FALSE) -> #N/A | H54: =VLOOKUP(B54,'LLM Stats list of Model'!C$2:I1001,2,FALSE) -> #N/A | I54: =VLOOKUP(F54,'LLM Stats list of Model'!B$2:I1001,8,FALSE) -> #N/A | J54: =VLOOKUP(F54,'LLM Stats list of Model'!B$2:I1001,3,FALSE) -> #N/A | K54: =IF(ISNA(G54),I54,G54) -> #N/A | L54: =IF(ISNA(H54),J54,H54) -> #N/A | M54: MiniMax's M2-series model for coding, agentic workflows, and professional productivity. | N54: 219.5K | O54: 1 month ago | P54: Tag | Q54: 1 | R54: tools
A55: https://ollama.com/library/glm-ocr | B55: glm-ocr | G55: =VLOOKUP(B55,'LLM Stats list of Model'!C$2:I1001,7,FALSE) -> #N/A | H55: =VLOOKUP(B55,'LLM Stats list of Model'!C$2:I1001,2,FALSE) -> #N/A | I55: =VLOOKUP(F55,'LLM Stats list of Model'!B$2:I1001,8,FALSE) -> #N/A | J55: =VLOOKUP(F55,'LLM Stats list of Model'!B$2:I1001,3,FALSE) -> #N/A | K55: =IF(ISNA(G55),I55,G55) -> #N/A | L55: =IF(ISNA(H55),J55,H55) -> #N/A | M55: GLM-OCR is a multimodal OCR model for complex document understanding, built on the GLM-V encoder–decoder architecture. | N55: 424.5K | O55: 3 months ago | P55: Tags | Q55: 3 | R55: vision
A56: https://ollama.com/library/minimax-m2.5 | B56: minimax-m2.5 | D56: Minimax | G56: =VLOOKUP(B56,'LLM Stats list of Model'!C$2:I1001,7,FALSE) -> #N/A | H56: =VLOOKUP(B56,'LLM Stats list of Model'!C$2:I1001,2,FALSE) -> #N/A | I56: =VLOOKUP(F56,'LLM Stats list of Model'!B$2:I1001,8,FALSE) -> #N/A | J56: =VLOOKUP(F56,'LLM Stats list of Model'!B$2:I1001,3,FALSE) -> #N/A | K56: =IF(ISNA(G56),I56,G56) -> #N/A | L56: =IF(ISNA(H56),J56,H56) -> #N/A | M56: MiniMax-M2.5 is a state-of-the-art large language model designed for real-world productivity and coding tasks. | N56: 282.2K | O56: 2 months ago | P56: Tag | Q56: 1 | R56: tools
A57: https://ollama.com/library/qwen3-next | B57: qwen3-next | D57: Qwen | G57: =VLOOKUP(B57,'LLM Stats list of Model'!C$2:I1001,7,FALSE) -> #N/A | H57: =VLOOKUP(B57,'LLM Stats list of Model'!C$2:I1001,2,FALSE) -> #N/A | I57: =VLOOKUP(F57,'LLM Stats list of Model'!B$2:I1001,8,FALSE) -> #N/A | J57: =VLOOKUP(F57,'LLM Stats list of Model'!B$2:I1001,3,FALSE) -> #N/A | K57: =IF(ISNA(G57),I57,G57) -> #N/A | L57: =IF(ISNA(H57),J57,H57) -> #N/A | M57: The first installment in the Qwen3-Next series with strong performance in terms of both parameter efficiency and inference speed. | N57: 537.6K | O57: 4 months ago | P57: Tags | Q57: 10 | R57: tools | S57: 80b
A58: https://ollama.com/library/rnj-1 | B58: rnj-1 | D58: Essential AI | G58: =VLOOKUP(B58,'LLM Stats list of Model'!C$2:I1001,7,FALSE) -> #N/A | H58: =VLOOKUP(B58,'LLM Stats list of Model'!C$2:I1001,2,FALSE) -> #N/A | I58: =VLOOKUP(F58,'LLM Stats list of Model'!B$2:I1001,8,FALSE) -> #N/A | J58: =VLOOKUP(F58,'LLM Stats list of Model'!B$2:I1001,3,FALSE) -> #N/A | K58: =IF(ISNA(G58),I58,G58) -> #N/A | L58: =IF(ISNA(H58),J58,H58) -> #N/A | M58: Rnj-1 is a family of 8B parameter open-weight, dense models trained from scratch by Essential AI, optimized for code and STEM with capabilities on par with SOTA open-weight models. | N58: 455.5K | O58: 4 months ago | P58: Tags | Q58: 6 | R58: tools | S58: 8b
A59: https://ollama.com/library/nemotron-cascade-2 | B59: nemotron-cascade-2 | G59: =VLOOKUP(B59,'LLM Stats list of Model'!C$2:I1001,7,FALSE) -> #N/A | H59: =VLOOKUP(B59,'LLM Stats list of Model'!C$2:I1001,2,FALSE) -> #N/A | I59: =VLOOKUP(F59,'LLM Stats list of Model'!B$2:I1001,8,FALSE) -> #N/A | J59: =VLOOKUP(F59,'LLM Stats list of Model'!B$2:I1001,3,FALSE) -> #N/A | K59: =IF(ISNA(G59),I59,G59) -> #N/A | L59: =IF(ISNA(H59),J59,H59) -> #N/A | M59: An open 30B MoE model from NVIDIA with 3B activated parameters that delivers strong reasoning and agentic capabilities. | N59: 110.9K | O59: 1 month ago | P59: Tags | Q59: 3 | R59: tools | S59: 30b
A60: https://ollama.com/library/olmo-3 | B60: olmo-3 | D60: AllenAI | G60: =VLOOKUP(B60,'LLM Stats list of Model'!C$2:I1001,7,FALSE) -> #N/A | H60: =VLOOKUP(B60,'LLM Stats list of Model'!C$2:I1001,2,FALSE) -> #N/A | I60: =VLOOKUP(F60,'LLM Stats list of Model'!B$2:I1001,8,FALSE) -> #N/A | J60: =VLOOKUP(F60,'LLM Stats list of Model'!B$2:I1001,3,FALSE) -> #N/A | K60: =IF(ISNA(G60),I60,G60) -> #N/A | L60: =IF(ISNA(H60),J60,H60) -> #N/A | M60: Olmo is a series of Open language models designed to enable the science of language models. These models are pre-trained on the Dolma 3 dataset and post-trained on the Dolci datasets. | N60: 421.8K | O60: 4 months ago | P60: Tags | Q60: 15 | S60: 7b | T60: 32b
A61: https://ollama.com/library/deepseek-ocr | B61: deepseek-ocr | G61: =VLOOKUP(B61,'LLM Stats list of Model'!C$2:I1001,7,FALSE) -> #N/A | H61: =VLOOKUP(B61,'LLM Stats list of Model'!C$2:I1001,2,FALSE) -> #N/A | I61: =VLOOKUP(F61,'LLM Stats list of Model'!B$2:I1001,8,FALSE) -> #N/A | J61: =VLOOKUP(F61,'LLM Stats list of Model'!B$2:I1001,3,FALSE) -> #N/A | K61: =IF(ISNA(G61),I61,G61) -> #N/A | L61: =IF(ISNA(H61),J61,H61) -> #N/A | M61: DeepSeek-OCR is a vision-language model that can perform token-efficient OCR. | N61: 436.7K | O61: 5 months ago | P61: Tags | Q61: 3 | R61: vision | S61: 3b
A62: https://ollama.com/library/olmo-3.1 | B62: olmo-3.1 | D62: AllenAI | G62: =VLOOKUP(B62,'LLM Stats list of Model'!C$2:I1001,7,FALSE) -> #N/A | H62: =VLOOKUP(B62,'LLM Stats list of Model'!C$2:I1001,2,FALSE) -> #N/A | I62: =VLOOKUP(F62,'LLM Stats list of Model'!B$2:I1001,8,FALSE) -> #N/A | J62: =VLOOKUP(F62,'LLM Stats list of Model'!B$2:I1001,3,FALSE) -> #N/A | K62: =IF(ISNA(G62),I62,G62) -> #N/A | L62: =IF(ISNA(H62),J62,H62) -> #N/A | M62: Olmo is a series of Open language models designed to enable the science of language models. These models are pre-trained on the Dolma 3 dataset and post-trained on the Dolci datasets. | N62: 268.7K | O62: 4 months ago | P62: Tags | Q62: 10 | R62: tools | S62: 32b
A63: https://ollama.com/library/nomic-embed-text-v2-moe | B63: nomic-embed-text-v2-moe | F63: https://huggingface.co/nomic-ai/nomic-embed-text-v2-moe | G63: =VLOOKUP(B63,'LLM Stats list of Model'!C$2:I1001,7,FALSE) -> #N/A | H63: =VLOOKUP(B63,'LLM Stats list of Model'!C$2:I1001,2,FALSE) -> #N/A | I63: =VLOOKUP(F63,'LLM Stats list of Model'!B$2:I1001,8,FALSE) -> #N/A | J63: =VLOOKUP(F63,'LLM Stats list of Model'!B$2:I1001,3,FALSE) -> #N/A | K63: =IF(ISNA(G63),I63,G63) -> #N/A | L63: =IF(ISNA(H63),J63,H63) -> #N/A | M63: nomic-embed-text-v2-moe is a multilingual MoE text embedding model that excels at multilingual retrieval. | N63: 199K | O63: 4 months ago | P63: Tag | Q63: 1 | R63: embedding
A64: https://ollama.com/library/minimax-m2.1 | B64: minimax-m2.1 | D64: Minimax | G64: =VLOOKUP(B64,'LLM Stats list of Model'!C$2:I1001,7,FALSE) -> #N/A | H64: =VLOOKUP(B64,'LLM Stats list of Model'!C$2:I1001,2,FALSE) -> #N/A | I64: =VLOOKUP(F64,'LLM Stats list of Model'!B$2:I1001,8,FALSE) -> #N/A | J64: =VLOOKUP(F64,'LLM Stats list of Model'!B$2:I1001,3,FALSE) -> #N/A | K64: =IF(ISNA(G64),I64,G64) -> #N/A | L64: =IF(ISNA(H64),J64,H64) -> #N/A | M64: Exceptional multilingual capabilities to elevate code engineering | N64: 154.5K | O64: 4 months ago | P64: Tag | Q64: 1 | R64: tools
A65: https://ollama.com/library/functiongemma | B65: functiongemma | F65: https://huggingface.co/google/functiongemma-270m-it | G65: =VLOOKUP(B65,'LLM Stats list of Model'!C$2:I1001,7,FALSE) -> #N/A | H65: =VLOOKUP(B65,'LLM Stats list of Model'!C$2:I1001,2,FALSE) -> #N/A | I65: =VLOOKUP(F65,'LLM Stats list of Model'!B$2:I1001,8,FALSE) -> #N/A | J65: =VLOOKUP(F65,'LLM Stats list of Model'!B$2:I1001,3,FALSE) -> #N/A | K65: =IF(ISNA(G65),I65,G65) -> #N/A | L65: =IF(ISNA(H65),J65,H65) -> #N/A | M65: FunctionGemma is a specialized version of Google's Gemma 3 270M model fine-tuned explicitly for function calling. | N65: 154.5K | O65: 4 months ago | P65: Tags | Q65: 4 | R65: tools | S65: 270m
A66: https://ollama.com/library/cogito-2.1 | B66: cogito-2.1 | F66: https://www.deepcogito.com/research/cogito-v2-1 | G66: =VLOOKUP(B66,'LLM Stats list of Model'!C$2:I1001,7,FALSE) -> #N/A | H66: =VLOOKUP(B66,'LLM Stats list of Model'!C$2:I1001,2,FALSE) -> #N/A | I66: =VLOOKUP(F66,'LLM Stats list of Model'!B$2:I1001,8,FALSE) -> #N/A | J66: =VLOOKUP(F66,'LLM Stats list of Model'!B$2:I1001,3,FALSE) -> #N/A | K66: =IF(ISNA(G66),I66,G66) -> #N/A | L66: =IF(ISNA(H66),J66,H66) -> #N/A | M66: The Cogito v2.1 LLMs are instruction tuned generative models. All models are released under MIT license for commercial use. | N66: 179.8K | O66: 5 months ago | P66: Tags | Q66: 6 | S66: 671b
A67: https://ollama.com/library/qwen3-embedding | B67: qwen3-embedding | G67: =VLOOKUP(B67,'LLM Stats list of Model'!C$2:I1001,7,FALSE) -> #N/A | H67: =VLOOKUP(B67,'LLM Stats list of Model'!C$2:I1001,2,FALSE) -> #N/A | I67: =VLOOKUP(F67,'LLM Stats list of Model'!B$2:I1001,8,FALSE) -> #N/A | J67: =VLOOKUP(F67,'LLM Stats list of Model'!B$2:I1001,3,FALSE) -> #N/A | K67: =IF(ISNA(G67),I67,G67) -> #N/A | L67: =IF(ISNA(H67),J67,H67) -> #N/A | M67: Building upon the foundational models of the Qwen3 series, Qwen3 Embedding provides a comprehensive range of text embeddings models in various sizes | N67: 1.8M | O67: 7 months ago | P67: Tags | Q67: 12 | R67: embedding | S67: 0.6b | T67: 4b | U67: 8b
A68: https://ollama.com/library/granite4 | B68: granite4 | C68: https://huggingface.co/collections/ibm-granite/granite-40-language-models | D68: IBM | G68: =VLOOKUP(B68,'LLM Stats list of Model'!C$2:I1001,7,FALSE) -> #N/A | H68: =VLOOKUP(B68,'LLM Stats list of Model'!C$2:I1001,2,FALSE) -> #N/A | I68: =VLOOKUP(F68,'LLM Stats list of Model'!B$2:I1001,8,FALSE) -> #N/A | J68: =VLOOKUP(F68,'LLM Stats list of Model'!B$2:I1001,3,FALSE) -> #N/A | K68: =IF(ISNA(G68),I68,G68) -> #N/A | L68: =IF(ISNA(H68),J68,H68) -> #N/A | M68: Granite 4 features improved instruction following (IF) and tool-calling capabilities, making them more effective in enterprise applications. | N68: 1.2M | O68: 6 months ago | P68: Tags | Q68: 17 | R68: tools | S68: 350m | T68: 1b | U68: 3b
A69: https://ollama.com/library/embeddinggemma | B69: embeddinggemma | G69: =VLOOKUP(B69,'LLM Stats list of Model'!C$2:I1001,7,FALSE) -> #N/A | H69: =VLOOKUP(B69,'LLM Stats list of Model'!C$2:I1001,2,FALSE) -> #N/A | I69: =VLOOKUP(F69,'LLM Stats list of Model'!B$2:I1001,8,FALSE) -> #N/A | J69: =VLOOKUP(F69,'LLM Stats list of Model'!B$2:I1001,3,FALSE) -> #N/A | K69: =IF(ISNA(G69),I69,G69) -> #N/A | L69: =IF(ISNA(H69),J69,H69) -> #N/A | M69: EmbeddingGemma is a 300M parameter embedding model from Google. | N69: 1.1M | O69: 7 months ago | P69: Tags | Q69: 5 | R69: embedding | S69: 300m
A70: https://ollama.com/library/minimax-m2 | B70: minimax-m2 | D70: Minimax | G70: =VLOOKUP(B70,'LLM Stats list of Model'!C$2:I1001,7,FALSE) -> #N/A | H70: =VLOOKUP(B70,'LLM Stats list of Model'!C$2:I1001,2,FALSE) -> #N/A | I70: =VLOOKUP(F70,'LLM Stats list of Model'!B$2:I1001,8,FALSE) -> #N/A | J70: =VLOOKUP(F70,'LLM Stats list of Model'!B$2:I1001,3,FALSE) -> #N/A | K70: =IF(ISNA(G70),I70,G70) -> #N/A | L70: =IF(ISNA(H70),J70,H70) -> #N/A | M70: MiniMax M2 is a high-efficiency large language model built for coding and agentic workflows. | N70: 216.3K | O70: 6 months ago | P70: Tag | Q70: 1 | R70: tools
A71: https://ollama.com/library/gpt-oss-safeguard | B71: gpt-oss-safeguard | F71: https://github.com/openai/gpt-oss-safeguard | G71: =VLOOKUP(B71,'LLM Stats list of Model'!C$2:I1001,7,FALSE) -> #N/A | H71: =VLOOKUP(B71,'LLM Stats list of Model'!C$2:I1001,2,FALSE) -> #N/A | I71: =VLOOKUP(F71,'LLM Stats list of Model'!B$2:I1001,8,FALSE) -> #N/A | J71: =VLOOKUP(F71,'LLM Stats list of Model'!B$2:I1001,3,FALSE) -> #N/A | K71: =IF(ISNA(G71),I71,G71) -> #N/A | L71: =IF(ISNA(H71),J71,H71) -> #N/A | M71: gpt-oss-safeguard-20b and gpt-oss-safeguard-120b are safety reasoning models built-upon gpt-oss | N71: 137.9K | O71: 6 months ago | P71: Tags | Q71: 3 | R71: tools | S71: 20b | T71: 120b
A72: https://ollama.com/library/llama3.2 | B72: llama3.2 | G72: =VLOOKUP(B72,'LLM Stats list of Model'!C$2:I1001,7,FALSE) -> #N/A | H72: =VLOOKUP(B72,'LLM Stats list of Model'!C$2:I1001,2,FALSE) -> #N/A | I72: =VLOOKUP(F72,'LLM Stats list of Model'!B$2:I1001,8,FALSE) -> #N/A | J72: =VLOOKUP(F72,'LLM Stats list of Model'!B$2:I1001,3,FALSE) -> #N/A | K72: =IF(ISNA(G72),I72,G72) -> #N/A | L72: =IF(ISNA(H72),J72,H72) -> #N/A | M72: Meta's Llama 3.2 goes small with 1B and 3B models. | N72: 68.1M | O72: 1 year ago | P72: Tags | Q72: 63 | R72: tools | S72: 1b | T72: 3b
A73: https://ollama.com/library/nomic-embed-text | B73: nomic-embed-text | G73: =VLOOKUP(B73,'LLM Stats list of Model'!C$2:I1001,7,FALSE) -> #N/A | H73: =VLOOKUP(B73,'LLM Stats list of Model'!C$2:I1001,2,FALSE) -> #N/A | I73: =VLOOKUP(F73,'LLM Stats list of Model'!B$2:I1001,8,FALSE) -> #N/A | J73: =VLOOKUP(F73,'LLM Stats list of Model'!B$2:I1001,3,FALSE) -> #N/A | K73: =IF(ISNA(G73),I73,G73) -> #N/A | L73: =IF(ISNA(H73),J73,H73) -> #N/A | M73: A high-performing open embedding model with a large token context window. | N73: 68.4M | O73: 2 years ago | P73: Tags | Q73: 3 | R73: embedding
A74: https://ollama.com/library/qwen2.5 | B74: qwen2.5 | G74: =VLOOKUP(B74,'LLM Stats list of Model'!C$2:I1001,7,FALSE) -> #N/A | H74: =VLOOKUP(B74,'LLM Stats list of Model'!C$2:I1001,2,FALSE) -> #N/A | I74: =VLOOKUP(F74,'LLM Stats list of Model'!B$2:I1001,8,FALSE) -> #N/A | J74: =VLOOKUP(F74,'LLM Stats list of Model'!B$2:I1001,3,FALSE) -> #N/A | K74: =IF(ISNA(G74),I74,G74) -> #N/A | L74: =IF(ISNA(H74),J74,H74) -> #N/A | M74: Qwen2.5 models are pretrained on Alibaba's latest large-scale dataset, encompassing up to 18 trillion tokens. The model supports up to 128K tokens and has multilingual support. | N74: 29.3M | O74: 1 year ago | P74: Tags | Q74: 133 | R74: tools | S74: 0.5b | T74: 1.5b | U74: 3b
A75: https://ollama.com/library/gemma2 | B75: gemma2 | G75: =VLOOKUP(B75,'LLM Stats list of Model'!C$2:I1001,7,FALSE) -> #N/A | H75: =VLOOKUP(B75,'LLM Stats list of Model'!C$2:I1001,2,FALSE) -> #N/A | I75: =VLOOKUP(F75,'LLM Stats list of Model'!B$2:I1001,8,FALSE) -> #N/A | J75: =VLOOKUP(F75,'LLM Stats list of Model'!B$2:I1001,3,FALSE) -> #N/A | K75: =IF(ISNA(G75),I75,G75) -> #N/A | L75: =IF(ISNA(H75),J75,H75) -> #N/A | M75: Google Gemma 2 is a high-performing and efficient model available in three sizes: 2B, 9B, and 27B. | N75: 22.4M | O75: 1 year ago | P75: Tags | Q75: 94 | S75: 2b | T75: 9b | U75: 27b
A76: https://ollama.com/library/llama3 | B76: llama3 | G76: =VLOOKUP(B76,'LLM Stats list of Model'!C$2:I1001,7,FALSE) -> #N/A | H76: =VLOOKUP(B76,'LLM Stats list of Model'!C$2:I1001,2,FALSE) -> #N/A | I76: =VLOOKUP(F76,'LLM Stats list of Model'!B$2:I1001,8,FALSE) -> #N/A | J76: =VLOOKUP(F76,'LLM Stats list of Model'!B$2:I1001,3,FALSE) -> #N/A | K76: =IF(ISNA(G76),I76,G76) -> #N/A | L76: =IF(ISNA(H76),J76,H76) -> #N/A | M76: Meta Llama 3: The most capable openly available LLM to date | N76: 23.7M | O76: 1 year ago | P76: Tags | Q76: 68 | S76: 8b | T76: 70b
A77: https://ollama.com/library/llava | B77: llava | G77: =VLOOKUP(B77,'LLM Stats list of Model'!C$2:I1001,7,FALSE) -> #N/A | H77: =VLOOKUP(B77,'LLM Stats list of Model'!C$2:I1001,2,FALSE) -> #N/A | I77: =VLOOKUP(F77,'LLM Stats list of Model'!B$2:I1001,8,FALSE) -> #N/A | J77: =VLOOKUP(F77,'LLM Stats list of Model'!B$2:I1001,3,FALSE) -> #N/A | K77: =IF(ISNA(G77),I77,G77) -> #N/A | L77: =IF(ISNA(H77),J77,H77) -> #N/A | M77: 🌋 LLaVA is a novel end-to-end trained large multimodal model that combines a vision encoder and Vicuna for general-purpose visual and language understanding. Updated to version 1.6. | N77: 14M | O77: 2 years ago | P77: Tags | Q77: 98 | R77: vision | S77: 7b | T77: 13b | U77: 34b
A78: https://ollama.com/library/mxbai-embed-large | B78: mxbai-embed-large | G78: =VLOOKUP(B78,'LLM Stats list of Model'!C$2:I1001,7,FALSE) -> #N/A | H78: =VLOOKUP(B78,'LLM Stats list of Model'!C$2:I1001,2,FALSE) -> #N/A | I78: =VLOOKUP(F78,'LLM Stats list of Model'!B$2:I1001,8,FALSE) -> #N/A | J78: =VLOOKUP(F78,'LLM Stats list of Model'!B$2:I1001,3,FALSE) -> #N/A | K78: =IF(ISNA(G78),I78,G78) -> #N/A | L78: =IF(ISNA(H78),J78,H78) -> #N/A | M78: State-of-the-art large embedding model from mixedbread.ai | N78: 10.3M | O78: 1 year ago | P78: Tags | Q78: 4 | R78: embedding | S78: 335m
A79: https://ollama.com/library/dolphin3 | B79: dolphin3 | F79: https://huggingface.co/dphn | G79: =VLOOKUP(B79,'LLM Stats list of Model'!C$2:I1001,7,FALSE) -> #N/A | H79: =VLOOKUP(B79,'LLM Stats list of Model'!C$2:I1001,2,FALSE) -> #N/A | I79: =VLOOKUP(F79,'LLM Stats list of Model'!B$2:I1001,8,FALSE) -> #N/A | J79: =VLOOKUP(F79,'LLM Stats list of Model'!B$2:I1001,3,FALSE) -> #N/A | K79: =IF(ISNA(G79),I79,G79) -> #N/A | L79: =IF(ISNA(H79),J79,H79) -> #N/A | M79: Dolphin 3.0 Llama 3.1 8B 🐬 is the next generation of the Dolphin series of instruct-tuned models designed to be the ultimate general purpose local model, enabling coding, math, agentic, function calling, and general use cases. | N79: 3.8M | O79: 1 year ago | P79: Tags | Q79: 5 | S79: 8b
A80: https://ollama.com/library/olmo2 | B80: olmo2 | D80: AllenAI | G80: =VLOOKUP(B80,'LLM Stats list of Model'!C$2:I1001,7,FALSE) -> #N/A | H80: =VLOOKUP(B80,'LLM Stats list of Model'!C$2:I1001,2,FALSE) -> #N/A | I80: =VLOOKUP(F80,'LLM Stats list of Model'!B$2:I1001,8,FALSE) -> #N/A | J80: =VLOOKUP(F80,'LLM Stats list of Model'!B$2:I1001,3,FALSE) -> #N/A | K80: =IF(ISNA(G80),I80,G80) -> #N/A | L80: =IF(ISNA(H80),J80,H80) -> #N/A | M80: OLMo 2 is a new family of 7B and 13B models trained on up to 5T tokens. These models are on par with or better than equivalently sized fully open models, and competitive with open-weight models such as Llama 3.1 on English academic benchmarks. | N80: 3.7M | O80: 1 year ago | P80: Tags | Q80: 9 | S80: 7b | T80: 13b
A81: https://ollama.com/library/minicpm-v | B81: minicpm-v | F81: https://huggingface.co/openbmb/MiniCPM-V | G81: =VLOOKUP(B81,'LLM Stats list of Model'!C$2:I1001,7,FALSE) -> #N/A | H81: =VLOOKUP(B81,'LLM Stats list of Model'!C$2:I1001,2,FALSE) -> #N/A | I81: =VLOOKUP(F81,'LLM Stats list of Model'!B$2:I1001,8,FALSE) -> #N/A | J81: =VLOOKUP(F81,'LLM Stats list of Model'!B$2:I1001,3,FALSE) -> #N/A | K81: =IF(ISNA(G81),I81,G81) -> #N/A | L81: =IF(ISNA(H81),J81,H81) -> #N/A | M81: A series of multimodal LLMs (MLLMs) designed for vision-language understanding. | N81: 5.1M | O81: 1 year ago | P81: Tags | Q81: 17 | R81: vision | S81: 8b
A82: https://ollama.com/library/qwen2 | B82: qwen2 | G82: =VLOOKUP(B82,'LLM Stats list of Model'!C$2:I1001,7,FALSE) -> #N/A | H82: =VLOOKUP(B82,'LLM Stats list of Model'!C$2:I1001,2,FALSE) -> #N/A | I82: =VLOOKUP(F82,'LLM Stats list of Model'!B$2:I1001,8,FALSE) -> #N/A | J82: =VLOOKUP(F82,'LLM Stats list of Model'!B$2:I1001,3,FALSE) -> #N/A | K82: =IF(ISNA(G82),I82,G82) -> #N/A | L82: =IF(ISNA(H82),J82,H82) -> #N/A | M82: Qwen2 is a new series of large language models from Alibaba group | N82: 5.8M | O82: 1 year ago | P82: Tags | Q82: 97 | R82: tools | S82: 0.5b | T82: 1.5b | U82: 7b
A83: https://ollama.com/library/gemma | B83: gemma | G83: =VLOOKUP(B83,'LLM Stats list of Model'!C$2:I1001,7,FALSE) -> #N/A | H83: =VLOOKUP(B83,'LLM Stats list of Model'!C$2:I1001,2,FALSE) -> #N/A | I83: =VLOOKUP(F83,'LLM Stats list of Model'!B$2:I1001,8,FALSE) -> #N/A | J83: =VLOOKUP(F83,'LLM Stats list of Model'!B$2:I1001,3,FALSE) -> #N/A | K83: =IF(ISNA(G83),I83,G83) -> #N/A | L83: =IF(ISNA(H83),J83,H83) -> #N/A | M83: Gemma is a family of lightweight, state-of-the-art open models built by Google DeepMind. Updated to version 1.1 | N83: 7M | O83: 2 years ago | P83: Tags | Q83: 102 | S83: 2b | T83: 7b
A84: https://ollama.com/library/qwen | B84: qwen | G84: =VLOOKUP(B84,'LLM Stats list of Model'!C$2:I1001,7,FALSE) -> #N/A | H84: =VLOOKUP(B84,'LLM Stats list of Model'!C$2:I1001,2,FALSE) -> #N/A | I84: =VLOOKUP(F84,'LLM Stats list of Model'!B$2:I1001,8,FALSE) -> #N/A | J84: =VLOOKUP(F84,'LLM Stats list of Model'!B$2:I1001,3,FALSE) -> #N/A | K84: =IF(ISNA(G84),I84,G84) -> #N/A | L84: =IF(ISNA(H84),J84,H84) -> #N/A | M84: Qwen 1.5 is a series of large language models by Alibaba Cloud spanning from 0.5B to 110B parameters | N84: 6.6M | O84: 2 years ago | P84: Tags | Q84: 379 | S84: 0.5b | T84: 1.8b | U84: 4b
A85: https://ollama.com/library/smollm2 | B85: smollm2 | G85: =VLOOKUP(B85,'LLM Stats list of Model'!C$2:I1001,7,FALSE) -> #N/A | H85: =VLOOKUP(B85,'LLM Stats list of Model'!C$2:I1001,2,FALSE) -> #N/A | I85: =VLOOKUP(F85,'LLM Stats list of Model'!B$2:I1001,8,FALSE) -> #N/A | J85: =VLOOKUP(F85,'LLM Stats list of Model'!B$2:I1001,3,FALSE) -> #N/A | K85: =IF(ISNA(G85),I85,G85) -> #N/A | L85: =IF(ISNA(H85),J85,H85) -> #N/A | M85: SmolLM2 is a family of compact language models available in three size: 135M, 360M, and 1.7B parameters. | N85: 3.4M | O85: 1 year ago | P85: Tags | Q85: 49 | R85: tools | S85: 135m | T85: 360m | U85: 1.7b
A86: https://ollama.com/library/mistral-nemo | B86: mistral-nemo | G86: =VLOOKUP(B86,'LLM Stats list of Model'!C$2:I1001,7,FALSE) -> #N/A | H86: =VLOOKUP(B86,'LLM Stats list of Model'!C$2:I1001,2,FALSE) -> #N/A | I86: =VLOOKUP(F86,'LLM Stats list of Model'!B$2:I1001,8,FALSE) -> #N/A | J86: =VLOOKUP(F86,'LLM Stats list of Model'!B$2:I1001,3,FALSE) -> #N/A | K86: =IF(ISNA(G86),I86,G86) -> #N/A | L86: =IF(ISNA(H86),J86,H86) -> #N/A | M86: A state-of-the-art 12B model with 128k context length, built by Mistral AI in collaboration with NVIDIA. | N86: 4.3M | O86: 9 months ago | P86: Tags | Q86: 17 | R86: tools | S86: 12b
A87: https://ollama.com/library/granite3.1-moe | B87: granite3.1-moe | G87: =VLOOKUP(B87,'LLM Stats list of Model'!C$2:I1001,7,FALSE) -> #N/A | H87: =VLOOKUP(B87,'LLM Stats list of Model'!C$2:I1001,2,FALSE) -> #N/A | I87: =VLOOKUP(F87,'LLM Stats list of Model'!B$2:I1001,8,FALSE) -> #N/A | J87: =VLOOKUP(F87,'LLM Stats list of Model'!B$2:I1001,3,FALSE) -> #N/A | K87: =IF(ISNA(G87),I87,G87) -> #N/A | L87: =IF(ISNA(H87),J87,H87) -> #N/A | M87: The IBM Granite 1B and 3B models are long-context mixture of experts (MoE) Granite models from IBM designed for low latency usage. | N87: 2.9M | O87: 1 year ago | P87: Tags | Q87: 33 | R87: tools | S87: 1b | T87: 3b
A88: https://ollama.com/library/bge-m3 | B88: bge-m3 | G88: =VLOOKUP(B88,'LLM Stats list of Model'!C$2:I1001,7,FALSE) -> #N/A | H88: =VLOOKUP(B88,'LLM Stats list of Model'!C$2:I1001,2,FALSE) -> #N/A | I88: =VLOOKUP(F88,'LLM Stats list of Model'!B$2:I1001,8,FALSE) -> #N/A | J88: =VLOOKUP(F88,'LLM Stats list of Model'!B$2:I1001,3,FALSE) -> #N/A | K88: =IF(ISNA(G88),I88,G88) -> #N/A | L88: =IF(ISNA(H88),J88,H88) -> #N/A | M88: BGE-M3 is a new model from BAAI distinguished for its versatility in Multi-Functionality, Multi-Linguality, and Multi-Granularity. | N88: 4.1M | O88: 1 year ago | P88: Tags | Q88: 3 | R88: embedding | S88: 567m
A89: https://ollama.com/library/cogito | B89: cogito | G89: =VLOOKUP(B89,'LLM Stats list of Model'!C$2:I1001,7,FALSE) -> #N/A | H89: =VLOOKUP(B89,'LLM Stats list of Model'!C$2:I1001,2,FALSE) -> #N/A | I89: =VLOOKUP(F89,'LLM Stats list of Model'!B$2:I1001,8,FALSE) -> #N/A | J89: =VLOOKUP(F89,'LLM Stats list of Model'!B$2:I1001,3,FALSE) -> #N/A | K89: =IF(ISNA(G89),I89,G89) -> #N/A | L89: =IF(ISNA(H89),J89,H89) -> #N/A | M89: Cogito v1 Preview is a family of hybrid reasoning models by Deep Cogito that outperform the best available open models of the same size, including counterparts from LLaMA, DeepSeek, and Qwen across most standard benchmarks. | N89: 2M | O89: 1 year ago | P89: Tags | Q89: 20 | R89: tools | S89: 3b | T89: 8b | U89: 14b
A90: https://ollama.com/library/falcon3 | B90: falcon3 | G90: =VLOOKUP(B90,'LLM Stats list of Model'!C$2:I1001,7,FALSE) -> #N/A | H90: =VLOOKUP(B90,'LLM Stats list of Model'!C$2:I1001,2,FALSE) -> #N/A | I90: =VLOOKUP(F90,'LLM Stats list of Model'!B$2:I1001,8,FALSE) -> #N/A | J90: =VLOOKUP(F90,'LLM Stats list of Model'!B$2:I1001,3,FALSE) -> #N/A | K90: =IF(ISNA(G90),I90,G90) -> #N/A | L90: =IF(ISNA(H90),J90,H90) -> #N/A | M90: A family of efficient AI models under 10B parameters performant in science, math, and coding through innovative training techniques. | N90: 2.6M | O90: 1 year ago | P90: Tags | Q90: 17 | S90: 1b | T90: 3b | U90: 7b
A91: https://ollama.com/library/llama2 | B91: llama2 | G91: =VLOOKUP(B91,'LLM Stats list of Model'!C$2:I1001,7,FALSE) -> #N/A | H91: =VLOOKUP(B91,'LLM Stats list of Model'!C$2:I1001,2,FALSE) -> #N/A | I91: =VLOOKUP(F91,'LLM Stats list of Model'!B$2:I1001,8,FALSE) -> #N/A | J91: =VLOOKUP(F91,'LLM Stats list of Model'!B$2:I1001,3,FALSE) -> #N/A | K91: =IF(ISNA(G91),I91,G91) -> #N/A | L91: =IF(ISNA(H91),J91,H91) -> #N/A | M91: Llama 2 is a collection of foundation language models ranging from 7B to 70B parameters. | N91: 6.8M | O91: 2 years ago | P91: Tags | Q91: 102 | S91: 7b | T91: 13b | U91: 70b
A92: https://ollama.com/library/phi4-reasoning | B92: phi4-reasoning | G92: =VLOOKUP(B92,'LLM Stats list of Model'!C$2:I1001,7,FALSE) -> #N/A | H92: =VLOOKUP(B92,'LLM Stats list of Model'!C$2:I1001,2,FALSE) -> #N/A | I92: =VLOOKUP(F92,'LLM Stats list of Model'!B$2:I1001,8,FALSE) -> #N/A | J92: =VLOOKUP(F92,'LLM Stats list of Model'!B$2:I1001,3,FALSE) -> #N/A | K92: =IF(ISNA(G92),I92,G92) -> #N/A | L92: =IF(ISNA(H92),J92,H92) -> #N/A | M92: Phi 4 reasoning and reasoning plus are 14-billion parameter open-weight reasoning models that rival much larger models on complex reasoning tasks. | N92: 1.5M | O92: 1 year ago | P92: Tags | Q92: 9 | S92: 14b
A93: https://ollama.com/library/mistral-small | B93: mistral-small | G93: =VLOOKUP(B93,'LLM Stats list of Model'!C$2:I1001,7,FALSE) -> #N/A | H93: =VLOOKUP(B93,'LLM Stats list of Model'!C$2:I1001,2,FALSE) -> #N/A | I93: =VLOOKUP(F93,'LLM Stats list of Model'!B$2:I1001,8,FALSE) -> #N/A | J93: =VLOOKUP(F93,'LLM Stats list of Model'!B$2:I1001,3,FALSE) -> #N/A | K93: =IF(ISNA(G93),I93,G93) -> #N/A | L93: =IF(ISNA(H93),J93,H93) -> #N/A | M93: Mistral Small 3 sets a new benchmark in the “small” Large Language Models category below 70B. | N93: 3M | O93: 1 year ago | P93: Tags | Q93: 21 | R93: tools | S93: 22b | T93: 24b
A94: https://ollama.com/library/llama4 | B94: llama4 | F94: https://llm-stats.com/models/llama-4-scout | G94: =VLOOKUP(B94,'LLM Stats list of Model'!C$2:I1001,7,FALSE) -> #N/A | H94: =VLOOKUP(B94,'LLM Stats list of Model'!C$2:I1001,2,FALSE) -> #N/A | I94: =VLOOKUP(F94,'LLM Stats list of Model'!B$2:I1001,8,FALSE) -> 45748 | J94: =VLOOKUP(F94,'LLM Stats list of Model'!B$2:I1001,3,FALSE) | K94: =IF(ISNA(G94),I94,G94) -> 45748 | L94: =IF(ISNA(H94),J94,H94) | M94: Meta's latest collection of multimodal models. | N94: 1.6M | O94: 10 months ago | P94: Tags | Q94: 11 | R94: vision | S94: 16x17b | T94: 128x17b
A95: https://ollama.com/library/tinyllama | B95: tinyllama | G95: =VLOOKUP(B95,'LLM Stats list of Model'!C$2:I1001,7,FALSE) -> #N/A | H95: =VLOOKUP(B95,'LLM Stats list of Model'!C$2:I1001,2,FALSE) -> #N/A | I95: =VLOOKUP(F95,'LLM Stats list of Model'!B$2:I1001,8,FALSE) -> #N/A | J95: =VLOOKUP(F95,'LLM Stats list of Model'!B$2:I1001,3,FALSE) -> #N/A | K95: =IF(ISNA(G95),I95,G95) -> #N/A | L95: =IF(ISNA(H95),J95,H95) -> #N/A | M95: The TinyLlama project is an open endeavor to train a compact 1.1B Llama model on 3 trillion tokens. | N95: 4.8M | O95: 2 years ago | P95: Tags | Q95: 36 | S95: 1.1b
A96: https://ollama.com/library/qwq | B96: qwq | G96: =VLOOKUP(B96,'LLM Stats list of Model'!C$2:I1001,7,FALSE) -> #N/A | H96: =VLOOKUP(B96,'LLM Stats list of Model'!C$2:I1001,2,FALSE) -> #N/A | I96: =VLOOKUP(F96,'LLM Stats list of Model'!B$2:I1001,8,FALSE) -> #N/A | J96: =VLOOKUP(F96,'LLM Stats list of Model'!B$2:I1001,3,FALSE) -> #N/A | K96: =IF(ISNA(G96),I96,G96) -> #N/A | L96: =IF(ISNA(H96),J96,H96) -> #N/A | M96: QwQ is the reasoning model of the Qwen series. | N96: 2.2M | O96: 1 year ago | P96: Tags | Q96: 8 | R96: tools | S96: 32b
A97: https://ollama.com/library/codellama | B97: codellama | G97: =VLOOKUP(B97,'LLM Stats list of Model'!C$2:I1001,7,FALSE) -> #N/A | H97: =VLOOKUP(B97,'LLM Stats list of Model'!C$2:I1001,2,FALSE) -> #N/A | I97: =VLOOKUP(F97,'LLM Stats list of Model'!B$2:I1001,8,FALSE) -> #N/A | J97: =VLOOKUP(F97,'LLM Stats list of Model'!B$2:I1001,3,FALSE) -> #N/A | K97: =IF(ISNA(G97),I97,G97) -> #N/A | L97: =IF(ISNA(H97),J97,H97) -> #N/A | M97: A large language model that can use text prompts to generate and discuss code. | N97: 5.5M | O97: 1 year ago | P97: Tags | Q97: 199 | S97: 7b | T97: 13b | U97: 34b
